[{"context": "NEW_SUBSCRIBED_EPISODE", "id": 43480225, "time": "2018-06-20T01:09:46Z", "content": {"id": "413442970244", "title": "19.June 2018 - \u062f\u06a9\u062a\u0631 \u0647\u0644\u0627\u06a9\u0648\u06cc\u06cc , \u0631\u0627\u0632\u0647\u0627 \u0648 \u0646\u06cc\u0627\u0632\u0647\u0627, \u0639\u0635\u0631", "pub_date": "2018-06-20T01:09:46Z", "summary": "19.June 2018 - \u062f\u06a9\u062a\u0631 \u0647\u0644\u0627\u06a9\u0648\u06cc\u06cc , \u0631\u0627\u0632\u0647\u0627 \u0648 \u0646\u06cc\u0627\u0632\u0647\u0627, \u0639\u0635\u0631", "is_recommended": false, "recommendations_count": 0, "series": {"title": "Razha va Niazha", "id": 82316448, "image_url_sm": "https://cdn1.player.fm/images/1027679/series/n237MsJ0HGRntqQU/64.png", "image_url_lg": "https://cdn1.player.fm/images/1027679/series/n237MsJ0HGRntqQU/256.png"}, "duration": "1:59:05", "tags": "", "audio_url": "http://feeds.soundcloud.com/stream/460717641-razhavaniazha-com-19-06-2018-r-e.mp3", "current_progress": 0.0, "real_duration_written": false}, "context_supplier": {"id": 82316448, "title": "Razha va Niazha", "image_url_sm": "https://cdn1.player.fm/images/1027679/series/n237MsJ0HGRntqQU/64.png", "image_url_lg": "https://cdn1.player.fm/images/1027679/series/n237MsJ0HGRntqQU/256.png", "las_updated": "2018-06-20T01:09:46Z", "author": "me", "is_subscribed": false, "subscribers_count": 0, "genres": "culture"}}, {"context": "NEW_SUBSCRIBED_EPISODE", "id": 55083712, "time": "2018-06-19T21:53:58Z", "content": {"id": "417521269484", "title": "Toranj-20-06-2018 Zange Salamat", "pub_date": "2018-06-19T21:53:58Z", "summary": "Toranj-20-06-2018 Zange Salamat", "is_recommended": false, "recommendations_count": 0, "series": {"title": "Toranj", "id": 60154034, "image_url_sm": "https://cdn1.player.fm/images/16403860/series/eGg5OFKoNQoVZSLO/64.png", "image_url_lg": "https://cdn1.player.fm/images/16403860/series/eGg5OFKoNQoVZSLO/256.png"}, "duration": "24:38", "tags": "", "audio_url": "https://static.accessradio.org/StationFolder/plainsfm/Toranj%2020%20June.mp3", "current_progress": 0.0, "real_duration_written": false}, "context_supplier": {"id": 60154034, "title": "Toranj", "image_url_sm": "https://cdn1.player.fm/images/16403860/series/eGg5OFKoNQoVZSLO/64.png", "image_url_lg": "https://cdn1.player.fm/images/16403860/series/eGg5OFKoNQoVZSLO/256.png", "las_updated": "2018-06-19T21:53:58Z", "author": "me", "is_subscribed": false, "subscribers_count": 0, "genres": "culture"}}, {"context": "NEW_SUBSCRIBED_EPISODE", "id": 5608190, "time": "2018-06-19T19:08:48Z", "content": {"id": "784093240634", "title": "19.June 2018 - \u062f\u06a9\u062a\u0631 \u0647\u0644\u0627\u06a9\u0648\u06cc\u06cc , \u0631\u0627\u0632\u0647\u0627 \u0648 \u0646\u06cc\u0627\u0632\u0647\u0627, \u0635\u0628\u062d", "pub_date": "2018-06-19T19:08:48Z", "summary": "19.June 2018 - \u062f\u06a9\u062a\u0631 \u0647\u0644\u0627\u06a9\u0648\u06cc\u06cc , \u0631\u0627\u0632\u0647\u0627 \u0648 \u0646\u06cc\u0627\u0632\u0647\u0627, \u0635\u0628\u062d", "is_recommended": false, "recommendations_count": 0, "series": {"title": "Razha va Niazha", "id": 82316448, "image_url_sm": "https://cdn1.player.fm/images/1027679/series/n237MsJ0HGRntqQU/64.png", "image_url_lg": "https://cdn1.player.fm/images/1027679/series/n237MsJ0HGRntqQU/256.png"}, "duration": "21:09", "tags": "", "audio_url": "http://feeds.soundcloud.com/stream/460568337-razhavaniazha-com-19-06-2018-r-m.mp3", "current_progress": 0.0, "real_duration_written": false}, "context_supplier": {"id": 82316448, "title": "Razha va Niazha", "image_url_sm": "https://cdn1.player.fm/images/1027679/series/n237MsJ0HGRntqQU/64.png", "image_url_lg": "https://cdn1.player.fm/images/1027679/series/n237MsJ0HGRntqQU/256.png", "las_updated": "2018-06-19T19:08:48Z", "author": "me", "is_subscribed": false, "subscribers_count": 0, "genres": "culture"}}, {"context": "NEW_SUBSCRIBED_EPISODE", "id": 31961559, "time": "2018-06-19T04:00:00Z", "content": {"id": "302438619757", "title": "Khodcast (S2 E10 P1 - The Power of Sleep)", "pub_date": "2018-06-19T04:00:00Z", "summary": "Khodcast (S2 E10 P1 - The Power of Sleep)", "is_recommended": false, "recommendations_count": 0, "series": {"title": "Radio Javan Podcasts", "id": 2912296, "image_url_sm": "https://cdn1.player.fm/images/2210354/series/CP2HKKvW3oif9lC1/64.jpg", "image_url_lg": "https://cdn1.player.fm/images/2210354/series/CP2HKKvW3oif9lC1/256.jpg"}, "duration": "", "tags": "", "audio_url": "https://host2.rjmusicmedia.com/media/podcast/mp3-192/Khodcast-2-10-1.mp3", "current_progress": 0.0, "real_duration_written": false}, "context_supplier": {"id": 2912296, "title": "Radio Javan Podcasts", "image_url_sm": "https://cdn1.player.fm/images/2210354/series/CP2HKKvW3oif9lC1/64.jpg", "image_url_lg": "https://cdn1.player.fm/images/2210354/series/CP2HKKvW3oif9lC1/256.jpg", "las_updated": "2018-06-19T04:00:00Z", "author": "me", "is_subscribed": false, "subscribers_count": 0, "genres": "culture"}}, {"context": "NEW_SUBSCRIBED_EPISODE", "id": 32481821, "time": "2018-06-18T19:09:11Z", "content": {"id": "108649636947", "title": "18.June 2018 - \u062f\u06a9\u062a\u0631 \u0647\u0644\u0627\u06a9\u0648\u06cc\u06cc , \u0631\u0627\u0632\u0647\u0627 \u0648 \u0646\u06cc\u0627\u0632\u0647\u0627, \u0635\u0628\u062d", "pub_date": "2018-06-18T19:09:11Z", "summary": "18.June 2018 - \u062f\u06a9\u062a\u0631 \u0647\u0644\u0627\u06a9\u0648\u06cc\u06cc , \u0631\u0627\u0632\u0647\u0627 \u0648 \u0646\u06cc\u0627\u0632\u0647\u0627, \u0635\u0628\u062d", "is_recommended": false, "recommendations_count": 0, "series": {"title": "Razha va Niazha", "id": 82316448, "image_url_sm": "https://cdn1.player.fm/images/1027679/series/n237MsJ0HGRntqQU/64.png", "image_url_lg": "https://cdn1.player.fm/images/1027679/series/n237MsJ0HGRntqQU/256.png"}, "duration": "1:59:06", "tags": "", "audio_url": "http://feeds.soundcloud.com/stream/460086636-razhavaniazha-com-18-06-2018-r-m.mp3", "current_progress": 0.0, "real_duration_written": false}, "context_supplier": {"id": 82316448, "title": "Razha va Niazha", "image_url_sm": "https://cdn1.player.fm/images/1027679/series/n237MsJ0HGRntqQU/64.png", "image_url_lg": "https://cdn1.player.fm/images/1027679/series/n237MsJ0HGRntqQU/256.png", "las_updated": "2018-06-18T19:09:11Z", "author": "me", "is_subscribed": false, "subscribers_count": 0, "genres": "culture"}}, {"context": "NEW_SUBSCRIBED_EPISODE", "id": 6951303, "time": "2018-06-18T16:06:37Z", "content": {"id": "609307975467", "title": "Ganje Hozour audio Program #715_1", "pub_date": "2018-06-18T16:06:37Z", "summary": "Ganje Hozour audio Program #715_1", "is_recommended": false, "recommendations_count": 0, "series": {"title": "Ganj e Hozour Telephone messages", "id": 48625885, "image_url_sm": "https://cdn1.player.fm/images/20704450/series/oqhLxVnLgMe9ue2N/64.jpg", "image_url_lg": "https://cdn1.player.fm/images/20704450/series/oqhLxVnLgMe9ue2N/256.jpg"}, "duration": "", "tags": "", "audio_url": "http://www.parvizshahbazi.com/Audio/715-1_Webaudio.m4a", "current_progress": 0.0, "real_duration_written": false}, "context_supplier": {"id": 48625885, "title": "Ganj e Hozour Telephone messages", "image_url_sm": "https://cdn1.player.fm/images/20704450/series/oqhLxVnLgMe9ue2N/64.jpg", "image_url_lg": "https://cdn1.player.fm/images/20704450/series/oqhLxVnLgMe9ue2N/256.jpg", "las_updated": "2018-06-18T16:06:37Z", "author": "me", "is_subscribed": false, "subscribers_count": 0, "genres": "culture"}}, {"context": "NEW_SUBSCRIBED_EPISODE", "id": 49878692, "time": "2018-06-16T01:09:47Z", "content": {"id": "206421256066", "title": "15.June 2018 - \u062f\u06a9\u062a\u0631 \u0647\u0644\u0627\u06a9\u0648\u06cc\u06cc , \u0631\u0627\u0632\u0647\u0627 \u0648 \u0646\u06cc\u0627\u0632\u0647\u0627, \u0639\u0635\u0631", "pub_date": "2018-06-16T01:09:47Z", "summary": "15.June 2018 - \u062f\u06a9\u062a\u0631 \u0647\u0644\u0627\u06a9\u0648\u06cc\u06cc , \u0631\u0627\u0632\u0647\u0627 \u0648 \u0646\u06cc\u0627\u0632\u0647\u0627, \u0639\u0635\u0631", "is_recommended": false, "recommendations_count": 0, "series": {"title": "Razha va Niazha", "id": 82316448, "image_url_sm": "https://cdn1.player.fm/images/1027679/series/n237MsJ0HGRntqQU/64.png", "image_url_lg": "https://cdn1.player.fm/images/1027679/series/n237MsJ0HGRntqQU/256.png"}, "duration": "2:05:05", "tags": "", "audio_url": "http://feeds.soundcloud.com/stream/459036855-razhavaniazha-com-15-06-2018-r-e.mp3", "current_progress": 0.0, "real_duration_written": false}, "context_supplier": {"id": 82316448, "title": "Razha va Niazha", "image_url_sm": "https://cdn1.player.fm/images/1027679/series/n237MsJ0HGRntqQU/64.png", "image_url_lg": "https://cdn1.player.fm/images/1027679/series/n237MsJ0HGRntqQU/256.png", "las_updated": "2018-06-16T01:09:47Z", "author": "me", "is_subscribed": false, "subscribers_count": 0, "genres": "culture"}}, {"context": "NEW_SUBSCRIBED_EPISODE", "id": 37462944, "time": "2018-06-15T20:51:09Z", "content": {"id": "210526712232", "title": "13.June 2018 - \u062f\u06a9\u062a\u0631 \u0647\u0644\u0627\u06a9\u0648\u0626\u06cc \u0647\u0645\u0631\u0627\u0647 \u0628\u0627 \u0639\u0644\u06cc\u0631\u0636\u0627 \u0645\u06cc\u0628\u062f\u06cc", "pub_date": "2018-06-15T20:51:09Z", "summary": "13.June 2018 - \u062f\u06a9\u062a\u0631 \u0647\u0644\u0627\u06a9\u0648\u0626\u06cc \u0647\u0645\u0631\u0627\u0647 \u0628\u0627 \u0639\u0644\u06cc\u0631\u0636\u0627 \u0645\u06cc\u0628\u062f\u06cc", "is_recommended": false, "recommendations_count": 0, "series": {"title": "Razha va Niazha", "id": 82316448, "image_url_sm": "https://cdn1.player.fm/images/1027679/series/n237MsJ0HGRntqQU/64.png", "image_url_lg": "https://cdn1.player.fm/images/1027679/series/n237MsJ0HGRntqQU/256.png"}, "duration": "36:34", "tags": "", "audio_url": "http://feeds.soundcloud.com/stream/458950524-razhavaniazha-com-13-06-2018-h-m.mp3", "current_progress": 0.0, "real_duration_written": false}, "context_supplier": {"id": 82316448, "title": "Razha va Niazha", "image_url_sm": "https://cdn1.player.fm/images/1027679/series/n237MsJ0HGRntqQU/64.png", "image_url_lg": "https://cdn1.player.fm/images/1027679/series/n237MsJ0HGRntqQU/256.png", "las_updated": "2018-06-15T20:51:09Z", "author": "me", "is_subscribed": false, "subscribers_count": 0, "genres": "culture"}}, {"context": "NEW_SUBSCRIBED_EPISODE", "id": 29883738, "time": "2018-06-15T19:09:10Z", "content": {"id": "889966327981", "title": "15.June 2018 - \u062f\u06a9\u062a\u0631 \u0647\u0644\u0627\u06a9\u0648\u06cc\u06cc , \u0631\u0627\u0632\u0647\u0627 \u0648 \u0646\u06cc\u0627\u0632\u0647\u0627, \u0635\u0628\u062d", "pub_date": "2018-06-15T19:09:10Z", "summary": "15.June 2018 - \u062f\u06a9\u062a\u0631 \u0647\u0644\u0627\u06a9\u0648\u06cc\u06cc , \u0631\u0627\u0632\u0647\u0627 \u0648 \u0646\u06cc\u0627\u0632\u0647\u0627, \u0635\u0628\u062d", "is_recommended": false, "recommendations_count": 0, "series": {"title": "Razha va Niazha", "id": 82316448, "image_url_sm": "https://cdn1.player.fm/images/1027679/series/n237MsJ0HGRntqQU/64.png", "image_url_lg": "https://cdn1.player.fm/images/1027679/series/n237MsJ0HGRntqQU/256.png"}, "duration": "1:33:32", "tags": "", "audio_url": "http://feeds.soundcloud.com/stream/458906136-razhavaniazha-com-15-06-2018-r-m.mp3", "current_progress": 0.0, "real_duration_written": false}, "context_supplier": {"id": 82316448, "title": "Razha va Niazha", "image_url_sm": "https://cdn1.player.fm/images/1027679/series/n237MsJ0HGRntqQU/64.png", "image_url_lg": "https://cdn1.player.fm/images/1027679/series/n237MsJ0HGRntqQU/256.png", "las_updated": "2018-06-15T19:09:10Z", "author": "me", "is_subscribed": false, "subscribers_count": 0, "genres": "culture"}}, {"context": "NEW_SUBSCRIBED_EPISODE", "id": 4401074, "time": "2018-06-15T16:49:46Z", "content": {"id": "822461910139", "title": "Radio Rumi Program 6: Don't let Your Habitat be your Prison:  Albert Einstein and Rumi", "pub_date": "2018-06-15T16:49:46Z", "summary": "Radio Rumi Program 6: Don't let Your Habitat be your Prison:  Albert Einstein and Rumi", "is_recommended": false, "recommendations_count": 0, "series": {"title": "Radio Rumi", "id": 65960378, "image_url_sm": "https://cdn1.player.fm/images/20670553/series/rXlS8PmQMG0mEs6B/64.jpg", "image_url_lg": "https://cdn1.player.fm/images/20670553/series/rXlS8PmQMG0mEs6B/256.jpg"}, "duration": "35:23", "tags": "", "audio_url": "http://api.spreaker.com/download/episode/15057258/program6_finished.mp3", "current_progress": 0.0, "real_duration_written": false}, "context_supplier": {"id": 65960378, "title": "Radio Rumi", "image_url_sm": "https://cdn1.player.fm/images/20670553/series/rXlS8PmQMG0mEs6B/64.jpg", "image_url_lg": "https://cdn1.player.fm/images/20670553/series/rXlS8PmQMG0mEs6B/256.jpg", "las_updated": "2018-06-15T16:49:46Z", "author": "me", "is_subscribed": false, "subscribers_count": 0, "genres": "culture"}}, {"context": "NEW_SUBSCRIBED_EPISODE", "id": 1561480, "time": "2018-06-15T04:00:00Z", "content": {"id": "25911299924", "title": "Dubways (Episode 93)", "pub_date": "2018-06-15T04:00:00Z", "summary": "Dubways (Episode 93)", "is_recommended": false, "recommendations_count": 0, "series": {"title": "Radio Javan Podcasts", "id": 2912296, "image_url_sm": "https://cdn1.player.fm/images/2210354/series/CP2HKKvW3oif9lC1/64.jpg", "image_url_lg": "https://cdn1.player.fm/images/2210354/series/CP2HKKvW3oif9lC1/256.jpg"}, "duration": "", "tags": "", "audio_url": "https://host2.rjmusicmedia.com/media/podcast/mp3-192/Dubways-93.mp3", "current_progress": 0.0, "real_duration_written": false}, "context_supplier": {"id": 2912296, "title": "Radio Javan Podcasts", "image_url_sm": "https://cdn1.player.fm/images/2210354/series/CP2HKKvW3oif9lC1/64.jpg", "image_url_lg": "https://cdn1.player.fm/images/2210354/series/CP2HKKvW3oif9lC1/256.jpg", "las_updated": "2018-06-15T04:00:00Z", "author": "me", "is_subscribed": false, "subscribers_count": 0, "genres": "culture"}}, {"context": "NEW_SUBSCRIBED_EPISODE", "id": 36441672, "time": "2018-06-15T01:09:45Z", "content": {"id": "660316274079", "title": "14.June 2018 - \u062f\u06a9\u062a\u0631 \u0647\u0644\u0627\u06a9\u0648\u06cc\u06cc , \u0631\u0627\u0632\u0647\u0627 \u0648 \u0646\u06cc\u0627\u0632\u0647\u0627, \u0639\u0635\u0631", "pub_date": "2018-06-15T01:09:45Z", "summary": "14.June 2018 - \u062f\u06a9\u062a\u0631 \u0647\u0644\u0627\u06a9\u0648\u06cc\u06cc , \u0631\u0627\u0632\u0647\u0627 \u0648 \u0646\u06cc\u0627\u0632\u0647\u0627, \u0639\u0635\u0631", "is_recommended": false, "recommendations_count": 0, "series": {"title": "Razha va Niazha", "id": 82316448, "image_url_sm": "https://cdn1.player.fm/images/1027679/series/n237MsJ0HGRntqQU/64.png", "image_url_lg": "https://cdn1.player.fm/images/1027679/series/n237MsJ0HGRntqQU/256.png"}, "duration": "1:51:14", "tags": "", "audio_url": "http://feeds.soundcloud.com/stream/458553906-razhavaniazha-com-14-06-2018-r-e.mp3", "current_progress": 0.0, "real_duration_written": false}, "context_supplier": {"id": 82316448, "title": "Razha va Niazha", "image_url_sm": "https://cdn1.player.fm/images/1027679/series/n237MsJ0HGRntqQU/64.png", "image_url_lg": "https://cdn1.player.fm/images/1027679/series/n237MsJ0HGRntqQU/256.png", "las_updated": "2018-06-15T01:09:45Z", "author": "me", "is_subscribed": false, "subscribers_count": 0, "genres": "culture"}}, {"context": "NEW_SUBSCRIBED_EPISODE", "id": 72577275, "time": "2018-06-14T19:09:10Z", "content": {"id": "806559440473", "title": "14.June 2018 - \u062f\u06a9\u062a\u0631 \u0647\u0644\u0627\u06a9\u0648\u06cc\u06cc , \u0631\u0627\u0632\u0647\u0627 \u0648 \u0646\u06cc\u0627\u0632\u0647\u0627, \u0635\u0628\u062d", "pub_date": "2018-06-14T19:09:10Z", "summary": "14.June 2018 - \u062f\u06a9\u062a\u0631 \u0647\u0644\u0627\u06a9\u0648\u06cc\u06cc , \u0631\u0627\u0632\u0647\u0627 \u0648 \u0646\u06cc\u0627\u0632\u0647\u0627, \u0635\u0628\u062d", "is_recommended": false, "recommendations_count": 0, "series": {"title": "Razha va Niazha", "id": 82316448, "image_url_sm": "https://cdn1.player.fm/images/1027679/series/n237MsJ0HGRntqQU/64.png", "image_url_lg": "https://cdn1.player.fm/images/1027679/series/n237MsJ0HGRntqQU/256.png"}, "duration": "1:55:07", "tags": "", "audio_url": "http://feeds.soundcloud.com/stream/458407077-razhavaniazha-com-14-06-2018-r-m.mp3", "current_progress": 0.0, "real_duration_written": false}, "context_supplier": {"id": 82316448, "title": "Razha va Niazha", "image_url_sm": "https://cdn1.player.fm/images/1027679/series/n237MsJ0HGRntqQU/64.png", "image_url_lg": "https://cdn1.player.fm/images/1027679/series/n237MsJ0HGRntqQU/256.png", "las_updated": "2018-06-14T19:09:10Z", "author": "me", "is_subscribed": false, "subscribers_count": 0, "genres": "culture"}}, {"context": "NEW_SUBSCRIBED_EPISODE", "id": 17637992, "time": "2018-06-14T04:00:00Z", "content": {"id": "793038837019", "title": "Khodcast (S2 E9 P2 - Accent)", "pub_date": "2018-06-14T04:00:00Z", "summary": "Khodcast (S2 E9 P2 - Accent)", "is_recommended": false, "recommendations_count": 0, "series": {"title": "Radio Javan Podcasts", "id": 2912296, "image_url_sm": "https://cdn1.player.fm/images/2210354/series/CP2HKKvW3oif9lC1/64.jpg", "image_url_lg": "https://cdn1.player.fm/images/2210354/series/CP2HKKvW3oif9lC1/256.jpg"}, "duration": "", "tags": "", "audio_url": "https://host2.rjmusicmedia.com/media/podcast/mp3-192/Khodcast-2-9-2.mp3", "current_progress": 0.0, "real_duration_written": false}, "context_supplier": {"id": 2912296, "title": "Radio Javan Podcasts", "image_url_sm": "https://cdn1.player.fm/images/2210354/series/CP2HKKvW3oif9lC1/64.jpg", "image_url_lg": "https://cdn1.player.fm/images/2210354/series/CP2HKKvW3oif9lC1/256.jpg", "las_updated": "2018-06-14T04:00:00Z", "author": "me", "is_subscribed": false, "subscribers_count": 0, "genres": "culture"}}, {"context": "NEW_SUBSCRIBED_EPISODE", "id": 35886882, "time": "2018-06-14T04:00:00Z", "content": {"id": "230437653947", "title": "Majoon (Episode 3 (World Cup Special))", "pub_date": "2018-06-14T04:00:00Z", "summary": "Majoon (Episode 3 (World Cup Special))", "is_recommended": false, "recommendations_count": 0, "series": {"title": "Radio Javan Podcasts", "id": 2912296, "image_url_sm": "https://cdn1.player.fm/images/2210354/series/CP2HKKvW3oif9lC1/64.jpg", "image_url_lg": "https://cdn1.player.fm/images/2210354/series/CP2HKKvW3oif9lC1/256.jpg"}, "duration": "", "tags": "", "audio_url": "https://host2.rjmusicmedia.com/media/podcast/mp3-192/Majoon-3.mp3", "current_progress": 0.0, "real_duration_written": false}, "context_supplier": {"id": 2912296, "title": "Radio Javan Podcasts", "image_url_sm": "https://cdn1.player.fm/images/2210354/series/CP2HKKvW3oif9lC1/64.jpg", "image_url_lg": "https://cdn1.player.fm/images/2210354/series/CP2HKKvW3oif9lC1/256.jpg", "las_updated": "2018-06-14T04:00:00Z", "author": "me", "is_subscribed": false, "subscribers_count": 0, "genres": "culture"}}, {"context": "NEW_SUBSCRIBED_EPISODE", "id": 71986468, "time": "2018-06-14T01:09:44Z", "content": {"id": "307322349600", "title": "13.June 2018 - \u062f\u06a9\u062a\u0631 \u0647\u0644\u0627\u06a9\u0648\u06cc\u06cc , \u0631\u0627\u0632\u0647\u0627 \u0648 \u0646\u06cc\u0627\u0632\u0647\u0627, \u0639\u0635\u0631", "pub_date": "2018-06-14T01:09:44Z", "summary": "13.June 2018 - \u062f\u06a9\u062a\u0631 \u0647\u0644\u0627\u06a9\u0648\u06cc\u06cc , \u0631\u0627\u0632\u0647\u0627 \u0648 \u0646\u06cc\u0627\u0632\u0647\u0627, \u0639\u0635\u0631", "is_recommended": false, "recommendations_count": 0, "series": {"title": "Razha va Niazha", "id": 82316448, "image_url_sm": "https://cdn1.player.fm/images/1027679/series/n237MsJ0HGRntqQU/64.png", "image_url_lg": "https://cdn1.player.fm/images/1027679/series/n237MsJ0HGRntqQU/256.png"}, "duration": "1:59:06", "tags": "", "audio_url": "http://feeds.soundcloud.com/stream/458060286-razhavaniazha-com-13-06-2018-r-e.mp3", "current_progress": 0.0, "real_duration_written": false}, "context_supplier": {"id": 82316448, "title": "Razha va Niazha", "image_url_sm": "https://cdn1.player.fm/images/1027679/series/n237MsJ0HGRntqQU/64.png", "image_url_lg": "https://cdn1.player.fm/images/1027679/series/n237MsJ0HGRntqQU/256.png", "las_updated": "2018-06-14T01:09:44Z", "author": "me", "is_subscribed": false, "subscribers_count": 0, "genres": "culture"}}, {"context": "NEW_SUBSCRIBED_EPISODE", "id": 11627204, "time": "2018-06-13T19:09:09Z", "content": {"id": "955067126141", "title": "13.June 2018 - \u062f\u06a9\u062a\u0631 \u0647\u0644\u0627\u06a9\u0648\u06cc\u06cc , \u0631\u0627\u0632\u0647\u0627 \u0648 \u0646\u06cc\u0627\u0632\u0647\u0627, \u0635\u0628\u062d", "pub_date": "2018-06-13T19:09:09Z", "summary": "13.June 2018 - \u062f\u06a9\u062a\u0631 \u0647\u0644\u0627\u06a9\u0648\u06cc\u06cc , \u0631\u0627\u0632\u0647\u0627 \u0648 \u0646\u06cc\u0627\u0632\u0647\u0627, \u0635\u0628\u062d", "is_recommended": false, "recommendations_count": 0, "series": {"title": "Razha va Niazha", "id": 82316448, "image_url_sm": "https://cdn1.player.fm/images/1027679/series/n237MsJ0HGRntqQU/64.png", "image_url_lg": "https://cdn1.player.fm/images/1027679/series/n237MsJ0HGRntqQU/256.png"}, "duration": "1:59:05", "tags": "", "audio_url": "http://feeds.soundcloud.com/stream/457917264-razhavaniazha-com-13-06-2018-r-m.mp3", "current_progress": 0.0, "real_duration_written": false}, "context_supplier": {"id": 82316448, "title": "Razha va Niazha", "image_url_sm": "https://cdn1.player.fm/images/1027679/series/n237MsJ0HGRntqQU/64.png", "image_url_lg": "https://cdn1.player.fm/images/1027679/series/n237MsJ0HGRntqQU/256.png", "las_updated": "2018-06-13T19:09:09Z", "author": "me", "is_subscribed": false, "subscribers_count": 0, "genres": "culture"}}, {"context": "NEW_SUBSCRIBED_EPISODE", "id": 18208542, "time": "2018-06-13T01:09:45Z", "content": {"id": "237453558765", "title": "12.June 2018 - \u062f\u06a9\u062a\u0631 \u0647\u0644\u0627\u06a9\u0648\u06cc\u06cc , \u0631\u0627\u0632\u0647\u0627 \u0648 \u0646\u06cc\u0627\u0632\u0647\u0627, \u0639\u0635\u0631", "pub_date": "2018-06-13T01:09:45Z", "summary": "12.June 2018 - \u062f\u06a9\u062a\u0631 \u0647\u0644\u0627\u06a9\u0648\u06cc\u06cc , \u0631\u0627\u0632\u0647\u0627 \u0648 \u0646\u06cc\u0627\u0632\u0647\u0627, \u0639\u0635\u0631", "is_recommended": false, "recommendations_count": 0, "series": {"title": "Razha va Niazha", "id": 82316448, "image_url_sm": "https://cdn1.player.fm/images/1027679/series/n237MsJ0HGRntqQU/64.png", "image_url_lg": "https://cdn1.player.fm/images/1027679/series/n237MsJ0HGRntqQU/256.png"}, "duration": "1:59:05", "tags": "", "audio_url": "http://feeds.soundcloud.com/stream/457596000-razhavaniazha-com-12-06-2018-r-e.mp3", "current_progress": 0.0, "real_duration_written": false}, "context_supplier": {"id": 82316448, "title": "Razha va Niazha", "image_url_sm": "https://cdn1.player.fm/images/1027679/series/n237MsJ0HGRntqQU/64.png", "image_url_lg": "https://cdn1.player.fm/images/1027679/series/n237MsJ0HGRntqQU/256.png", "las_updated": "2018-06-13T01:09:45Z", "author": "me", "is_subscribed": false, "subscribers_count": 0, "genres": "culture"}}, {"context": "NEW_SUBSCRIBED_EPISODE", "id": 66463221, "time": "2018-06-12T21:36:00Z", "content": {"id": "750198601137", "title": "Toranj-13-06-2018", "pub_date": "2018-06-12T21:36:00Z", "summary": "Toranj-13-06-2018", "is_recommended": false, "recommendations_count": 0, "series": {"title": "Toranj", "id": 60154034, "image_url_sm": "https://cdn1.player.fm/images/16403860/series/eGg5OFKoNQoVZSLO/64.png", "image_url_lg": "https://cdn1.player.fm/images/16403860/series/eGg5OFKoNQoVZSLO/256.png"}, "duration": "24:38", "tags": "", "audio_url": "https://static.accessradio.org/StationFolder/plainsfm/Toranj%2013%20June.mp3", "current_progress": 0.0, "real_duration_written": false}, "context_supplier": {"id": 60154034, "title": "Toranj", "image_url_sm": "https://cdn1.player.fm/images/16403860/series/eGg5OFKoNQoVZSLO/64.png", "image_url_lg": "https://cdn1.player.fm/images/16403860/series/eGg5OFKoNQoVZSLO/256.png", "las_updated": "2018-06-12T21:36:00Z", "author": "me", "is_subscribed": false, "subscribers_count": 0, "genres": "culture"}}, {"context": "NEW_SUBSCRIBED_EPISODE", "id": 39328097, "time": "2018-06-12T19:09:11Z", "content": {"id": "847249112426", "title": "12.June 2018 - \u062f\u06a9\u062a\u0631 \u0647\u0644\u0627\u06a9\u0648\u06cc\u06cc , \u0631\u0627\u0632\u0647\u0627 \u0648 \u0646\u06cc\u0627\u0632\u0647\u0627, \u0635\u0628\u062d", "pub_date": "2018-06-12T19:09:11Z", "summary": "12.June 2018 - \u062f\u06a9\u062a\u0631 \u0647\u0644\u0627\u06a9\u0648\u06cc\u06cc , \u0631\u0627\u0632\u0647\u0627 \u0648 \u0646\u06cc\u0627\u0632\u0647\u0627, \u0635\u0628\u062d", "is_recommended": false, "recommendations_count": 0, "series": {"title": "Razha va Niazha", "id": 82316448, "image_url_sm": "https://cdn1.player.fm/images/1027679/series/n237MsJ0HGRntqQU/64.png", "image_url_lg": "https://cdn1.player.fm/images/1027679/series/n237MsJ0HGRntqQU/256.png"}, "duration": "1:59:05", "tags": "", "audio_url": "http://feeds.soundcloud.com/stream/457440624-razhavaniazha-com-12-06-2018-r-m.mp3", "current_progress": 0.0, "real_duration_written": false}, "context_supplier": {"id": 82316448, "title": "Razha va Niazha", "image_url_sm": "https://cdn1.player.fm/images/1027679/series/n237MsJ0HGRntqQU/64.png", "image_url_lg": "https://cdn1.player.fm/images/1027679/series/n237MsJ0HGRntqQU/256.png", "las_updated": "2018-06-12T19:09:11Z", "author": "me", "is_subscribed": false, "subscribers_count": 0, "genres": "culture"}}, {"context": "NEW_SUBSCRIBED_EPISODE", "id": 97408231, "time": "2018-06-12T04:00:00Z", "content": {"id": "267398361792", "title": "Khodcast (S2 E9 P1 - Forgiveness)", "pub_date": "2018-06-12T04:00:00Z", "summary": "Khodcast (S2 E9 P1 - Forgiveness)", "is_recommended": false, "recommendations_count": 0, "series": {"title": "Radio Javan Podcasts", "id": 2912296, "image_url_sm": "https://cdn1.player.fm/images/2210354/series/CP2HKKvW3oif9lC1/64.jpg", "image_url_lg": "https://cdn1.player.fm/images/2210354/series/CP2HKKvW3oif9lC1/256.jpg"}, "duration": "", "tags": "", "audio_url": "https://host2.rjmusicmedia.com/media/podcast/mp3-192/Khodcast-2-9-1.mp3", "current_progress": 0.0, "real_duration_written": false}, "context_supplier": {"id": 2912296, "title": "Radio Javan Podcasts", "image_url_sm": "https://cdn1.player.fm/images/2210354/series/CP2HKKvW3oif9lC1/64.jpg", "image_url_lg": "https://cdn1.player.fm/images/2210354/series/CP2HKKvW3oif9lC1/256.jpg", "las_updated": "2018-06-12T04:00:00Z", "author": "me", "is_subscribed": false, "subscribers_count": 0, "genres": "culture"}}, {"context": "NEW_SUBSCRIBED_EPISODE", "id": 92219039, "time": "2018-06-12T01:09:40Z", "content": {"id": "716329186297", "title": "11.June 2018 - \u062f\u06a9\u062a\u0631 \u0647\u0644\u0627\u06a9\u0648\u06cc\u06cc , \u0631\u0627\u0632\u0647\u0627 \u0648 \u0646\u06cc\u0627\u0632\u0647\u0627, \u0639\u0635\u0631", "pub_date": "2018-06-12T01:09:40Z", "summary": "11.June 2018 - \u062f\u06a9\u062a\u0631 \u0647\u0644\u0627\u06a9\u0648\u06cc\u06cc , \u0631\u0627\u0632\u0647\u0627 \u0648 \u0646\u06cc\u0627\u0632\u0647\u0627, \u0639\u0635\u0631", "is_recommended": false, "recommendations_count": 0, "series": {"title": "Razha va Niazha", "id": 82316448, "image_url_sm": "https://cdn1.player.fm/images/1027679/series/n237MsJ0HGRntqQU/64.png", "image_url_lg": "https://cdn1.player.fm/images/1027679/series/n237MsJ0HGRntqQU/256.png"}, "duration": "1:36:49", "tags": "", "audio_url": "http://feeds.soundcloud.com/stream/457108446-razhavaniazha-com-11-06-2018-r-e.mp3", "current_progress": 0.0, "real_duration_written": false}, "context_supplier": {"id": 82316448, "title": "Razha va Niazha", "image_url_sm": "https://cdn1.player.fm/images/1027679/series/n237MsJ0HGRntqQU/64.png", "image_url_lg": "https://cdn1.player.fm/images/1027679/series/n237MsJ0HGRntqQU/256.png", "las_updated": "2018-06-12T01:09:40Z", "author": "me", "is_subscribed": false, "subscribers_count": 0, "genres": "culture"}}, {"context": "NEW_SUBSCRIBED_EPISODE", "id": 942653, "time": "2018-06-11T21:34:45Z", "content": {"id": "85326031849", "title": "\u0642\u0633\u0645\u062a \u062f\u0648\u0645 \u2013 \u0627\u0642\u062a\u0635\u0627\u062f \u0633\u06cc\u0627\u0633\u06cc \u0627\u0645\u0631\u06cc\u06a9\u0627 \u0648 \u0628\u062d\u0631\u0627\u0646 \u0645\u0627\u0644\u06cc \u0633\u0627\u0644 \u06f2\u06f0\u06f0\u06f8", "pub_date": "2018-06-11T21:34:45Z", "summary": "\u0642\u0633\u0645\u062a \u062f\u0648\u0645 \u2013 \u0627\u0642\u062a\u0635\u0627\u062f \u0633\u06cc\u0627\u0633\u06cc \u0627\u0645\u0631\u06cc\u06a9\u0627 \u0648 \u0628\u062d\u0631\u0627\u0646 \u0645\u0627\u0644\u06cc \u0633\u0627\u0644 \u06f2\u06f0\u06f0\u06f8", "is_recommended": false, "recommendations_count": 0, "series": {"title": "Democracy DarKar", "id": 56057924, "image_url_sm": "https://cdn1.player.fm/images/21187874/series/ixPUL7G3Vx7KzL9s/64.jpg", "image_url_lg": "https://cdn1.player.fm/images/21187874/series/ixPUL7G3Vx7KzL9s/256.jpg"}, "duration": "1:04:05", "tags": "", "audio_url": "https://media.blubrry.com/datwfa/content.blubrry.com/datwfa/Episode_2-Political_Economy_of_US_and_2008_Crisis.mp3", "current_progress": 0.0, "real_duration_written": false}, "context_supplier": {"id": 56057924, "title": "Democracy DarKar", "image_url_sm": "https://cdn1.player.fm/images/21187874/series/ixPUL7G3Vx7KzL9s/64.jpg", "image_url_lg": "https://cdn1.player.fm/images/21187874/series/ixPUL7G3Vx7KzL9s/256.jpg", "las_updated": "2018-06-11T21:34:45Z", "author": "me", "is_subscribed": false, "subscribers_count": 0, "genres": "culture"}}, {"context": "NEW_SUBSCRIBED_EPISODE", "id": 88489511, "time": "2018-06-11T19:08:50Z", "content": {"id": "232861911828", "title": "11.June 2018 - \u062f\u06a9\u062a\u0631 \u0647\u0644\u0627\u06a9\u0648\u06cc\u06cc , \u0631\u0627\u0632\u0647\u0627 \u0648 \u0646\u06cc\u0627\u0632\u0647\u0627, \u0635\u0628\u062d", "pub_date": "2018-06-11T19:08:50Z", "summary": "11.June 2018 - \u062f\u06a9\u062a\u0631 \u0647\u0644\u0627\u06a9\u0648\u06cc\u06cc , \u0631\u0627\u0632\u0647\u0627 \u0648 \u0646\u06cc\u0627\u0632\u0647\u0627, \u0635\u0628\u062d", "is_recommended": false, "recommendations_count": 0, "series": {"title": "Razha va Niazha", "id": 82316448, "image_url_sm": "https://cdn1.player.fm/images/1027679/series/n237MsJ0HGRntqQU/64.png", "image_url_lg": "https://cdn1.player.fm/images/1027679/series/n237MsJ0HGRntqQU/256.png"}, "duration": "1:56:54", "tags": "", "audio_url": "http://feeds.soundcloud.com/stream/456951681-razhavaniazha-com-11-06-2018-r-m.mp3", "current_progress": 0.0, "real_duration_written": false}, "context_supplier": {"id": 82316448, "title": "Razha va Niazha", "image_url_sm": "https://cdn1.player.fm/images/1027679/series/n237MsJ0HGRntqQU/64.png", "image_url_lg": "https://cdn1.player.fm/images/1027679/series/n237MsJ0HGRntqQU/256.png", "las_updated": "2018-06-11T19:08:50Z", "author": "me", "is_subscribed": false, "subscribers_count": 0, "genres": "culture"}}, {"context": "NEW_SUBSCRIBED_EPISODE", "id": 89288515, "time": "2018-06-11T04:00:00Z", "content": {"id": "837858504071", "title": "RhythmOtism (Episode 7)", "pub_date": "2018-06-11T04:00:00Z", "summary": "RhythmOtism (Episode 7)", "is_recommended": false, "recommendations_count": 0, "series": {"title": "Radio Javan Podcasts", "id": 2912296, "image_url_sm": "https://cdn1.player.fm/images/2210354/series/CP2HKKvW3oif9lC1/64.jpg", "image_url_lg": "https://cdn1.player.fm/images/2210354/series/CP2HKKvW3oif9lC1/256.jpg"}, "duration": "", "tags": "", "audio_url": "https://host2.rjmusicmedia.com/media/podcast/mp3-192/RhythmOtism-7.mp3", "current_progress": 0.0, "real_duration_written": false}, "context_supplier": {"id": 2912296, "title": "Radio Javan Podcasts", "image_url_sm": "https://cdn1.player.fm/images/2210354/series/CP2HKKvW3oif9lC1/64.jpg", "image_url_lg": "https://cdn1.player.fm/images/2210354/series/CP2HKKvW3oif9lC1/256.jpg", "las_updated": "2018-06-11T04:00:00Z", "author": "me", "is_subscribed": false, "subscribers_count": 0, "genres": "culture"}}, {"context": "NEW_SUBSCRIBED_EPISODE", "id": 71381286, "time": "2018-06-10T04:00:00Z", "content": {"id": "148253461138", "title": "Bazaar (Episode 28 (80's & 90's Pop))", "pub_date": "2018-06-10T04:00:00Z", "summary": "Bazaar (Episode 28 (80's & 90's Pop))", "is_recommended": false, "recommendations_count": 0, "series": {"title": "Radio Javan Podcasts", "id": 2912296, "image_url_sm": "https://cdn1.player.fm/images/2210354/series/CP2HKKvW3oif9lC1/64.jpg", "image_url_lg": "https://cdn1.player.fm/images/2210354/series/CP2HKKvW3oif9lC1/256.jpg"}, "duration": "", "tags": "", "audio_url": "https://host2.rjmusicmedia.com/media/podcast/mp3-192/Bazaar-28.mp3", "current_progress": 0.0, "real_duration_written": false}, "context_supplier": {"id": 2912296, "title": "Radio Javan Podcasts", "image_url_sm": "https://cdn1.player.fm/images/2210354/series/CP2HKKvW3oif9lC1/64.jpg", "image_url_lg": "https://cdn1.player.fm/images/2210354/series/CP2HKKvW3oif9lC1/256.jpg", "las_updated": "2018-06-10T04:00:00Z", "author": "me", "is_subscribed": false, "subscribers_count": 0, "genres": "culture"}}, {"context": "NEW_SUBSCRIBED_EPISODE", "id": 265778, "time": "2018-06-09T01:09:45Z", "content": {"id": "128658473315", "title": "08.June 2018 - \u062f\u06a9\u062a\u0631 \u0647\u0644\u0627\u06a9\u0648\u06cc\u06cc , \u0631\u0627\u0632\u0647\u0627 \u0648 \u0646\u06cc\u0627\u0632\u0647\u0627, \u0639\u0635\u0631", "pub_date": "2018-06-09T01:09:45Z", "summary": "08.June 2018 - \u062f\u06a9\u062a\u0631 \u0647\u0644\u0627\u06a9\u0648\u06cc\u06cc , \u0631\u0627\u0632\u0647\u0627 \u0648 \u0646\u06cc\u0627\u0632\u0647\u0627, \u0639\u0635\u0631", "is_recommended": false, "recommendations_count": 0, "series": {"title": "Razha va Niazha", "id": 82316448, "image_url_sm": "https://cdn1.player.fm/images/1027679/series/n237MsJ0HGRntqQU/64.png", "image_url_lg": "https://cdn1.player.fm/images/1027679/series/n237MsJ0HGRntqQU/256.png"}, "duration": "2:05:05", "tags": "", "audio_url": "http://feeds.soundcloud.com/stream/455857185-razhavaniazha-com-08-06-2018-r-e.mp3", "current_progress": 0.0, "real_duration_written": false}, "context_supplier": {"id": 82316448, "title": "Razha va Niazha", "image_url_sm": "https://cdn1.player.fm/images/1027679/series/n237MsJ0HGRntqQU/64.png", "image_url_lg": "https://cdn1.player.fm/images/1027679/series/n237MsJ0HGRntqQU/256.png", "las_updated": "2018-06-09T01:09:45Z", "author": "me", "is_subscribed": false, "subscribers_count": 0, "genres": "culture"}}, {"context": "NEW_SUBSCRIBED_EPISODE", "id": 49050880, "time": "2018-06-08T23:47:11Z", "content": {"id": "208228301832", "title": "Ganje Hozour audio Program #714_1", "pub_date": "2018-06-08T23:47:11Z", "summary": "Ganje Hozour audio Program #714_1", "is_recommended": false, "recommendations_count": 0, "series": {"title": "Ganj e Hozour Telephone messages", "id": 48625885, "image_url_sm": "https://cdn1.player.fm/images/20704450/series/oqhLxVnLgMe9ue2N/64.jpg", "image_url_lg": "https://cdn1.player.fm/images/20704450/series/oqhLxVnLgMe9ue2N/256.jpg"}, "duration": "", "tags": "", "audio_url": "http://www.parvizshahbazi.com/Audio/714-1_Webaudio.m4a", "current_progress": 0.0, "real_duration_written": false}, "context_supplier": {"id": 48625885, "title": "Ganj e Hozour Telephone messages", "image_url_sm": "https://cdn1.player.fm/images/20704450/series/oqhLxVnLgMe9ue2N/64.jpg", "image_url_lg": "https://cdn1.player.fm/images/20704450/series/oqhLxVnLgMe9ue2N/256.jpg", "las_updated": "2018-06-08T23:47:11Z", "author": "me", "is_subscribed": false, "subscribers_count": 0, "genres": "culture"}}, {"context": "NEW_SUBSCRIBED_EPISODE", "id": 36639755, "time": "2018-06-08T19:39:08Z", "content": {"id": "479170802585", "title": "08.June 2018 - \u062f\u06a9\u062a\u0631 \u0647\u0644\u0627\u06a9\u0648\u06cc\u06cc , \u0631\u0627\u0632\u0647\u0627 \u0648 \u0646\u06cc\u0627\u0632\u0647\u0627, \u0635\u0628\u062d", "pub_date": "2018-06-08T19:39:08Z", "summary": "08.June 2018 - \u062f\u06a9\u062a\u0631 \u0647\u0644\u0627\u06a9\u0648\u06cc\u06cc , \u0631\u0627\u0632\u0647\u0627 \u0648 \u0646\u06cc\u0627\u0632\u0647\u0627, \u0635\u0628\u062d", "is_recommended": false, "recommendations_count": 0, "series": {"title": "Razha va Niazha", "id": 82316448, "image_url_sm": "https://cdn1.player.fm/images/1027679/series/n237MsJ0HGRntqQU/64.png", "image_url_lg": "https://cdn1.player.fm/images/1027679/series/n237MsJ0HGRntqQU/256.png"}, "duration": "1:30:17", "tags": "", "audio_url": "http://feeds.soundcloud.com/stream/455737470-razhavaniazha-com-08-06-2018-r-m.mp3", "current_progress": 0.0, "real_duration_written": false}, "context_supplier": {"id": 82316448, "title": "Razha va Niazha", "image_url_sm": "https://cdn1.player.fm/images/1027679/series/n237MsJ0HGRntqQU/64.png", "image_url_lg": "https://cdn1.player.fm/images/1027679/series/n237MsJ0HGRntqQU/256.png", "las_updated": "2018-06-08T19:39:08Z", "author": "me", "is_subscribed": false, "subscribers_count": 0, "genres": "culture"}}, {"context": "NEW_SUBSCRIBED_EPISODE", "id": 62562943, "time": "2018-06-08T19:13:06Z", "content": {"id": "63906651681", "title": "07.June 2018 - \u062f\u06a9\u062a\u0631 \u0647\u0644\u0627\u06a9\u0648\u06cc\u06cc , \u0631\u0627\u0632\u0647\u0627 \u0648 \u0646\u06cc\u0627\u0632\u0647\u0627, \u0639\u0635\u0631", "pub_date": "2018-06-08T19:13:06Z", "summary": "07.June 2018 - \u062f\u06a9\u062a\u0631 \u0647\u0644\u0627\u06a9\u0648\u06cc\u06cc , \u0631\u0627\u0632\u0647\u0627 \u0648 \u0646\u06cc\u0627\u0632\u0647\u0627, \u0639\u0635\u0631", "is_recommended": false, "recommendations_count": 0, "series": {"title": "Razha va Niazha", "id": 82316448, "image_url_sm": "https://cdn1.player.fm/images/1027679/series/n237MsJ0HGRntqQU/64.png", "image_url_lg": "https://cdn1.player.fm/images/1027679/series/n237MsJ0HGRntqQU/256.png"}, "duration": "1:40:47", "tags": "", "audio_url": "http://feeds.soundcloud.com/stream/455726676-razhavaniazha-com-07-06-2018-r-e0.mp3", "current_progress": 0.0, "real_duration_written": false}, "context_supplier": {"id": 82316448, "title": "Razha va Niazha", "image_url_sm": "https://cdn1.player.fm/images/1027679/series/n237MsJ0HGRntqQU/64.png", "image_url_lg": "https://cdn1.player.fm/images/1027679/series/n237MsJ0HGRntqQU/256.png", "las_updated": "2018-06-08T19:13:06Z", "author": "me", "is_subscribed": false, "subscribers_count": 0, "genres": "culture"}}, {"context": "NEW_SUBSCRIBED_EPISODE", "id": 60286939, "time": "2018-06-08T18:05:27Z", "content": {"id": "691418045901", "title": "06.June 2018 - \u062f\u06a9\u062a\u0631 \u0647\u0644\u0627\u06a9\u0648\u0626\u06cc \u0647\u0645\u0631\u0627\u0647 \u0628\u0627 \u0639\u0644\u06cc\u0631\u0636\u0627 \u0645\u06cc\u0628\u062f\u06cc", "pub_date": "2018-06-08T18:05:27Z", "summary": "06.June 2018 - \u062f\u06a9\u062a\u0631 \u0647\u0644\u0627\u06a9\u0648\u0626\u06cc \u0647\u0645\u0631\u0627\u0647 \u0628\u0627 \u0639\u0644\u06cc\u0631\u0636\u0627 \u0645\u06cc\u0628\u062f\u06cc", "is_recommended": false, "recommendations_count": 0, "series": {"title": "Razha va Niazha", "id": 82316448, "image_url_sm": "https://cdn1.player.fm/images/1027679/series/n237MsJ0HGRntqQU/64.png", "image_url_lg": "https://cdn1.player.fm/images/1027679/series/n237MsJ0HGRntqQU/256.png"}, "duration": "36:09", "tags": "", "audio_url": "http://feeds.soundcloud.com/stream/455697933-razhavaniazha-com-06-06-2018-h-m.mp3", "current_progress": 0.0, "real_duration_written": false}, "context_supplier": {"id": 82316448, "title": "Razha va Niazha", "image_url_sm": "https://cdn1.player.fm/images/1027679/series/n237MsJ0HGRntqQU/64.png", "image_url_lg": "https://cdn1.player.fm/images/1027679/series/n237MsJ0HGRntqQU/256.png", "las_updated": "2018-06-08T18:05:27Z", "author": "me", "is_subscribed": false, "subscribers_count": 0, "genres": "culture"}}, {"context": "NEW_SUBSCRIBED_EPISODE", "id": 80787099, "time": "2018-06-08T04:00:00Z", "content": {"id": "68166779661", "title": "NoodLand (Episode 3)", "pub_date": "2018-06-08T04:00:00Z", "summary": "NoodLand (Episode 3)", "is_recommended": false, "recommendations_count": 0, "series": {"title": "Radio Javan Podcasts", "id": 2912296, "image_url_sm": "https://cdn1.player.fm/images/2210354/series/CP2HKKvW3oif9lC1/64.jpg", "image_url_lg": "https://cdn1.player.fm/images/2210354/series/CP2HKKvW3oif9lC1/256.jpg"}, "duration": "", "tags": "", "audio_url": "https://host2.rjmusicmedia.com/media/podcast/mp3-192/NoodLand-3.mp3", "current_progress": 0.0, "real_duration_written": false}, "context_supplier": {"id": 2912296, "title": "Radio Javan Podcasts", "image_url_sm": "https://cdn1.player.fm/images/2210354/series/CP2HKKvW3oif9lC1/64.jpg", "image_url_lg": "https://cdn1.player.fm/images/2210354/series/CP2HKKvW3oif9lC1/256.jpg", "las_updated": "2018-06-08T04:00:00Z", "author": "me", "is_subscribed": false, "subscribers_count": 0, "genres": "culture"}}, {"context": "NEW_SUBSCRIBED_EPISODE", "id": 40252684, "time": "2018-06-07T19:09:10Z", "content": {"id": "671424103680", "title": "07.June 2018 - \u062f\u06a9\u062a\u0631 \u0647\u0644\u0627\u06a9\u0648\u06cc\u06cc , \u0631\u0627\u0632\u0647\u0627 \u0648 \u0646\u06cc\u0627\u0632\u0647\u0627, \u0635\u0628\u062d", "pub_date": "2018-06-07T19:09:10Z", "summary": "07.June 2018 - \u062f\u06a9\u062a\u0631 \u0647\u0644\u0627\u06a9\u0648\u06cc\u06cc , \u0631\u0627\u0632\u0647\u0627 \u0648 \u0646\u06cc\u0627\u0632\u0647\u0627, \u0635\u0628\u062d", "is_recommended": false, "recommendations_count": 0, "series": {"title": "Razha va Niazha", "id": 82316448, "image_url_sm": "https://cdn1.player.fm/images/1027679/series/n237MsJ0HGRntqQU/64.png", "image_url_lg": "https://cdn1.player.fm/images/1027679/series/n237MsJ0HGRntqQU/256.png"}, "duration": "1:59:05", "tags": "", "audio_url": "http://feeds.soundcloud.com/stream/455231280-razhavaniazha-com-07-06-2018-r-m.mp3", "current_progress": 0.0, "real_duration_written": false}, "context_supplier": {"id": 82316448, "title": "Razha va Niazha", "image_url_sm": "https://cdn1.player.fm/images/1027679/series/n237MsJ0HGRntqQU/64.png", "image_url_lg": "https://cdn1.player.fm/images/1027679/series/n237MsJ0HGRntqQU/256.png", "las_updated": "2018-06-07T19:09:10Z", "author": "me", "is_subscribed": false, "subscribers_count": 0, "genres": "culture"}}, {"context": "NEW_SUBSCRIBED_EPISODE", "id": 96290188, "time": "2018-06-07T11:02:14Z", "content": {"id": "852975519397", "title": "06.June 2018 - \u062f\u06a9\u062a\u0631 \u0647\u0644\u0627\u06a9\u0648\u06cc\u06cc , \u0631\u0627\u0632\u0647\u0627 \u0648 \u0646\u06cc\u0627\u0632\u0647\u0627, \u0639\u0635\u0631", "pub_date": "2018-06-07T11:02:14Z", "summary": "06.June 2018 - \u062f\u06a9\u062a\u0631 \u0647\u0644\u0627\u06a9\u0648\u06cc\u06cc , \u0631\u0627\u0632\u0647\u0627 \u0648 \u0646\u06cc\u0627\u0632\u0647\u0627, \u0639\u0635\u0631", "is_recommended": false, "recommendations_count": 0, "series": {"title": "Razha va Niazha", "id": 82316448, "image_url_sm": "https://cdn1.player.fm/images/1027679/series/n237MsJ0HGRntqQU/64.png", "image_url_lg": "https://cdn1.player.fm/images/1027679/series/n237MsJ0HGRntqQU/256.png"}, "duration": "1:59:03", "tags": "", "audio_url": "http://feeds.soundcloud.com/stream/455028390-razhavaniazha-com-06-06-2018-r-e.mp3", "current_progress": 0.0, "real_duration_written": false}, "context_supplier": {"id": 82316448, "title": "Razha va Niazha", "image_url_sm": "https://cdn1.player.fm/images/1027679/series/n237MsJ0HGRntqQU/64.png", "image_url_lg": "https://cdn1.player.fm/images/1027679/series/n237MsJ0HGRntqQU/256.png", "las_updated": "2018-06-07T11:02:14Z", "author": "me", "is_subscribed": false, "subscribers_count": 0, "genres": "culture"}}, {"context": "NEW_SUBSCRIBED_EPISODE", "id": 58818136, "time": "2018-06-07T04:00:00Z", "content": {"id": "20546980179", "title": "RJ Countdown (Jun 7, 2018)", "pub_date": "2018-06-07T04:00:00Z", "summary": "RJ Countdown (Jun 7, 2018)", "is_recommended": false, "recommendations_count": 0, "series": {"title": "Radio Javan Podcasts", "id": 2912296, "image_url_sm": "https://cdn1.player.fm/images/2210354/series/CP2HKKvW3oif9lC1/64.jpg", "image_url_lg": "https://cdn1.player.fm/images/2210354/series/CP2HKKvW3oif9lC1/256.jpg"}, "duration": "", "tags": "", "audio_url": "https://host2.rjmusicmedia.com/media/podcast/mp3-192/RJ-Countdown-20180607.mp3", "current_progress": 0.0, "real_duration_written": false}, "context_supplier": {"id": 2912296, "title": "Radio Javan Podcasts", "image_url_sm": "https://cdn1.player.fm/images/2210354/series/CP2HKKvW3oif9lC1/64.jpg", "image_url_lg": "https://cdn1.player.fm/images/2210354/series/CP2HKKvW3oif9lC1/256.jpg", "las_updated": "2018-06-07T04:00:00Z", "author": "me", "is_subscribed": false, "subscribers_count": 0, "genres": "culture"}}, {"context": "NEW_SUBSCRIBED_EPISODE", "id": 27664161, "time": "2018-06-07T04:00:00Z", "content": {"id": "734546600723", "title": "Khodcast (S2 E8 P2 - Procrastination Benefits)", "pub_date": "2018-06-07T04:00:00Z", "summary": "Khodcast (S2 E8 P2 - Procrastination Benefits)", "is_recommended": false, "recommendations_count": 0, "series": {"title": "Radio Javan Podcasts", "id": 2912296, "image_url_sm": "https://cdn1.player.fm/images/2210354/series/CP2HKKvW3oif9lC1/64.jpg", "image_url_lg": "https://cdn1.player.fm/images/2210354/series/CP2HKKvW3oif9lC1/256.jpg"}, "duration": "", "tags": "", "audio_url": "https://host2.rjmusicmedia.com/media/podcast/mp3-192/Khodcast-2-8-2.mp3", "current_progress": 0.0, "real_duration_written": false}, "context_supplier": {"id": 2912296, "title": "Radio Javan Podcasts", "image_url_sm": "https://cdn1.player.fm/images/2210354/series/CP2HKKvW3oif9lC1/64.jpg", "image_url_lg": "https://cdn1.player.fm/images/2210354/series/CP2HKKvW3oif9lC1/256.jpg", "las_updated": "2018-06-07T04:00:00Z", "author": "me", "is_subscribed": false, "subscribers_count": 0, "genres": "culture"}}, {"context": "NEW_SUBSCRIBED_EPISODE", "id": 57028269, "time": "2018-06-06T19:09:12Z", "content": {"id": "420790095424", "title": "06.June 2018 - \u062f\u06a9\u062a\u0631 \u0647\u0644\u0627\u06a9\u0648\u06cc\u06cc , \u0631\u0627\u0632\u0647\u0627 \u0648 \u0646\u06cc\u0627\u0632\u0647\u0627, \u0635\u0628\u062d", "pub_date": "2018-06-06T19:09:12Z", "summary": "06.June 2018 - \u062f\u06a9\u062a\u0631 \u0647\u0644\u0627\u06a9\u0648\u06cc\u06cc , \u0631\u0627\u0632\u0647\u0627 \u0648 \u0646\u06cc\u0627\u0632\u0647\u0627, \u0635\u0628\u062d", "is_recommended": false, "recommendations_count": 0, "series": {"title": "Razha va Niazha", "id": 82316448, "image_url_sm": "https://cdn1.player.fm/images/1027679/series/n237MsJ0HGRntqQU/64.png", "image_url_lg": "https://cdn1.player.fm/images/1027679/series/n237MsJ0HGRntqQU/256.png"}, "duration": "1:59:06", "tags": "", "audio_url": "http://feeds.soundcloud.com/stream/454737381-razhavaniazha-com-06-06-2018-r-m.mp3", "current_progress": 0.0, "real_duration_written": false}, "context_supplier": {"id": 82316448, "title": "Razha va Niazha", "image_url_sm": "https://cdn1.player.fm/images/1027679/series/n237MsJ0HGRntqQU/64.png", "image_url_lg": "https://cdn1.player.fm/images/1027679/series/n237MsJ0HGRntqQU/256.png", "las_updated": "2018-06-06T19:09:12Z", "author": "me", "is_subscribed": false, "subscribers_count": 0, "genres": "culture"}}, {"context": "NEW_SUBSCRIBED_EPISODE", "id": 33030006, "time": "2018-06-06T08:48:05Z", "content": {"id": "438582602379", "title": "05.June 2018 - \u062f\u06a9\u062a\u0631 \u0647\u0644\u0627\u06a9\u0648\u06cc\u06cc , \u0631\u0627\u0632\u0647\u0627 \u0648 \u0646\u06cc\u0627\u0632\u0647\u0627, \u0639\u0635\u0631", "pub_date": "2018-06-06T08:48:05Z", "summary": "05.June 2018 - \u062f\u06a9\u062a\u0631 \u0647\u0644\u0627\u06a9\u0648\u06cc\u06cc , \u0631\u0627\u0632\u0647\u0627 \u0648 \u0646\u06cc\u0627\u0632\u0647\u0627, \u0639\u0635\u0631", "is_recommended": false, "recommendations_count": 0, "series": {"title": "Razha va Niazha", "id": 82316448, "image_url_sm": "https://cdn1.player.fm/images/1027679/series/n237MsJ0HGRntqQU/64.png", "image_url_lg": "https://cdn1.player.fm/images/1027679/series/n237MsJ0HGRntqQU/256.png"}, "duration": "1:59:05", "tags": "", "audio_url": "http://feeds.soundcloud.com/stream/454519029-razhavaniazha-com-05-06-2018-r-e.mp3", "current_progress": 0.0, "real_duration_written": false}, "context_supplier": {"id": 82316448, "title": "Razha va Niazha", "image_url_sm": "https://cdn1.player.fm/images/1027679/series/n237MsJ0HGRntqQU/64.png", "image_url_lg": "https://cdn1.player.fm/images/1027679/series/n237MsJ0HGRntqQU/256.png", "las_updated": "2018-06-06T08:48:05Z", "author": "me", "is_subscribed": false, "subscribers_count": 0, "genres": "culture"}}, {"context": "NEW_SUBSCRIBED_EPISODE", "id": 63266062, "time": "2018-06-06T04:00:00Z", "content": {"id": "341257663667", "title": "Tek Nights (Episode 64)", "pub_date": "2018-06-06T04:00:00Z", "summary": "Tek Nights (Episode 64)", "is_recommended": false, "recommendations_count": 0, "series": {"title": "Radio Javan Podcasts", "id": 2912296, "image_url_sm": "https://cdn1.player.fm/images/2210354/series/CP2HKKvW3oif9lC1/64.jpg", "image_url_lg": "https://cdn1.player.fm/images/2210354/series/CP2HKKvW3oif9lC1/256.jpg"}, "duration": "", "tags": "", "audio_url": "https://host2.rjmusicmedia.com/media/podcast/mp3-192/Tek-Nights-64.mp3", "current_progress": 0.0, "real_duration_written": false}, "context_supplier": {"id": 2912296, "title": "Radio Javan Podcasts", "image_url_sm": "https://cdn1.player.fm/images/2210354/series/CP2HKKvW3oif9lC1/64.jpg", "image_url_lg": "https://cdn1.player.fm/images/2210354/series/CP2HKKvW3oif9lC1/256.jpg", "las_updated": "2018-06-06T04:00:00Z", "author": "me", "is_subscribed": false, "subscribers_count": 0, "genres": "culture"}}, {"context": "NEW_SUBSCRIBED_EPISODE", "id": 14486483, "time": "2018-06-05T21:48:53Z", "content": {"id": "43997633078", "title": "Toranj-06-06-2018", "pub_date": "2018-06-05T21:48:53Z", "summary": "Toranj-06-06-2018", "is_recommended": false, "recommendations_count": 0, "series": {"title": "Toranj", "id": 60154034, "image_url_sm": "https://cdn1.player.fm/images/16403860/series/eGg5OFKoNQoVZSLO/64.png", "image_url_lg": "https://cdn1.player.fm/images/16403860/series/eGg5OFKoNQoVZSLO/256.png"}, "duration": "25:08", "tags": "", "audio_url": "https://static.accessradio.org/StationFolder/plainsfm/Toranj%206%20June.mp3", "current_progress": 0.0, "real_duration_written": false}, "context_supplier": {"id": 60154034, "title": "Toranj", "image_url_sm": "https://cdn1.player.fm/images/16403860/series/eGg5OFKoNQoVZSLO/64.png", "image_url_lg": "https://cdn1.player.fm/images/16403860/series/eGg5OFKoNQoVZSLO/256.png", "las_updated": "2018-06-05T21:48:53Z", "author": "me", "is_subscribed": false, "subscribers_count": 0, "genres": "culture"}}, {"context": "NEW_SUBSCRIBED_EPISODE", "id": 81768481, "time": "2018-06-05T20:36:07Z", "content": {"id": "773451871369", "title": "\u0633\u0648\u0627\u062f \u0645\u0627\u0644\u06cc \u062f\u0631 \u0632\u0646\u062f\u06af\u06cc", "pub_date": "2018-06-05T20:36:07Z", "summary": "\u0633\u0648\u0627\u062f \u0645\u0627\u0644\u06cc \u062f\u0631 \u0632\u0646\u062f\u06af\u06cc", "is_recommended": false, "recommendations_count": 0, "series": {"title": "Parsclick", "id": 9356712, "image_url_sm": "https://cdn1.player.fm/images/11372622/series/q2D05LsXiUipppqq/64.jpg", "image_url_lg": "https://cdn1.player.fm/images/11372622/series/q2D05LsXiUipppqq/256.jpg"}, "duration": "25:50", "tags": "", "audio_url": "http://feeds.soundcloud.com/stream/454275456-amir-hazz-azimi-ubgskhyyrcp8.mp3", "current_progress": 0.0, "real_duration_written": false}, "context_supplier": {"id": 9356712, "title": "Parsclick", "image_url_sm": "https://cdn1.player.fm/images/11372622/series/q2D05LsXiUipppqq/64.jpg", "image_url_lg": "https://cdn1.player.fm/images/11372622/series/q2D05LsXiUipppqq/256.jpg", "las_updated": "2018-06-05T20:36:07Z", "author": "me", "is_subscribed": false, "subscribers_count": 0, "genres": "culture"}}]