[{"context": "NEW_SUBSCRIBED_EPISODE", "id": 7390105, "time": "2020-09-26T04:00:00Z", "content": {"id": "344891188771", "title": "Apollo (Episode 9 (Bombic))", "pub_date": "2020-09-26T04:00:00Z", "summary": "Apollo (Episode 9 (Bombic))", "is_recommended": false, "recommendations_count": 0, "series": {"title": "Radio Javan Podcasts", "id": 82716221, "image_url_sm": "https://cdn.player.fm/images/2210354/series/CP2HKKvW3oif9lC1/64.jpg", "image_url_lg": "https://cdn.player.fm/images/2210354/series/CP2HKKvW3oif9lC1/256.jpg"}, "duration": "30", "tags": "", "audio_url": "https://host2.rj-mw1.com/media/podcast/mp3-192/3007-2acd479c62aca08.mp3", "current_progress": 0.0, "real_duration_written": false}, "context_supplier": {"id": 82716221, "title": "Radio Javan Podcasts", "image_url_sm": "https://cdn.player.fm/images/2210354/series/CP2HKKvW3oif9lC1/64.jpg", "image_url_lg": "https://cdn.player.fm/images/2210354/series/CP2HKKvW3oif9lC1/256.jpg", "las_updated": "2020-09-26T04:00:00Z", "author": "me", "is_subscribed": false, "subscribers_count": 0, "genres": "culture"}}, {"context": "NEW_SUBSCRIBED_EPISODE", "id": 59208741, "time": "2020-09-22T19:38:04Z", "content": {"id": "581871551428", "title": "Ganje Hozour audio Program #832_1", "pub_date": "2020-09-22T19:38:04Z", "summary": "Ganje Hozour audio Program #832_1", "is_recommended": false, "recommendations_count": 0, "series": {"title": "Ganj e Hozour Telephone messages", "id": 72137314, "image_url_sm": "https://cdn.player.fm/images/20704450/series/oqhLxVnLgMe9ue2N/64.jpg", "image_url_lg": "https://cdn.player.fm/images/20704450/series/oqhLxVnLgMe9ue2N/256.jpg"}, "duration": "30", "tags": "", "audio_url": "http://www.parvizshahbazi.com/Audio/832-1_Webaudio.m4a", "current_progress": 0.0, "real_duration_written": false}, "context_supplier": {"id": 72137314, "title": "Ganj e Hozour Telephone messages", "image_url_sm": "https://cdn.player.fm/images/20704450/series/oqhLxVnLgMe9ue2N/64.jpg", "image_url_lg": "https://cdn.player.fm/images/20704450/series/oqhLxVnLgMe9ue2N/256.jpg", "las_updated": "2020-09-22T19:38:04Z", "author": "me", "is_subscribed": false, "subscribers_count": 0, "genres": "culture"}}, {"context": "NEW_SUBSCRIBED_EPISODE", "id": 29353802, "time": "2020-09-22T04:00:00Z", "content": {"id": "843296125852", "title": "Ajil (Sexism)", "pub_date": "2020-09-22T04:00:00Z", "summary": "Ajil (Sexism)", "is_recommended": false, "recommendations_count": 0, "series": {"title": "Radio Javan Podcasts", "id": 82716221, "image_url_sm": "https://cdn.player.fm/images/2210354/series/CP2HKKvW3oif9lC1/64.jpg", "image_url_lg": "https://cdn.player.fm/images/2210354/series/CP2HKKvW3oif9lC1/256.jpg"}, "duration": "30", "tags": "", "audio_url": "https://host2.rj-mw1.com/media/podcast/mp3-192/3006-d90c6f2ac5513a9.mp3", "current_progress": 0.0, "real_duration_written": false}, "context_supplier": {"id": 82716221, "title": "Radio Javan Podcasts", "image_url_sm": "https://cdn.player.fm/images/2210354/series/CP2HKKvW3oif9lC1/64.jpg", "image_url_lg": "https://cdn.player.fm/images/2210354/series/CP2HKKvW3oif9lC1/256.jpg", "las_updated": "2020-09-22T04:00:00Z", "author": "me", "is_subscribed": false, "subscribers_count": 0, "genres": "culture"}}, {"context": "NEW_SUBSCRIBED_EPISODE", "id": 70375874, "time": "2020-09-21T21:38:02Z", "content": {"id": "929858884087", "title": "\u0645\u0639\u0636\u0644 \u0627\u062c\u062a\u0645\u0627\u0639\u06cc", "pub_date": "2020-09-21T21:38:02Z", "summary": "\u0645\u0639\u0636\u0644 \u0627\u062c\u062a\u0645\u0627\u0639\u06cc", "is_recommended": false, "recommendations_count": 0, "series": {"title": "Parsclick", "id": 88571840, "image_url_sm": "https://cdn.player.fm/images/11372622/series/QdS8vDBSFkErL30d/64.jpg", "image_url_lg": "https://cdn.player.fm/images/11372622/series/QdS8vDBSFkErL30d/256.jpg"}, "duration": "30", "tags": "", "audio_url": "https://anchor.fm/s/192e8ad8/podcast/play/19962777/https%3A%2F%2Fd3ctxlq1ktw2nl.cloudfront.net%2Fstaging%2F2020-8-21%2F81ccf2aa-3414-2962-273b-d8609cc077e3.mp3", "current_progress": 0.0, "real_duration_written": false}, "context_supplier": {"id": 88571840, "title": "Parsclick", "image_url_sm": "https://cdn.player.fm/images/11372622/series/QdS8vDBSFkErL30d/64.jpg", "image_url_lg": "https://cdn.player.fm/images/11372622/series/QdS8vDBSFkErL30d/256.jpg", "las_updated": "2020-09-21T21:38:02Z", "author": "me", "is_subscribed": false, "subscribers_count": 0, "genres": "culture"}}, {"context": "NEW_SUBSCRIBED_EPISODE", "id": 85658415, "time": "2020-09-21T04:00:00Z", "content": {"id": "223626721680", "title": "Glory Stories (Tafrihe Akhare Hafteh)", "pub_date": "2020-09-21T04:00:00Z", "summary": "Glory Stories (Tafrihe Akhare Hafteh)", "is_recommended": false, "recommendations_count": 0, "series": {"title": "Radio Javan Podcasts", "id": 82716221, "image_url_sm": "https://cdn.player.fm/images/2210354/series/CP2HKKvW3oif9lC1/64.jpg", "image_url_lg": "https://cdn.player.fm/images/2210354/series/CP2HKKvW3oif9lC1/256.jpg"}, "duration": "30", "tags": "", "audio_url": "https://host2.rj-mw1.com/media/podcast/mp3-192/3005-291d0ffce1cbd38.mp3", "current_progress": 0.0, "real_duration_written": false}, "context_supplier": {"id": 82716221, "title": "Radio Javan Podcasts", "image_url_sm": "https://cdn.player.fm/images/2210354/series/CP2HKKvW3oif9lC1/64.jpg", "image_url_lg": "https://cdn.player.fm/images/2210354/series/CP2HKKvW3oif9lC1/256.jpg", "las_updated": "2020-09-21T04:00:00Z", "author": "me", "is_subscribed": false, "subscribers_count": 0, "genres": "culture"}}, {"context": "NEW_SUBSCRIBED_EPISODE", "id": 26503898, "time": "2020-09-20T14:33:23Z", "content": {"id": "121762139437", "title": "\u0647\u0641\u062a\u0627\u062f - \u0633\u0631\u06cc\u0627\u0644 \u0622\u062a\u06cc\u0644\u0627 \u0642\u0633\u0645\u062a \u062f\u0648\u0645\u061b \u0627\u0641\u0633\u0627\u0646\u0647\u200c\u06cc \u0622\u062a\u06cc\u0644\u0627", "pub_date": "2020-09-20T14:33:23Z", "summary": "\u0647\u0641\u062a\u0627\u062f - \u0633\u0631\u06cc\u0627\u0644 \u0622\u062a\u06cc\u0644\u0627 \u0642\u0633\u0645\u062a \u062f\u0648\u0645\u061b \u0627\u0641\u0633\u0627\u0646\u0647\u200c\u06cc \u0622\u062a\u06cc\u0644\u0627", "is_recommended": false, "recommendations_count": 0, "series": {"title": "ChannelB \u067e\u0627\u062f\u06a9\u0633\u062a \u0641\u0627\u0631\u0633\u06cc", "id": 11247131, "image_url_sm": "https://cdn.player.fm/images/15689550/series/ImK0iTs7LYDB5ltu/64.png", "image_url_lg": "https://cdn.player.fm/images/15689550/series/ImK0iTs7LYDB5ltu/256.png"}, "duration": "30", "tags": "", "audio_url": "https://traffic.libsyn.com/secure/channelb/ChannelB_Popdcast_Episode_70_-_Atila_Part_II.mp3?dest-id=1516907", "current_progress": 0.0, "real_duration_written": false}, "context_supplier": {"id": 11247131, "title": "ChannelB \u067e\u0627\u062f\u06a9\u0633\u062a \u0641\u0627\u0631\u0633\u06cc", "image_url_sm": "https://cdn.player.fm/images/15689550/series/ImK0iTs7LYDB5ltu/64.png", "image_url_lg": "https://cdn.player.fm/images/15689550/series/ImK0iTs7LYDB5ltu/256.png", "las_updated": "2020-09-20T14:33:23Z", "author": "me", "is_subscribed": false, "subscribers_count": 0, "genres": "culture"}}, {"context": "NEW_SUBSCRIBED_EPISODE", "id": 76482868, "time": "2020-09-20T04:00:00Z", "content": {"id": "726371424464", "title": "Dance Station (Episode 27)", "pub_date": "2020-09-20T04:00:00Z", "summary": "Dance Station (Episode 27)", "is_recommended": false, "recommendations_count": 0, "series": {"title": "Radio Javan Podcasts", "id": 82716221, "image_url_sm": "https://cdn.player.fm/images/2210354/series/CP2HKKvW3oif9lC1/64.jpg", "image_url_lg": "https://cdn.player.fm/images/2210354/series/CP2HKKvW3oif9lC1/256.jpg"}, "duration": "30", "tags": "", "audio_url": "https://host2.rj-mw1.com/media/podcast/mp3-192/3004-bbf8c0cd9dbc750.mp3", "current_progress": 0.0, "real_duration_written": false}, "context_supplier": {"id": 82716221, "title": "Radio Javan Podcasts", "image_url_sm": "https://cdn.player.fm/images/2210354/series/CP2HKKvW3oif9lC1/64.jpg", "image_url_lg": "https://cdn.player.fm/images/2210354/series/CP2HKKvW3oif9lC1/256.jpg", "las_updated": "2020-09-20T04:00:00Z", "author": "me", "is_subscribed": false, "subscribers_count": 0, "genres": "culture"}}, {"context": "NEW_SUBSCRIBED_EPISODE", "id": 12632313, "time": "2020-09-19T04:00:00Z", "content": {"id": "761006046749", "title": "RJ Countdown (Sep 19, 2020)", "pub_date": "2020-09-19T04:00:00Z", "summary": "RJ Countdown (Sep 19, 2020)", "is_recommended": false, "recommendations_count": 0, "series": {"title": "Radio Javan Podcasts", "id": 82716221, "image_url_sm": "https://cdn.player.fm/images/2210354/series/CP2HKKvW3oif9lC1/64.jpg", "image_url_lg": "https://cdn.player.fm/images/2210354/series/CP2HKKvW3oif9lC1/256.jpg"}, "duration": "30", "tags": "", "audio_url": "https://host2.rj-mw1.com/media/podcast/mp3-192/3003-b7b463057a4b98b.mp3", "current_progress": 0.0, "real_duration_written": false}, "context_supplier": {"id": 82716221, "title": "Radio Javan Podcasts", "image_url_sm": "https://cdn.player.fm/images/2210354/series/CP2HKKvW3oif9lC1/64.jpg", "image_url_lg": "https://cdn.player.fm/images/2210354/series/CP2HKKvW3oif9lC1/256.jpg", "las_updated": "2020-09-19T04:00:00Z", "author": "me", "is_subscribed": false, "subscribers_count": 0, "genres": "culture"}}, {"context": "NEW_SUBSCRIBED_EPISODE", "id": 7692335, "time": "2020-09-18T04:00:00Z", "content": {"id": "175144126703", "title": "Dubways (Episode 119)", "pub_date": "2020-09-18T04:00:00Z", "summary": "Dubways (Episode 119)", "is_recommended": false, "recommendations_count": 0, "series": {"title": "Radio Javan Podcasts", "id": 82716221, "image_url_sm": "https://cdn.player.fm/images/2210354/series/CP2HKKvW3oif9lC1/64.jpg", "image_url_lg": "https://cdn.player.fm/images/2210354/series/CP2HKKvW3oif9lC1/256.jpg"}, "duration": "30", "tags": "", "audio_url": "https://host2.rj-mw1.com/media/podcast/mp3-192/3002-49e8fa391577439.mp3", "current_progress": 0.0, "real_duration_written": false}, "context_supplier": {"id": 82716221, "title": "Radio Javan Podcasts", "image_url_sm": "https://cdn.player.fm/images/2210354/series/CP2HKKvW3oif9lC1/64.jpg", "image_url_lg": "https://cdn.player.fm/images/2210354/series/CP2HKKvW3oif9lC1/256.jpg", "las_updated": "2020-09-18T04:00:00Z", "author": "me", "is_subscribed": false, "subscribers_count": 0, "genres": "culture"}}, {"context": "NEW_SUBSCRIBED_EPISODE", "id": 95014095, "time": "2020-09-17T04:00:00Z", "content": {"id": "146450532264", "title": "Chamokham (Davandegyo Barazandegi)", "pub_date": "2020-09-17T04:00:00Z", "summary": "Chamokham (Davandegyo Barazandegi)", "is_recommended": false, "recommendations_count": 0, "series": {"title": "Radio Javan Podcasts", "id": 82716221, "image_url_sm": "https://cdn.player.fm/images/2210354/series/CP2HKKvW3oif9lC1/64.jpg", "image_url_lg": "https://cdn.player.fm/images/2210354/series/CP2HKKvW3oif9lC1/256.jpg"}, "duration": "30", "tags": "", "audio_url": "https://host2.rj-mw1.com/media/podcast/mp3-192/3001-0113661675232bc.mp3", "current_progress": 0.0, "real_duration_written": false}, "context_supplier": {"id": 82716221, "title": "Radio Javan Podcasts", "image_url_sm": "https://cdn.player.fm/images/2210354/series/CP2HKKvW3oif9lC1/64.jpg", "image_url_lg": "https://cdn.player.fm/images/2210354/series/CP2HKKvW3oif9lC1/256.jpg", "las_updated": "2020-09-17T04:00:00Z", "author": "me", "is_subscribed": false, "subscribers_count": 0, "genres": "culture"}}, {"context": "NEW_SUBSCRIBED_EPISODE", "id": 3652397, "time": "2020-09-16T22:31:07Z", "content": {"id": "162521877410", "title": "Ganje Hozour audio Program #831_1", "pub_date": "2020-09-16T22:31:07Z", "summary": "Ganje Hozour audio Program #831_1", "is_recommended": false, "recommendations_count": 0, "series": {"title": "Ganj e Hozour Telephone messages", "id": 72137314, "image_url_sm": "https://cdn.player.fm/images/20704450/series/oqhLxVnLgMe9ue2N/64.jpg", "image_url_lg": "https://cdn.player.fm/images/20704450/series/oqhLxVnLgMe9ue2N/256.jpg"}, "duration": "30", "tags": "", "audio_url": "http://www.parvizshahbazi.com/Audio/831-1_Webaudio.m4a", "current_progress": 0.0, "real_duration_written": false}, "context_supplier": {"id": 72137314, "title": "Ganj e Hozour Telephone messages", "image_url_sm": "https://cdn.player.fm/images/20704450/series/oqhLxVnLgMe9ue2N/64.jpg", "image_url_lg": "https://cdn.player.fm/images/20704450/series/oqhLxVnLgMe9ue2N/256.jpg", "las_updated": "2020-09-16T22:31:07Z", "author": "me", "is_subscribed": false, "subscribers_count": 0, "genres": "culture"}}, {"context": "NEW_SUBSCRIBED_EPISODE", "id": 219129, "time": "2020-09-15T20:36:04Z", "content": {"id": "40721460392", "title": "Radio Rumi Program 48: The City of Light", "pub_date": "2020-09-15T20:36:04Z", "summary": "Radio Rumi Program 48: The City of Light", "is_recommended": false, "recommendations_count": 0, "series": {"title": "Radio Rumi", "id": 31036322, "image_url_sm": "https://cdn.player.fm/images/20670553/series/rXlS8PmQMG0mEs6B/64.jpg", "image_url_lg": "https://cdn.player.fm/images/20670553/series/rXlS8PmQMG0mEs6B/256.jpg"}, "duration": "30", "tags": "", "audio_url": "https://anchor.fm/s/1d56e128/podcast/play/19659836/https%3A%2F%2Fd3ctxlq1ktw2nl.cloudfront.net%2Fstaging%2F2020-8-15%2Ff9d53449-857e-b20b-1823-5eb31f791713.mp3", "current_progress": 0.0, "real_duration_written": false}, "context_supplier": {"id": 31036322, "title": "Radio Rumi", "image_url_sm": "https://cdn.player.fm/images/20670553/series/rXlS8PmQMG0mEs6B/64.jpg", "image_url_lg": "https://cdn.player.fm/images/20670553/series/rXlS8PmQMG0mEs6B/256.jpg", "las_updated": "2020-09-15T20:36:04Z", "author": "me", "is_subscribed": false, "subscribers_count": 0, "genres": "culture"}}, {"context": "NEW_SUBSCRIBED_EPISODE", "id": 20319719, "time": "2020-09-15T04:00:00Z", "content": {"id": "393128464689", "title": "Ajil (Secret To Happiness)", "pub_date": "2020-09-15T04:00:00Z", "summary": "Ajil (Secret To Happiness)", "is_recommended": false, "recommendations_count": 0, "series": {"title": "Radio Javan Podcasts", "id": 82716221, "image_url_sm": "https://cdn.player.fm/images/2210354/series/CP2HKKvW3oif9lC1/64.jpg", "image_url_lg": "https://cdn.player.fm/images/2210354/series/CP2HKKvW3oif9lC1/256.jpg"}, "duration": "30", "tags": "", "audio_url": "https://host2.rj-mw1.com/media/podcast/mp3-192/3000-2d836b2cd86e119.mp3", "current_progress": 0.0, "real_duration_written": false}, "context_supplier": {"id": 82716221, "title": "Radio Javan Podcasts", "image_url_sm": "https://cdn.player.fm/images/2210354/series/CP2HKKvW3oif9lC1/64.jpg", "image_url_lg": "https://cdn.player.fm/images/2210354/series/CP2HKKvW3oif9lC1/256.jpg", "las_updated": "2020-09-15T04:00:00Z", "author": "me", "is_subscribed": false, "subscribers_count": 0, "genres": "culture"}}, {"context": "NEW_SUBSCRIBED_EPISODE", "id": 31209889, "time": "2020-09-13T16:47:36Z", "content": {"id": "557171856484", "title": "\u0634\u0635\u062a \u0648 \u0646\u0647 - \u0633\u0631\u06cc\u0627\u0644 \u0622\u062a\u06cc\u0644\u0627 \u0642\u0633\u0645\u062a \u0627\u0648\u0644\u061b \u062a\u0631\u0627\u0646\u0633\u06cc\u0644\u0648\u0627\u0646\u06cc\u0627 \u06a9\u062c\u0627\u0633\u062a\u061f", "pub_date": "2020-09-13T16:47:36Z", "summary": "\u0634\u0635\u062a \u0648 \u0646\u0647 - \u0633\u0631\u06cc\u0627\u0644 \u0622\u062a\u06cc\u0644\u0627 \u0642\u0633\u0645\u062a \u0627\u0648\u0644\u061b \u062a\u0631\u0627\u0646\u0633\u06cc\u0644\u0648\u0627\u0646\u06cc\u0627 \u06a9\u062c\u0627\u0633\u062a\u061f", "is_recommended": false, "recommendations_count": 0, "series": {"title": "ChannelB \u067e\u0627\u062f\u06a9\u0633\u062a \u0641\u0627\u0631\u0633\u06cc", "id": 11247131, "image_url_sm": "https://cdn.player.fm/images/15689550/series/ImK0iTs7LYDB5ltu/64.png", "image_url_lg": "https://cdn.player.fm/images/15689550/series/ImK0iTs7LYDB5ltu/256.png"}, "duration": "30", "tags": "", "audio_url": "https://traffic.libsyn.com/secure/channelb/ChannelB_Podcast_Episode_69_-_Atila_PART_I.mp3?dest-id=1516907", "current_progress": 0.0, "real_duration_written": false}, "context_supplier": {"id": 11247131, "title": "ChannelB \u067e\u0627\u062f\u06a9\u0633\u062a \u0641\u0627\u0631\u0633\u06cc", "image_url_sm": "https://cdn.player.fm/images/15689550/series/ImK0iTs7LYDB5ltu/64.png", "image_url_lg": "https://cdn.player.fm/images/15689550/series/ImK0iTs7LYDB5ltu/256.png", "las_updated": "2020-09-13T16:47:36Z", "author": "me", "is_subscribed": false, "subscribers_count": 0, "genres": "culture"}}, {"context": "NEW_SUBSCRIBED_EPISODE", "id": 91464331, "time": "2020-09-13T16:29:02Z", "content": {"id": "926510255393", "title": "2020 Hip Hop & Reggaeton Mix", "pub_date": "2020-09-13T16:29:02Z", "summary": "2020 Hip Hop & Reggaeton Mix", "is_recommended": false, "recommendations_count": 0, "series": {"title": "360 Show", "id": 27914027, "image_url_sm": "https://cdn.player.fm/images/11892158/series/MlvadrQXawPsStq9/64.jpg", "image_url_lg": "https://cdn.player.fm/images/11892158/series/MlvadrQXawPsStq9/256.jpg"}, "duration": "30", "tags": "", "audio_url": "https://hearthis.at/djborhan/2020-hip-hop-reggaeton/listen.mp3?s=SEM", "current_progress": 0.0, "real_duration_written": false}, "context_supplier": {"id": 27914027, "title": "360 Show", "image_url_sm": "https://cdn.player.fm/images/11892158/series/MlvadrQXawPsStq9/64.jpg", "image_url_lg": "https://cdn.player.fm/images/11892158/series/MlvadrQXawPsStq9/256.jpg", "las_updated": "2020-09-13T16:29:02Z", "author": "me", "is_subscribed": false, "subscribers_count": 0, "genres": "culture"}}, {"context": "NEW_SUBSCRIBED_EPISODE", "id": 99067875, "time": "2020-09-12T04:00:00Z", "content": {"id": "141950829406", "title": "Bazaar (Episode 42)", "pub_date": "2020-09-12T04:00:00Z", "summary": "Bazaar (Episode 42)", "is_recommended": false, "recommendations_count": 0, "series": {"title": "Radio Javan Podcasts", "id": 82716221, "image_url_sm": "https://cdn.player.fm/images/2210354/series/CP2HKKvW3oif9lC1/64.jpg", "image_url_lg": "https://cdn.player.fm/images/2210354/series/CP2HKKvW3oif9lC1/256.jpg"}, "duration": "30", "tags": "", "audio_url": "https://host2.rj-mw1.com/media/podcast/mp3-192/2998-8a734a88c0a3892.mp3", "current_progress": 0.0, "real_duration_written": false}, "context_supplier": {"id": 82716221, "title": "Radio Javan Podcasts", "image_url_sm": "https://cdn.player.fm/images/2210354/series/CP2HKKvW3oif9lC1/64.jpg", "image_url_lg": "https://cdn.player.fm/images/2210354/series/CP2HKKvW3oif9lC1/256.jpg", "las_updated": "2020-09-12T04:00:00Z", "author": "me", "is_subscribed": false, "subscribers_count": 0, "genres": "culture"}}, {"context": "NEW_SUBSCRIBED_EPISODE", "id": 32689516, "time": "2020-09-11T04:00:00Z", "content": {"id": "716690556459", "title": "Techwich (IFA 2020 Tech News (Special))", "pub_date": "2020-09-11T04:00:00Z", "summary": "Techwich (IFA 2020 Tech News (Special))", "is_recommended": false, "recommendations_count": 0, "series": {"title": "Radio Javan Podcasts", "id": 82716221, "image_url_sm": "https://cdn.player.fm/images/2210354/series/CP2HKKvW3oif9lC1/64.jpg", "image_url_lg": "https://cdn.player.fm/images/2210354/series/CP2HKKvW3oif9lC1/256.jpg"}, "duration": "30", "tags": "", "audio_url": "https://host2.rj-mw1.com/media/podcast/mp3-192/2999-fd1cace94c87454.mp3", "current_progress": 0.0, "real_duration_written": false}, "context_supplier": {"id": 82716221, "title": "Radio Javan Podcasts", "image_url_sm": "https://cdn.player.fm/images/2210354/series/CP2HKKvW3oif9lC1/64.jpg", "image_url_lg": "https://cdn.player.fm/images/2210354/series/CP2HKKvW3oif9lC1/256.jpg", "las_updated": "2020-09-11T04:00:00Z", "author": "me", "is_subscribed": false, "subscribers_count": 0, "genres": "culture"}}, {"context": "NEW_SUBSCRIBED_EPISODE", "id": 57038741, "time": "2020-09-10T04:00:00Z", "content": {"id": "728147337793", "title": "Ajil (Dastane Rejimhaye Ghazaei)", "pub_date": "2020-09-10T04:00:00Z", "summary": "Ajil (Dastane Rejimhaye Ghazaei)", "is_recommended": false, "recommendations_count": 0, "series": {"title": "Radio Javan Podcasts", "id": 82716221, "image_url_sm": "https://cdn.player.fm/images/2210354/series/CP2HKKvW3oif9lC1/64.jpg", "image_url_lg": "https://cdn.player.fm/images/2210354/series/CP2HKKvW3oif9lC1/256.jpg"}, "duration": "30", "tags": "", "audio_url": "https://host2.rj-mw1.com/media/podcast/mp3-192/2996-34677bd706372d2.mp3", "current_progress": 0.0, "real_duration_written": false}, "context_supplier": {"id": 82716221, "title": "Radio Javan Podcasts", "image_url_sm": "https://cdn.player.fm/images/2210354/series/CP2HKKvW3oif9lC1/64.jpg", "image_url_lg": "https://cdn.player.fm/images/2210354/series/CP2HKKvW3oif9lC1/256.jpg", "las_updated": "2020-09-10T04:00:00Z", "author": "me", "is_subscribed": false, "subscribers_count": 0, "genres": "culture"}}, {"context": "NEW_SUBSCRIBED_EPISODE", "id": 92343472, "time": "2020-09-10T04:00:00Z", "content": {"id": "239632290633", "title": "Chamokham (Goftanihaye Shenidani)", "pub_date": "2020-09-10T04:00:00Z", "summary": "Chamokham (Goftanihaye Shenidani)", "is_recommended": false, "recommendations_count": 0, "series": {"title": "Radio Javan Podcasts", "id": 82716221, "image_url_sm": "https://cdn.player.fm/images/2210354/series/CP2HKKvW3oif9lC1/64.jpg", "image_url_lg": "https://cdn.player.fm/images/2210354/series/CP2HKKvW3oif9lC1/256.jpg"}, "duration": "30", "tags": "", "audio_url": "https://host2.rj-mw1.com/media/podcast/mp3-192/2997-623a8e749169046.mp3", "current_progress": 0.0, "real_duration_written": false}, "context_supplier": {"id": 82716221, "title": "Radio Javan Podcasts", "image_url_sm": "https://cdn.player.fm/images/2210354/series/CP2HKKvW3oif9lC1/64.jpg", "image_url_lg": "https://cdn.player.fm/images/2210354/series/CP2HKKvW3oif9lC1/256.jpg", "las_updated": "2020-09-10T04:00:00Z", "author": "me", "is_subscribed": false, "subscribers_count": 0, "genres": "culture"}}, {"context": "NEW_SUBSCRIBED_EPISODE", "id": 61332324, "time": "2020-09-09T00:00:00Z", "content": {"id": "670495622973", "title": "\u0622\u0647\u0646\u06af \u062a\u06cc\u062a\u0631\u0627\u0698 \u062f\u0647 \u0633\u0627\u0644\u06af\u06cc \u0633\u0627\u0644\u06cc\u200c \u062a\u0627\u06a9", "pub_date": "2020-09-09T00:00:00Z", "summary": "\u0622\u0647\u0646\u06af \u062a\u06cc\u062a\u0631\u0627\u0698 \u062f\u0647 \u0633\u0627\u0644\u06af\u06cc \u0633\u0627\u0644\u06cc\u200c \u062a\u0627\u06a9", "is_recommended": false, "recommendations_count": 0, "series": {"title": "Manoto \u0645\u0646\u200c \u0648 \u062a\u0648", "id": 35295983, "image_url_sm": "https://cdn.player.fm/images/2074379/series/FDhn8MmlwjO4w49Y/64.jpg", "image_url_lg": "https://cdn.player.fm/images/2074379/series/FDhn8MmlwjO4w49Y/256.jpg"}, "duration": "30", "tags": "", "audio_url": "http://feeds.soundcloud.com/stream/890281195-manototv-8yc6to0ju3zn.mp3", "current_progress": 0.0, "real_duration_written": false}, "context_supplier": {"id": 35295983, "title": "Manoto \u0645\u0646\u200c \u0648 \u062a\u0648", "image_url_sm": "https://cdn.player.fm/images/2074379/series/FDhn8MmlwjO4w49Y/64.jpg", "image_url_lg": "https://cdn.player.fm/images/2074379/series/FDhn8MmlwjO4w49Y/256.jpg", "las_updated": "2020-09-09T00:00:00Z", "author": "me", "is_subscribed": false, "subscribers_count": 0, "genres": "culture"}}, {"context": "NEW_SUBSCRIBED_EPISODE", "id": 18713980, "time": "2020-09-08T20:57:06Z", "content": {"id": "451433680354", "title": "Ganje Hozour audio Program #830_1", "pub_date": "2020-09-08T20:57:06Z", "summary": "Ganje Hozour audio Program #830_1", "is_recommended": false, "recommendations_count": 0, "series": {"title": "Ganj e Hozour Telephone messages", "id": 72137314, "image_url_sm": "https://cdn.player.fm/images/20704450/series/oqhLxVnLgMe9ue2N/64.jpg", "image_url_lg": "https://cdn.player.fm/images/20704450/series/oqhLxVnLgMe9ue2N/256.jpg"}, "duration": "30", "tags": "", "audio_url": "http://www.parvizshahbazi.com/Audio/830-1_Webaudio.m4a", "current_progress": 0.0, "real_duration_written": false}, "context_supplier": {"id": 72137314, "title": "Ganj e Hozour Telephone messages", "image_url_sm": "https://cdn.player.fm/images/20704450/series/oqhLxVnLgMe9ue2N/64.jpg", "image_url_lg": "https://cdn.player.fm/images/20704450/series/oqhLxVnLgMe9ue2N/256.jpg", "las_updated": "2020-09-08T20:57:06Z", "author": "me", "is_subscribed": false, "subscribers_count": 0, "genres": "culture"}}, {"context": "NEW_SUBSCRIBED_EPISODE", "id": 34243728, "time": "2020-09-04T22:53:49Z", "content": {"id": "190202759727", "title": "\u0642\u0633\u0645\u062a \u067e\u0627\u0646\u0632\u062f\u0647\u0645: \u0633\u0631\u0645\u0627\u06cc\u0647\u200c\u062f\u0627\u0631\u06cc \u0646\u0638\u0627\u0631\u062a\u06cc\u060c \u0628\u062e\u0634 \u062f\u0648\u0645\u061b \u0633\u0627\u0632\u0648\u06a9\u0627\u0631 \u0627\u0646\u0628\u0627\u0634\u062a \u0645\u0627\u0632\u0627\u062f \u0631\u0641\u062a\u0627\u0631\u06cc", "pub_date": "2020-09-04T22:53:49Z", "summary": "\u0642\u0633\u0645\u062a \u067e\u0627\u0646\u0632\u062f\u0647\u0645: \u0633\u0631\u0645\u0627\u06cc\u0647\u200c\u062f\u0627\u0631\u06cc \u0646\u0638\u0627\u0631\u062a\u06cc\u060c \u0628\u062e\u0634 \u062f\u0648\u0645\u061b \u0633\u0627\u0632\u0648\u06a9\u0627\u0631 \u0627\u0646\u0628\u0627\u0634\u062a \u0645\u0627\u0632\u0627\u062f \u0631\u0641\u062a\u0627\u0631\u06cc", "is_recommended": false, "recommendations_count": 0, "series": {"title": "Democracy DarKar", "id": 35522939, "image_url_sm": "https://cdn.player.fm/images/21187874/series/ixPUL7G3Vx7KzL9s/64.jpg", "image_url_lg": "https://cdn.player.fm/images/21187874/series/ixPUL7G3Vx7KzL9s/256.jpg"}, "duration": "30", "tags": "", "audio_url": "https://media.blubrry.com/datwfa/content.blubrry.com/datwfa/DatWfa_Episode_15_Surveillance_Capitalism_P02_Dynamic_Of_Behavioral_Accumulation.mp3", "current_progress": 0.0, "real_duration_written": false}, "context_supplier": {"id": 35522939, "title": "Democracy DarKar", "image_url_sm": "https://cdn.player.fm/images/21187874/series/ixPUL7G3Vx7KzL9s/64.jpg", "image_url_lg": "https://cdn.player.fm/images/21187874/series/ixPUL7G3Vx7KzL9s/256.jpg", "las_updated": "2020-09-04T22:53:49Z", "author": "me", "is_subscribed": false, "subscribers_count": 0, "genres": "culture"}}, {"context": "NEW_SUBSCRIBED_EPISODE", "id": 68781055, "time": "2020-09-04T11:53:12Z", "content": {"id": "24095871554", "title": "\u0631\u0642\u0627\u0628\u062a \u06cc\u0627 \u062d\u0633\u0648\u062f\u06cc\u061f", "pub_date": "2020-09-04T11:53:12Z", "summary": "\u0631\u0642\u0627\u0628\u062a \u06cc\u0627 \u062d\u0633\u0648\u062f\u06cc\u061f", "is_recommended": false, "recommendations_count": 0, "series": {"title": "Parsclick", "id": 88571840, "image_url_sm": "https://cdn.player.fm/images/11372622/series/QdS8vDBSFkErL30d/64.jpg", "image_url_lg": "https://cdn.player.fm/images/11372622/series/QdS8vDBSFkErL30d/256.jpg"}, "duration": "30", "tags": "", "audio_url": "https://anchor.fm/s/192e8ad8/podcast/play/19039102/https%3A%2F%2Fd3ctxlq1ktw2nl.cloudfront.net%2Fstaging%2F2020-8-3%2F5bd53608-5eb5-e131-1cd0-813db342301b.mp3", "current_progress": 0.0, "real_duration_written": false}, "context_supplier": {"id": 88571840, "title": "Parsclick", "image_url_sm": "https://cdn.player.fm/images/11372622/series/QdS8vDBSFkErL30d/64.jpg", "image_url_lg": "https://cdn.player.fm/images/11372622/series/QdS8vDBSFkErL30d/256.jpg", "las_updated": "2020-09-04T11:53:12Z", "author": "me", "is_subscribed": false, "subscribers_count": 0, "genres": "culture"}}, {"context": "NEW_SUBSCRIBED_EPISODE", "id": 56230866, "time": "2020-09-03T04:00:00Z", "content": {"id": "544064863398", "title": "Chamokham (Amoozeshe Ba Arzesh)", "pub_date": "2020-09-03T04:00:00Z", "summary": "Chamokham (Amoozeshe Ba Arzesh)", "is_recommended": false, "recommendations_count": 0, "series": {"title": "Radio Javan Podcasts", "id": 82716221, "image_url_sm": "https://cdn.player.fm/images/2210354/series/CP2HKKvW3oif9lC1/64.jpg", "image_url_lg": "https://cdn.player.fm/images/2210354/series/CP2HKKvW3oif9lC1/256.jpg"}, "duration": "30", "tags": "", "audio_url": "https://host2.rj-mw1.com/media/podcast/mp3-192/2992-d4a0a49f921314e.mp3", "current_progress": 0.0, "real_duration_written": false}, "context_supplier": {"id": 82716221, "title": "Radio Javan Podcasts", "image_url_sm": "https://cdn.player.fm/images/2210354/series/CP2HKKvW3oif9lC1/64.jpg", "image_url_lg": "https://cdn.player.fm/images/2210354/series/CP2HKKvW3oif9lC1/256.jpg", "las_updated": "2020-09-03T04:00:00Z", "author": "me", "is_subscribed": false, "subscribers_count": 0, "genres": "culture"}}, {"context": "NEW_SUBSCRIBED_EPISODE", "id": 39952979, "time": "2020-09-03T04:00:00Z", "content": {"id": "986419953120", "title": "Bekhandim (Episode 6)", "pub_date": "2020-09-03T04:00:00Z", "summary": "Bekhandim (Episode 6)", "is_recommended": false, "recommendations_count": 0, "series": {"title": "Radio Javan Podcasts", "id": 82716221, "image_url_sm": "https://cdn.player.fm/images/2210354/series/CP2HKKvW3oif9lC1/64.jpg", "image_url_lg": "https://cdn.player.fm/images/2210354/series/CP2HKKvW3oif9lC1/256.jpg"}, "duration": "30", "tags": "", "audio_url": "https://host2.rj-mw1.com/media/podcast/mp3-192/2993-d015aab911dce0a.mp3", "current_progress": 0.0, "real_duration_written": false}, "context_supplier": {"id": 82716221, "title": "Radio Javan Podcasts", "image_url_sm": "https://cdn.player.fm/images/2210354/series/CP2HKKvW3oif9lC1/64.jpg", "image_url_lg": "https://cdn.player.fm/images/2210354/series/CP2HKKvW3oif9lC1/256.jpg", "las_updated": "2020-09-03T04:00:00Z", "author": "me", "is_subscribed": false, "subscribers_count": 0, "genres": "culture"}}, {"context": "NEW_SUBSCRIBED_EPISODE", "id": 97990432, "time": "2020-09-03T04:00:00Z", "content": {"id": "521223839453", "title": "Techwich (Tech News & Cryptocurrency 3)", "pub_date": "2020-09-03T04:00:00Z", "summary": "Techwich (Tech News & Cryptocurrency 3)", "is_recommended": false, "recommendations_count": 0, "series": {"title": "Radio Javan Podcasts", "id": 82716221, "image_url_sm": "https://cdn.player.fm/images/2210354/series/CP2HKKvW3oif9lC1/64.jpg", "image_url_lg": "https://cdn.player.fm/images/2210354/series/CP2HKKvW3oif9lC1/256.jpg"}, "duration": "30", "tags": "", "audio_url": "https://host2.rj-mw1.com/media/podcast/mp3-192/2994-bbd249c445d90d2.mp3", "current_progress": 0.0, "real_duration_written": false}, "context_supplier": {"id": 82716221, "title": "Radio Javan Podcasts", "image_url_sm": "https://cdn.player.fm/images/2210354/series/CP2HKKvW3oif9lC1/64.jpg", "image_url_lg": "https://cdn.player.fm/images/2210354/series/CP2HKKvW3oif9lC1/256.jpg", "las_updated": "2020-09-03T04:00:00Z", "author": "me", "is_subscribed": false, "subscribers_count": 0, "genres": "culture"}}, {"context": "NEW_SUBSCRIBED_EPISODE", "id": 11315156, "time": "2020-09-02T18:59:25Z", "content": {"id": "813506130492", "title": "Ganje Hozour audio Program #829_1", "pub_date": "2020-09-02T18:59:25Z", "summary": "Ganje Hozour audio Program #829_1", "is_recommended": false, "recommendations_count": 0, "series": {"title": "Ganj e Hozour Telephone messages", "id": 72137314, "image_url_sm": "https://cdn.player.fm/images/20704450/series/oqhLxVnLgMe9ue2N/64.jpg", "image_url_lg": "https://cdn.player.fm/images/20704450/series/oqhLxVnLgMe9ue2N/256.jpg"}, "duration": "30", "tags": "", "audio_url": "http://www.parvizshahbazi.com/Audio/829-1_Webaudio.m4a", "current_progress": 0.0, "real_duration_written": false}, "context_supplier": {"id": 72137314, "title": "Ganj e Hozour Telephone messages", "image_url_sm": "https://cdn.player.fm/images/20704450/series/oqhLxVnLgMe9ue2N/64.jpg", "image_url_lg": "https://cdn.player.fm/images/20704450/series/oqhLxVnLgMe9ue2N/256.jpg", "las_updated": "2020-09-02T18:59:25Z", "author": "me", "is_subscribed": false, "subscribers_count": 0, "genres": "culture"}}, {"context": "NEW_SUBSCRIBED_EPISODE", "id": 21155786, "time": "2020-09-01T04:00:00Z", "content": {"id": "44203149658", "title": "Ajil (Daramad Zaie Online)", "pub_date": "2020-09-01T04:00:00Z", "summary": "Ajil (Daramad Zaie Online)", "is_recommended": false, "recommendations_count": 0, "series": {"title": "Radio Javan Podcasts", "id": 82716221, "image_url_sm": "https://cdn.player.fm/images/2210354/series/CP2HKKvW3oif9lC1/64.jpg", "image_url_lg": "https://cdn.player.fm/images/2210354/series/CP2HKKvW3oif9lC1/256.jpg"}, "duration": "30", "tags": "", "audio_url": "https://host2.rj-mw1.com/media/podcast/mp3-192/2991-684d20d4d6d2eb2.mp3", "current_progress": 0.0, "real_duration_written": false}, "context_supplier": {"id": 82716221, "title": "Radio Javan Podcasts", "image_url_sm": "https://cdn.player.fm/images/2210354/series/CP2HKKvW3oif9lC1/64.jpg", "image_url_lg": "https://cdn.player.fm/images/2210354/series/CP2HKKvW3oif9lC1/256.jpg", "las_updated": "2020-09-01T04:00:00Z", "author": "me", "is_subscribed": false, "subscribers_count": 0, "genres": "culture"}}, {"context": "NEW_SUBSCRIBED_EPISODE", "id": 74070758, "time": "2020-09-01T04:00:00Z", "content": {"id": "944825608374", "title": "TranceForm (Episode 90)", "pub_date": "2020-09-01T04:00:00Z", "summary": "TranceForm (Episode 90)", "is_recommended": false, "recommendations_count": 0, "series": {"title": "Radio Javan Podcasts", "id": 82716221, "image_url_sm": "https://cdn.player.fm/images/2210354/series/CP2HKKvW3oif9lC1/64.jpg", "image_url_lg": "https://cdn.player.fm/images/2210354/series/CP2HKKvW3oif9lC1/256.jpg"}, "duration": "30", "tags": "", "audio_url": "https://host2.rj-mw1.com/media/podcast/mp3-192/2990-7e8e81ed0851dc4.mp3", "current_progress": 0.0, "real_duration_written": false}, "context_supplier": {"id": 82716221, "title": "Radio Javan Podcasts", "image_url_sm": "https://cdn.player.fm/images/2210354/series/CP2HKKvW3oif9lC1/64.jpg", "image_url_lg": "https://cdn.player.fm/images/2210354/series/CP2HKKvW3oif9lC1/256.jpg", "las_updated": "2020-09-01T04:00:00Z", "author": "me", "is_subscribed": false, "subscribers_count": 0, "genres": "culture"}}, {"context": "NEW_SUBSCRIBED_EPISODE", "id": 13907350, "time": "2020-08-30T04:00:00Z", "content": {"id": "944904015249", "title": "RJ Countdown (Aug 30, 2020)", "pub_date": "2020-08-30T04:00:00Z", "summary": "RJ Countdown (Aug 30, 2020)", "is_recommended": false, "recommendations_count": 0, "series": {"title": "Radio Javan Podcasts", "id": 82716221, "image_url_sm": "https://cdn.player.fm/images/2210354/series/CP2HKKvW3oif9lC1/64.jpg", "image_url_lg": "https://cdn.player.fm/images/2210354/series/CP2HKKvW3oif9lC1/256.jpg"}, "duration": "30", "tags": "", "audio_url": "https://host2.rj-mw1.com/media/podcast/mp3-192/2989-63fe40eaa427360.mp3", "current_progress": 0.0, "real_duration_written": false}, "context_supplier": {"id": 82716221, "title": "Radio Javan Podcasts", "image_url_sm": "https://cdn.player.fm/images/2210354/series/CP2HKKvW3oif9lC1/64.jpg", "image_url_lg": "https://cdn.player.fm/images/2210354/series/CP2HKKvW3oif9lC1/256.jpg", "las_updated": "2020-08-30T04:00:00Z", "author": "me", "is_subscribed": false, "subscribers_count": 0, "genres": "culture"}}, {"context": "NEW_SUBSCRIBED_EPISODE", "id": 53272730, "time": "2020-08-27T04:00:00Z", "content": {"id": "440324023904", "title": "Chamokham (Haale Khoobe Khoone)", "pub_date": "2020-08-27T04:00:00Z", "summary": "Chamokham (Haale Khoobe Khoone)", "is_recommended": false, "recommendations_count": 0, "series": {"title": "Radio Javan Podcasts", "id": 82716221, "image_url_sm": "https://cdn.player.fm/images/2210354/series/CP2HKKvW3oif9lC1/64.jpg", "image_url_lg": "https://cdn.player.fm/images/2210354/series/CP2HKKvW3oif9lC1/256.jpg"}, "duration": "30", "tags": "", "audio_url": "https://host2.rj-mw1.com/media/podcast/mp3-192/2988-046c4d24b8bebdf.mp3", "current_progress": 0.0, "real_duration_written": false}, "context_supplier": {"id": 82716221, "title": "Radio Javan Podcasts", "image_url_sm": "https://cdn.player.fm/images/2210354/series/CP2HKKvW3oif9lC1/64.jpg", "image_url_lg": "https://cdn.player.fm/images/2210354/series/CP2HKKvW3oif9lC1/256.jpg", "las_updated": "2020-08-27T04:00:00Z", "author": "me", "is_subscribed": false, "subscribers_count": 0, "genres": "culture"}}, {"context": "NEW_SUBSCRIBED_EPISODE", "id": 56024633, "time": "2020-08-25T18:26:04Z", "content": {"id": "957095823880", "title": "Ganje Hozour audio Program #828_1", "pub_date": "2020-08-25T18:26:04Z", "summary": "Ganje Hozour audio Program #828_1", "is_recommended": false, "recommendations_count": 0, "series": {"title": "Ganj e Hozour Telephone messages", "id": 72137314, "image_url_sm": "https://cdn.player.fm/images/20704450/series/oqhLxVnLgMe9ue2N/64.jpg", "image_url_lg": "https://cdn.player.fm/images/20704450/series/oqhLxVnLgMe9ue2N/256.jpg"}, "duration": "30", "tags": "", "audio_url": "http://www.parvizshahbazi.com/Audio/828-1_Webaudio.m4a", "current_progress": 0.0, "real_duration_written": false}, "context_supplier": {"id": 72137314, "title": "Ganj e Hozour Telephone messages", "image_url_sm": "https://cdn.player.fm/images/20704450/series/oqhLxVnLgMe9ue2N/64.jpg", "image_url_lg": "https://cdn.player.fm/images/20704450/series/oqhLxVnLgMe9ue2N/256.jpg", "las_updated": "2020-08-25T18:26:04Z", "author": "me", "is_subscribed": false, "subscribers_count": 0, "genres": "culture"}}, {"context": "NEW_SUBSCRIBED_EPISODE", "id": 45212432, "time": "2020-08-25T04:00:00Z", "content": {"id": "351770260503", "title": "Ajil (Khianat)", "pub_date": "2020-08-25T04:00:00Z", "summary": "Ajil (Khianat)", "is_recommended": false, "recommendations_count": 0, "series": {"title": "Radio Javan Podcasts", "id": 82716221, "image_url_sm": "https://cdn.player.fm/images/2210354/series/CP2HKKvW3oif9lC1/64.jpg", "image_url_lg": "https://cdn.player.fm/images/2210354/series/CP2HKKvW3oif9lC1/256.jpg"}, "duration": "30", "tags": "", "audio_url": "https://host2.rj-mw1.com/media/podcast/mp3-192/2986-9c51cdf916c715a.mp3", "current_progress": 0.0, "real_duration_written": false}, "context_supplier": {"id": 82716221, "title": "Radio Javan Podcasts", "image_url_sm": "https://cdn.player.fm/images/2210354/series/CP2HKKvW3oif9lC1/64.jpg", "image_url_lg": "https://cdn.player.fm/images/2210354/series/CP2HKKvW3oif9lC1/256.jpg", "las_updated": "2020-08-25T04:00:00Z", "author": "me", "is_subscribed": false, "subscribers_count": 0, "genres": "culture"}}, {"context": "NEW_SUBSCRIBED_EPISODE", "id": 76668552, "time": "2020-08-25T04:00:00Z", "content": {"id": "58394453605", "title": "Techwich (Tech News & Cryptocurrency 2)", "pub_date": "2020-08-25T04:00:00Z", "summary": "Techwich (Tech News & Cryptocurrency 2)", "is_recommended": false, "recommendations_count": 0, "series": {"title": "Radio Javan Podcasts", "id": 82716221, "image_url_sm": "https://cdn.player.fm/images/2210354/series/CP2HKKvW3oif9lC1/64.jpg", "image_url_lg": "https://cdn.player.fm/images/2210354/series/CP2HKKvW3oif9lC1/256.jpg"}, "duration": "30", "tags": "", "audio_url": "https://host2.rj-mw1.com/media/podcast/mp3-192/2987-c31e9201e3c3812.mp3", "current_progress": 0.0, "real_duration_written": false}, "context_supplier": {"id": 82716221, "title": "Radio Javan Podcasts", "image_url_sm": "https://cdn.player.fm/images/2210354/series/CP2HKKvW3oif9lC1/64.jpg", "image_url_lg": "https://cdn.player.fm/images/2210354/series/CP2HKKvW3oif9lC1/256.jpg", "las_updated": "2020-08-25T04:00:00Z", "author": "me", "is_subscribed": false, "subscribers_count": 0, "genres": "culture"}}, {"context": "NEW_SUBSCRIBED_EPISODE", "id": 87119457, "time": "2020-08-23T04:00:00Z", "content": {"id": "180939898464", "title": "Glory Stories (Ariel & Shabahe Noorani)", "pub_date": "2020-08-23T04:00:00Z", "summary": "Glory Stories (Ariel & Shabahe Noorani)", "is_recommended": false, "recommendations_count": 0, "series": {"title": "Radio Javan Podcasts", "id": 82716221, "image_url_sm": "https://cdn.player.fm/images/2210354/series/CP2HKKvW3oif9lC1/64.jpg", "image_url_lg": "https://cdn.player.fm/images/2210354/series/CP2HKKvW3oif9lC1/256.jpg"}, "duration": "30", "tags": "", "audio_url": "https://host2.rj-mw1.com/media/podcast/mp3-192/2985-d0c7c3d4d696526.mp3", "current_progress": 0.0, "real_duration_written": false}, "context_supplier": {"id": 82716221, "title": "Radio Javan Podcasts", "image_url_sm": "https://cdn.player.fm/images/2210354/series/CP2HKKvW3oif9lC1/64.jpg", "image_url_lg": "https://cdn.player.fm/images/2210354/series/CP2HKKvW3oif9lC1/256.jpg", "las_updated": "2020-08-23T04:00:00Z", "author": "me", "is_subscribed": false, "subscribers_count": 0, "genres": "culture"}}, {"context": "NEW_SUBSCRIBED_EPISODE", "id": 13125230, "time": "2020-08-20T04:00:00Z", "content": {"id": "194000184506", "title": "Chamokham (Ramzo Raze Karsaz)", "pub_date": "2020-08-20T04:00:00Z", "summary": "Chamokham (Ramzo Raze Karsaz)", "is_recommended": false, "recommendations_count": 0, "series": {"title": "Radio Javan Podcasts", "id": 82716221, "image_url_sm": "https://cdn.player.fm/images/2210354/series/CP2HKKvW3oif9lC1/64.jpg", "image_url_lg": "https://cdn.player.fm/images/2210354/series/CP2HKKvW3oif9lC1/256.jpg"}, "duration": "30", "tags": "", "audio_url": "https://host2.rj-mw1.com/media/podcast/mp3-192/2983-7b586b5b6703448.mp3", "current_progress": 0.0, "real_duration_written": false}, "context_supplier": {"id": 82716221, "title": "Radio Javan Podcasts", "image_url_sm": "https://cdn.player.fm/images/2210354/series/CP2HKKvW3oif9lC1/64.jpg", "image_url_lg": "https://cdn.player.fm/images/2210354/series/CP2HKKvW3oif9lC1/256.jpg", "las_updated": "2020-08-20T04:00:00Z", "author": "me", "is_subscribed": false, "subscribers_count": 0, "genres": "culture"}}, {"context": "NEW_SUBSCRIBED_EPISODE", "id": 92968800, "time": "2020-08-20T04:00:00Z", "content": {"id": "369996808468", "title": "Mohsen's House (Episode 97)", "pub_date": "2020-08-20T04:00:00Z", "summary": "Mohsen's House (Episode 97)", "is_recommended": false, "recommendations_count": 0, "series": {"title": "Radio Javan Podcasts", "id": 82716221, "image_url_sm": "https://cdn.player.fm/images/2210354/series/CP2HKKvW3oif9lC1/64.jpg", "image_url_lg": "https://cdn.player.fm/images/2210354/series/CP2HKKvW3oif9lC1/256.jpg"}, "duration": "30", "tags": "", "audio_url": "https://host2.rj-mw1.com/media/podcast/mp3-192/2984-d552cb5aa55f384.mp3", "current_progress": 0.0, "real_duration_written": false}, "context_supplier": {"id": 82716221, "title": "Radio Javan Podcasts", "image_url_sm": "https://cdn.player.fm/images/2210354/series/CP2HKKvW3oif9lC1/64.jpg", "image_url_lg": "https://cdn.player.fm/images/2210354/series/CP2HKKvW3oif9lC1/256.jpg", "las_updated": "2020-08-20T04:00:00Z", "author": "me", "is_subscribed": false, "subscribers_count": 0, "genres": "culture"}}, {"context": "NEW_SUBSCRIBED_EPISODE", "id": 11495591, "time": "2020-08-19T20:54:40Z", "content": {"id": "512762181508", "title": "Ganje Hozour audio Program #827_1", "pub_date": "2020-08-19T20:54:40Z", "summary": "Ganje Hozour audio Program #827_1", "is_recommended": false, "recommendations_count": 0, "series": {"title": "Ganj e Hozour Telephone messages", "id": 72137314, "image_url_sm": "https://cdn.player.fm/images/20704450/series/oqhLxVnLgMe9ue2N/64.jpg", "image_url_lg": "https://cdn.player.fm/images/20704450/series/oqhLxVnLgMe9ue2N/256.jpg"}, "duration": "30", "tags": "", "audio_url": "http://www.parvizshahbazi.com/Audio/827-1_Webaudio.m4a", "current_progress": 0.0, "real_duration_written": false}, "context_supplier": {"id": 72137314, "title": "Ganj e Hozour Telephone messages", "image_url_sm": "https://cdn.player.fm/images/20704450/series/oqhLxVnLgMe9ue2N/64.jpg", "image_url_lg": "https://cdn.player.fm/images/20704450/series/oqhLxVnLgMe9ue2N/256.jpg", "las_updated": "2020-08-19T20:54:40Z", "author": "me", "is_subscribed": false, "subscribers_count": 0, "genres": "culture"}}, {"context": "NEW_SUBSCRIBED_EPISODE", "id": 26600312, "time": "2020-08-19T04:00:00Z", "content": {"id": "40333804192", "title": "Techwich (Tech News & Cryptocurrency)", "pub_date": "2020-08-19T04:00:00Z", "summary": "Techwich (Tech News & Cryptocurrency)", "is_recommended": false, "recommendations_count": 0, "series": {"title": "Radio Javan Podcasts", "id": 82716221, "image_url_sm": "https://cdn.player.fm/images/2210354/series/CP2HKKvW3oif9lC1/64.jpg", "image_url_lg": "https://cdn.player.fm/images/2210354/series/CP2HKKvW3oif9lC1/256.jpg"}, "duration": "30", "tags": "", "audio_url": "https://host2.rj-mw1.com/media/podcast/mp3-192/2982-bfef9f376ebd6c3.mp3", "current_progress": 0.0, "real_duration_written": false}, "context_supplier": {"id": 82716221, "title": "Radio Javan Podcasts", "image_url_sm": "https://cdn.player.fm/images/2210354/series/CP2HKKvW3oif9lC1/64.jpg", "image_url_lg": "https://cdn.player.fm/images/2210354/series/CP2HKKvW3oif9lC1/256.jpg", "las_updated": "2020-08-19T04:00:00Z", "author": "me", "is_subscribed": false, "subscribers_count": 0, "genres": "culture"}}, {"context": "NEW_SUBSCRIBED_EPISODE", "id": 23054894, "time": "2020-08-18T04:00:00Z", "content": {"id": "487274497567", "title": "Tabo Taab (Episode 2)", "pub_date": "2020-08-18T04:00:00Z", "summary": "Tabo Taab (Episode 2)", "is_recommended": false, "recommendations_count": 0, "series": {"title": "Radio Javan Podcasts", "id": 82716221, "image_url_sm": "https://cdn.player.fm/images/2210354/series/CP2HKKvW3oif9lC1/64.jpg", "image_url_lg": "https://cdn.player.fm/images/2210354/series/CP2HKKvW3oif9lC1/256.jpg"}, "duration": "30", "tags": "", "audio_url": "https://host2.rj-mw1.com/media/podcast/mp3-192/2980-69c5a04c040c2a4.mp3", "current_progress": 0.0, "real_duration_written": false}, "context_supplier": {"id": 82716221, "title": "Radio Javan Podcasts", "image_url_sm": "https://cdn.player.fm/images/2210354/series/CP2HKKvW3oif9lC1/64.jpg", "image_url_lg": "https://cdn.player.fm/images/2210354/series/CP2HKKvW3oif9lC1/256.jpg", "las_updated": "2020-08-18T04:00:00Z", "author": "me", "is_subscribed": false, "subscribers_count": 0, "genres": "culture"}}, {"context": "NEW_SUBSCRIBED_EPISODE", "id": 25112378, "time": "2020-08-18T04:00:00Z", "content": {"id": "738842072365", "title": "Ajil (Chetor Ejtemaie Bashim?)", "pub_date": "2020-08-18T04:00:00Z", "summary": "Ajil (Chetor Ejtemaie Bashim?)", "is_recommended": false, "recommendations_count": 0, "series": {"title": "Radio Javan Podcasts", "id": 82716221, "image_url_sm": "https://cdn.player.fm/images/2210354/series/CP2HKKvW3oif9lC1/64.jpg", "image_url_lg": "https://cdn.player.fm/images/2210354/series/CP2HKKvW3oif9lC1/256.jpg"}, "duration": "30", "tags": "", "audio_url": "https://host2.rj-mw1.com/media/podcast/mp3-192/2981-d000a85453da6d0.mp3", "current_progress": 0.0, "real_duration_written": false}, "context_supplier": {"id": 82716221, "title": "Radio Javan Podcasts", "image_url_sm": "https://cdn.player.fm/images/2210354/series/CP2HKKvW3oif9lC1/64.jpg", "image_url_lg": "https://cdn.player.fm/images/2210354/series/CP2HKKvW3oif9lC1/256.jpg", "las_updated": "2020-08-18T04:00:00Z", "author": "me", "is_subscribed": false, "subscribers_count": 0, "genres": "culture"}}, {"context": "NEW_SUBSCRIBED_EPISODE", "id": 62002612, "time": "2020-08-17T04:00:00Z", "content": {"id": "100351719333", "title": "Dor Dor (Episode 8 (Old School))", "pub_date": "2020-08-17T04:00:00Z", "summary": "Dor Dor (Episode 8 (Old School))", "is_recommended": false, "recommendations_count": 0, "series": {"title": "Radio Javan Podcasts", "id": 82716221, "image_url_sm": "https://cdn.player.fm/images/2210354/series/CP2HKKvW3oif9lC1/64.jpg", "image_url_lg": "https://cdn.player.fm/images/2210354/series/CP2HKKvW3oif9lC1/256.jpg"}, "duration": "30", "tags": "", "audio_url": "https://host2.rj-mw1.com/media/podcast/mp3-192/2979-cedb7bb84319d95.mp3", "current_progress": 0.0, "real_duration_written": false}, "context_supplier": {"id": 82716221, "title": "Radio Javan Podcasts", "image_url_sm": "https://cdn.player.fm/images/2210354/series/CP2HKKvW3oif9lC1/64.jpg", "image_url_lg": "https://cdn.player.fm/images/2210354/series/CP2HKKvW3oif9lC1/256.jpg", "las_updated": "2020-08-17T04:00:00Z", "author": "me", "is_subscribed": false, "subscribers_count": 0, "genres": "culture"}}, {"context": "NEW_SUBSCRIBED_EPISODE", "id": 68256022, "time": "2020-08-16T04:00:00Z", "content": {"id": "775959999653", "title": "Dance Station (Episode 26)", "pub_date": "2020-08-16T04:00:00Z", "summary": "Dance Station (Episode 26)", "is_recommended": false, "recommendations_count": 0, "series": {"title": "Radio Javan Podcasts", "id": 82716221, "image_url_sm": "https://cdn.player.fm/images/2210354/series/CP2HKKvW3oif9lC1/64.jpg", "image_url_lg": "https://cdn.player.fm/images/2210354/series/CP2HKKvW3oif9lC1/256.jpg"}, "duration": "30", "tags": "", "audio_url": "https://host2.rj-mw1.com/media/podcast/mp3-192/2978-6aff86e398a3d4d.mp3", "current_progress": 0.0, "real_duration_written": false}, "context_supplier": {"id": 82716221, "title": "Radio Javan Podcasts", "image_url_sm": "https://cdn.player.fm/images/2210354/series/CP2HKKvW3oif9lC1/64.jpg", "image_url_lg": "https://cdn.player.fm/images/2210354/series/CP2HKKvW3oif9lC1/256.jpg", "las_updated": "2020-08-16T04:00:00Z", "author": "me", "is_subscribed": false, "subscribers_count": 0, "genres": "culture"}}, {"context": "NEW_SUBSCRIBED_EPISODE", "id": 93653921, "time": "2020-08-15T15:01:05Z", "content": {"id": "564363292064", "title": "\u0642\u0633\u0645\u062a \u067e\u0627\u0646\u0632\u062f\u0647\u0645: \u0633\u0631\u0645\u0627\u06cc\u0647\u200c\u062f\u0627\u0631\u06cc \u0646\u0638\u0627\u0631\u062a\u06cc\u060c \u0628\u062e\u0634 \u0627\u0648\u0644\u061b \u062a\u0648\u0644\u062f \u0648 \u0627\u0646\u0628\u0627\u0634\u062a \u0627\u0648\u0644\u06cc\u0647 \u0627\u0637\u0644\u0627\u0639\u0627\u062a", "pub_date": "2020-08-15T15:01:05Z", "summary": "\u0642\u0633\u0645\u062a \u067e\u0627\u0646\u0632\u062f\u0647\u0645: \u0633\u0631\u0645\u0627\u06cc\u0647\u200c\u062f\u0627\u0631\u06cc \u0646\u0638\u0627\u0631\u062a\u06cc\u060c \u0628\u062e\u0634 \u0627\u0648\u0644\u061b \u062a\u0648\u0644\u062f \u0648 \u0627\u0646\u0628\u0627\u0634\u062a \u0627\u0648\u0644\u06cc\u0647 \u0627\u0637\u0644\u0627\u0639\u0627\u062a", "is_recommended": false, "recommendations_count": 0, "series": {"title": "Democracy DarKar", "id": 35522939, "image_url_sm": "https://cdn.player.fm/images/21187874/series/ixPUL7G3Vx7KzL9s/64.jpg", "image_url_lg": "https://cdn.player.fm/images/21187874/series/ixPUL7G3Vx7KzL9s/256.jpg"}, "duration": "30", "tags": "", "audio_url": "https://media.blubrry.com/datwfa/content.blubrry.com/datwfa/DatWfa_Episode_15_Surveillance_Capitalism_Birth_And_Primitive_Accumulation_of_Data.mp3", "current_progress": 0.0, "real_duration_written": false}, "context_supplier": {"id": 35522939, "title": "Democracy DarKar", "image_url_sm": "https://cdn.player.fm/images/21187874/series/ixPUL7G3Vx7KzL9s/64.jpg", "image_url_lg": "https://cdn.player.fm/images/21187874/series/ixPUL7G3Vx7KzL9s/256.jpg", "las_updated": "2020-08-15T15:01:05Z", "author": "me", "is_subscribed": false, "subscribers_count": 0, "genres": "culture"}}]