[{"context": "NEW_SUBSCRIBED_EPISODE", "id": 79990476, "time": "2018-12-01T05:00:00Z", "content": {"id": "286857849884", "title": "TranceForm (Episode 69)", "pub_date": "2018-12-01T05:00:00Z", "summary": "TranceForm (Episode 69)", "is_recommended": false, "recommendations_count": 0, "series": {"title": "Radio Javan Podcasts", "id": 24583351, "image_url_sm": "https://cdn1.player.fm/images/2210354/series/CP2HKKvW3oif9lC1/64.jpg", "image_url_lg": "https://cdn1.player.fm/images/2210354/series/CP2HKKvW3oif9lC1/256.jpg"}, "duration": "", "tags": "", "audio_url": "https://host2.rjmusicmedia.com/media/podcast/mp3-192/TranceForm-69.mp3", "current_progress": 0.0, "real_duration_written": false}, "context_supplier": {"id": 24583351, "title": "Radio Javan Podcasts", "image_url_sm": "https://cdn1.player.fm/images/2210354/series/CP2HKKvW3oif9lC1/64.jpg", "image_url_lg": "https://cdn1.player.fm/images/2210354/series/CP2HKKvW3oif9lC1/256.jpg", "las_updated": "2018-12-01T05:00:00Z", "author": "me", "is_subscribed": false, "subscribers_count": 0, "genres": "culture"}}, {"context": "NEW_SUBSCRIBED_EPISODE", "id": 44700948, "time": "2018-12-01T02:08:05Z", "content": {"id": "194420643838", "title": "30.November 2018 - \u062f\u06a9\u062a\u0631 \u0647\u0644\u0627\u06a9\u0648\u06cc\u06cc , \u0631\u0627\u0632\u0647\u0627 \u0648 \u0646\u06cc\u0627\u0632\u0647\u0627, \u0639\u0635\u0631", "pub_date": "2018-12-01T02:08:05Z", "summary": "30.November 2018 - \u062f\u06a9\u062a\u0631 \u0647\u0644\u0627\u06a9\u0648\u06cc\u06cc , \u0631\u0627\u0632\u0647\u0627 \u0648 \u0646\u06cc\u0627\u0632\u0647\u0627, \u0639\u0635\u0631", "is_recommended": false, "recommendations_count": 0, "series": {"title": "Razha va Niazha", "id": 54230894, "image_url_sm": "https://cdn1.player.fm/images/1027679/series/n237MsJ0HGRntqQU/64.png", "image_url_lg": "https://cdn1.player.fm/images/1027679/series/n237MsJ0HGRntqQU/256.png"}, "duration": "1:59:06", "tags": "", "audio_url": "http://feeds.soundcloud.com/stream/538066761-razhavaniazha-com-30-11-2018-r-e.mp3", "current_progress": 0.0, "real_duration_written": false}, "context_supplier": {"id": 54230894, "title": "Razha va Niazha", "image_url_sm": "https://cdn1.player.fm/images/1027679/series/n237MsJ0HGRntqQU/64.png", "image_url_lg": "https://cdn1.player.fm/images/1027679/series/n237MsJ0HGRntqQU/256.png", "las_updated": "2018-12-01T02:08:05Z", "author": "me", "is_subscribed": false, "subscribers_count": 0, "genres": "culture"}}, {"context": "NEW_SUBSCRIBED_EPISODE", "id": 88660204, "time": "2018-11-30T23:39:19Z", "content": {"id": "957623279241", "title": "Ganje Hozour audio Program #739_1", "pub_date": "2018-11-30T23:39:19Z", "summary": "Ganje Hozour audio Program #739_1", "is_recommended": false, "recommendations_count": 0, "series": {"title": "Ganj e Hozour Telephone messages", "id": 97938040, "image_url_sm": "https://cdn1.player.fm/images/20704450/series/oqhLxVnLgMe9ue2N/64.jpg", "image_url_lg": "https://cdn1.player.fm/images/20704450/series/oqhLxVnLgMe9ue2N/256.jpg"}, "duration": "", "tags": "", "audio_url": "http://www.parvizshahbazi.com/Audio/739-1_Webaudio.m4a", "current_progress": 0.0, "real_duration_written": false}, "context_supplier": {"id": 97938040, "title": "Ganj e Hozour Telephone messages", "image_url_sm": "https://cdn1.player.fm/images/20704450/series/oqhLxVnLgMe9ue2N/64.jpg", "image_url_lg": "https://cdn1.player.fm/images/20704450/series/oqhLxVnLgMe9ue2N/256.jpg", "las_updated": "2018-11-30T23:39:19Z", "author": "me", "is_subscribed": false, "subscribers_count": 0, "genres": "culture"}}, {"context": "NEW_SUBSCRIBED_EPISODE", "id": 90925893, "time": "2018-11-30T20:58:54Z", "content": {"id": "848097622480", "title": "Radio Rumi Program 17: Try to Be in Love!", "pub_date": "2018-11-30T20:58:54Z", "summary": "Radio Rumi Program 17: Try to Be in Love!", "is_recommended": false, "recommendations_count": 0, "series": {"title": "Radio Rumi", "id": 53171330, "image_url_sm": "https://cdn1.player.fm/images/20670553/series/rXlS8PmQMG0mEs6B/64.jpg", "image_url_lg": "https://cdn1.player.fm/images/20670553/series/rXlS8PmQMG0mEs6B/256.jpg"}, "duration": "35:35", "tags": "", "audio_url": "http://api.spreaker.com/download/episode/16354110/program17_finished.mp3", "current_progress": 0.0, "real_duration_written": false}, "context_supplier": {"id": 53171330, "title": "Radio Rumi", "image_url_sm": "https://cdn1.player.fm/images/20670553/series/rXlS8PmQMG0mEs6B/64.jpg", "image_url_lg": "https://cdn1.player.fm/images/20670553/series/rXlS8PmQMG0mEs6B/256.jpg", "las_updated": "2018-11-30T20:58:54Z", "author": "me", "is_subscribed": false, "subscribers_count": 0, "genres": "culture"}}, {"context": "NEW_SUBSCRIBED_EPISODE", "id": 47026518, "time": "2018-11-30T20:08:06Z", "content": {"id": "57944794407", "title": "30.November 2018 - \u062f\u06a9\u062a\u0631 \u0647\u0644\u0627\u06a9\u0648\u06cc\u06cc , \u0631\u0627\u0632\u0647\u0627 \u0648 \u0646\u06cc\u0627\u0632\u0647\u0627, \u0635\u0628\u062d", "pub_date": "2018-11-30T20:08:06Z", "summary": "30.November 2018 - \u062f\u06a9\u062a\u0631 \u0647\u0644\u0627\u06a9\u0648\u06cc\u06cc , \u0631\u0627\u0632\u0647\u0627 \u0648 \u0646\u06cc\u0627\u0632\u0647\u0627, \u0635\u0628\u062d", "is_recommended": false, "recommendations_count": 0, "series": {"title": "Razha va Niazha", "id": 54230894, "image_url_sm": "https://cdn1.player.fm/images/1027679/series/n237MsJ0HGRntqQU/64.png", "image_url_lg": "https://cdn1.player.fm/images/1027679/series/n237MsJ0HGRntqQU/256.png"}, "duration": "1:59:05", "tags": "", "audio_url": "http://feeds.soundcloud.com/stream/537924570-razhavaniazha-com-30-11-2018-r-m.mp3", "current_progress": 0.0, "real_duration_written": false}, "context_supplier": {"id": 54230894, "title": "Razha va Niazha", "image_url_sm": "https://cdn1.player.fm/images/1027679/series/n237MsJ0HGRntqQU/64.png", "image_url_lg": "https://cdn1.player.fm/images/1027679/series/n237MsJ0HGRntqQU/256.png", "las_updated": "2018-11-30T20:08:06Z", "author": "me", "is_subscribed": false, "subscribers_count": 0, "genres": "culture"}}, {"context": "NEW_SUBSCRIBED_EPISODE", "id": 912596, "time": "2018-11-30T18:00:24Z", "content": {"id": "459608451313", "title": "I Know You Want It!", "pub_date": "2018-11-30T18:00:24Z", "summary": "I Know You Want It!", "is_recommended": false, "recommendations_count": 0, "series": {"title": "Manoto \u0645\u0646\u200c \u0648 \u062a\u0648", "id": 17184812, "image_url_sm": "https://cdn1.player.fm/images/2074379/series/KgYoYRC972gxiCB2/64.jpg", "image_url_lg": "https://cdn1.player.fm/images/2074379/series/KgYoYRC972gxiCB2/256.jpg"}, "duration": "2:12", "tags": "", "audio_url": "http://feeds.soundcloud.com/stream/537837093-manototv-i-know-you-want-it.mp3", "current_progress": 0.0, "real_duration_written": false}, "context_supplier": {"id": 17184812, "title": "Manoto \u0645\u0646\u200c \u0648 \u062a\u0648", "image_url_sm": "https://cdn1.player.fm/images/2074379/series/KgYoYRC972gxiCB2/64.jpg", "image_url_lg": "https://cdn1.player.fm/images/2074379/series/KgYoYRC972gxiCB2/256.jpg", "las_updated": "2018-11-30T18:00:24Z", "author": "me", "is_subscribed": false, "subscribers_count": 0, "genres": "culture"}}, {"context": "NEW_SUBSCRIBED_EPISODE", "id": 80055782, "time": "2018-11-30T18:00:24Z", "content": {"id": "100341480346", "title": "\u0646\u0627\u0645\u0647\u0631\u0628\u0648\u0646\u0646", "pub_date": "2018-11-30T18:00:24Z", "summary": "\u0646\u0627\u0645\u0647\u0631\u0628\u0648\u0646\u0646", "is_recommended": false, "recommendations_count": 0, "series": {"title": "Manoto \u0645\u0646\u200c \u0648 \u062a\u0648", "id": 17184812, "image_url_sm": "https://cdn1.player.fm/images/2074379/series/KgYoYRC972gxiCB2/64.jpg", "image_url_lg": "https://cdn1.player.fm/images/2074379/series/KgYoYRC972gxiCB2/256.jpg"}, "duration": "2:39", "tags": "", "audio_url": "http://feeds.soundcloud.com/stream/537832860-manototv-4rflsrrhuxcn.mp3", "current_progress": 0.0, "real_duration_written": false}, "context_supplier": {"id": 17184812, "title": "Manoto \u0645\u0646\u200c \u0648 \u062a\u0648", "image_url_sm": "https://cdn1.player.fm/images/2074379/series/KgYoYRC972gxiCB2/64.jpg", "image_url_lg": "https://cdn1.player.fm/images/2074379/series/KgYoYRC972gxiCB2/256.jpg", "las_updated": "2018-11-30T18:00:24Z", "author": "me", "is_subscribed": false, "subscribers_count": 0, "genres": "culture"}}, {"context": "NEW_SUBSCRIBED_EPISODE", "id": 97667848, "time": "2018-11-30T02:08:04Z", "content": {"id": "250512572187", "title": "29.November 2018 - \u062f\u06a9\u062a\u0631 \u0647\u0644\u0627\u06a9\u0648\u06cc\u06cc , \u0631\u0627\u0632\u0647\u0627 \u0648 \u0646\u06cc\u0627\u0632\u0647\u0627, \u0639\u0635\u0631", "pub_date": "2018-11-30T02:08:04Z", "summary": "29.November 2018 - \u062f\u06a9\u062a\u0631 \u0647\u0644\u0627\u06a9\u0648\u06cc\u06cc , \u0631\u0627\u0632\u0647\u0627 \u0648 \u0646\u06cc\u0627\u0632\u0647\u0627, \u0639\u0635\u0631", "is_recommended": false, "recommendations_count": 0, "series": {"title": "Razha va Niazha", "id": 54230894, "image_url_sm": "https://cdn1.player.fm/images/1027679/series/n237MsJ0HGRntqQU/64.png", "image_url_lg": "https://cdn1.player.fm/images/1027679/series/n237MsJ0HGRntqQU/256.png"}, "duration": "1:59:06", "tags": "", "audio_url": "http://feeds.soundcloud.com/stream/537547725-razhavaniazha-com-29-11-2018-r-e.mp3", "current_progress": 0.0, "real_duration_written": false}, "context_supplier": {"id": 54230894, "title": "Razha va Niazha", "image_url_sm": "https://cdn1.player.fm/images/1027679/series/n237MsJ0HGRntqQU/64.png", "image_url_lg": "https://cdn1.player.fm/images/1027679/series/n237MsJ0HGRntqQU/256.png", "las_updated": "2018-11-30T02:08:04Z", "author": "me", "is_subscribed": false, "subscribers_count": 0, "genres": "culture"}}, {"context": "NEW_SUBSCRIBED_EPISODE", "id": 28161384, "time": "2018-11-30T00:00:00Z", "content": {"id": "152868084832", "title": "\u067e\u0627\u0631\u0627\u062f\u0648\u06a9\u0633 \u0628\u0627 \u06a9\u0627\u0645\u0628\u06cc\u0632 \u062d\u0633\u06cc\u0646\u06cc", "pub_date": "2018-11-30T00:00:00Z", "summary": "\u067e\u0627\u0631\u0627\u062f\u0648\u06a9\u0633 \u0628\u0627 \u06a9\u0627\u0645\u0628\u06cc\u0632 \u062d\u0633\u06cc\u0646\u06cc", "is_recommended": false, "recommendations_count": 0, "series": {"title": "Radio Farda  \u0631\u0627\u062f\u06cc\u0648 \u0641\u0631\u062f\u0627", "id": 23502008, "image_url_sm": "https://cdn1.player.fm/images/19614466/series/Jmzvxbwtrj7SwcyY/64.png", "image_url_lg": "https://cdn1.player.fm/images/19614466/series/Jmzvxbwtrj7SwcyY/256.png"}, "duration": "25:00", "tags": "", "audio_url": "http://feeds.soundcloud.com/stream/537861180-radio-farda-1ukmrbxa8rsz.mp3", "current_progress": 0.0, "real_duration_written": false}, "context_supplier": {"id": 23502008, "title": "Radio Farda  \u0631\u0627\u062f\u06cc\u0648 \u0641\u0631\u062f\u0627", "image_url_sm": "https://cdn1.player.fm/images/19614466/series/Jmzvxbwtrj7SwcyY/64.png", "image_url_lg": "https://cdn1.player.fm/images/19614466/series/Jmzvxbwtrj7SwcyY/256.png", "las_updated": "2018-11-30T00:00:00Z", "author": "me", "is_subscribed": false, "subscribers_count": 0, "genres": "culture"}}, {"context": "NEW_SUBSCRIBED_EPISODE", "id": 51882678, "time": "2018-11-30T00:00:00Z", "content": {"id": "186077532762", "title": "\u0633\u0627\u0639\u062a \u0634\u0634\u0645 - \u062e\u0627\u0626\u0646\u060c \u062e\u0627\u062f\u0645\u060c \u0631\u06cc\u0627\u06a9\u0627\u0631: \u0633\u0627\u06cc\u0647 \u0631\u0648\u0634\u0646\u200c\u0647\u0627\u06cc \u0638\u0631\u06cc\u0641", "pub_date": "2018-11-30T00:00:00Z", "summary": "\u0633\u0627\u0639\u062a \u0634\u0634\u0645 - \u062e\u0627\u0626\u0646\u060c \u062e\u0627\u062f\u0645\u060c \u0631\u06cc\u0627\u06a9\u0627\u0631: \u0633\u0627\u06cc\u0647 \u0631\u0648\u0634\u0646\u200c\u0647\u0627\u06cc \u0638\u0631\u06cc\u0641", "is_recommended": false, "recommendations_count": 0, "series": {"title": "Radio Farda  \u0631\u0627\u062f\u06cc\u0648 \u0641\u0631\u062f\u0627", "id": 23502008, "image_url_sm": "https://cdn1.player.fm/images/19614466/series/Jmzvxbwtrj7SwcyY/64.png", "image_url_lg": "https://cdn1.player.fm/images/19614466/series/Jmzvxbwtrj7SwcyY/256.png"}, "duration": "53:36", "tags": "", "audio_url": "http://feeds.soundcloud.com/stream/537878673-radio-farda-w4jye7r0k2yp.mp3", "current_progress": 0.0, "real_duration_written": false}, "context_supplier": {"id": 23502008, "title": "Radio Farda  \u0631\u0627\u062f\u06cc\u0648 \u0641\u0631\u062f\u0627", "image_url_sm": "https://cdn1.player.fm/images/19614466/series/Jmzvxbwtrj7SwcyY/64.png", "image_url_lg": "https://cdn1.player.fm/images/19614466/series/Jmzvxbwtrj7SwcyY/256.png", "las_updated": "2018-11-30T00:00:00Z", "author": "me", "is_subscribed": false, "subscribers_count": 0, "genres": "culture"}}, {"context": "NEW_SUBSCRIBED_EPISODE", "id": 51593474, "time": "2018-11-29T20:08:05Z", "content": {"id": "757487585867", "title": "29.November 2018 - \u062f\u06a9\u062a\u0631 \u0647\u0644\u0627\u06a9\u0648\u06cc\u06cc , \u0631\u0627\u0632\u0647\u0627 \u0648 \u0646\u06cc\u0627\u0632\u0647\u0627, \u0635\u0628\u062d", "pub_date": "2018-11-29T20:08:05Z", "summary": "29.November 2018 - \u062f\u06a9\u062a\u0631 \u0647\u0644\u0627\u06a9\u0648\u06cc\u06cc , \u0631\u0627\u0632\u0647\u0627 \u0648 \u0646\u06cc\u0627\u0632\u0647\u0627, \u0635\u0628\u062d", "is_recommended": false, "recommendations_count": 0, "series": {"title": "Razha va Niazha", "id": 54230894, "image_url_sm": "https://cdn1.player.fm/images/1027679/series/n237MsJ0HGRntqQU/64.png", "image_url_lg": "https://cdn1.player.fm/images/1027679/series/n237MsJ0HGRntqQU/256.png"}, "duration": "1:59:06", "tags": "", "audio_url": "http://feeds.soundcloud.com/stream/537400236-razhavaniazha-com-29-11-2018-r-m.mp3", "current_progress": 0.0, "real_duration_written": false}, "context_supplier": {"id": 54230894, "title": "Razha va Niazha", "image_url_sm": "https://cdn1.player.fm/images/1027679/series/n237MsJ0HGRntqQU/64.png", "image_url_lg": "https://cdn1.player.fm/images/1027679/series/n237MsJ0HGRntqQU/256.png", "las_updated": "2018-11-29T20:08:05Z", "author": "me", "is_subscribed": false, "subscribers_count": 0, "genres": "culture"}}, {"context": "NEW_SUBSCRIBED_EPISODE", "id": 5364553, "time": "2018-11-29T05:00:00Z", "content": {"id": "476553852505", "title": "Dynatomix (Episode 33)", "pub_date": "2018-11-29T05:00:00Z", "summary": "Dynatomix (Episode 33)", "is_recommended": false, "recommendations_count": 0, "series": {"title": "Radio Javan Podcasts", "id": 24583351, "image_url_sm": "https://cdn1.player.fm/images/2210354/series/CP2HKKvW3oif9lC1/64.jpg", "image_url_lg": "https://cdn1.player.fm/images/2210354/series/CP2HKKvW3oif9lC1/256.jpg"}, "duration": "", "tags": "", "audio_url": "https://host2.rjmusicmedia.com/media/podcast/mp3-192/Dynatomix-33.mp3", "current_progress": 0.0, "real_duration_written": false}, "context_supplier": {"id": 24583351, "title": "Radio Javan Podcasts", "image_url_sm": "https://cdn1.player.fm/images/2210354/series/CP2HKKvW3oif9lC1/64.jpg", "image_url_lg": "https://cdn1.player.fm/images/2210354/series/CP2HKKvW3oif9lC1/256.jpg", "las_updated": "2018-11-29T05:00:00Z", "author": "me", "is_subscribed": false, "subscribers_count": 0, "genres": "culture"}}, {"context": "NEW_SUBSCRIBED_EPISODE", "id": 2764453, "time": "2018-11-29T05:00:00Z", "content": {"id": "958347123004", "title": "Khodcast (116 - Types of Power)", "pub_date": "2018-11-29T05:00:00Z", "summary": "Khodcast (116 - Types of Power)", "is_recommended": false, "recommendations_count": 0, "series": {"title": "Radio Javan Podcasts", "id": 24583351, "image_url_sm": "https://cdn1.player.fm/images/2210354/series/CP2HKKvW3oif9lC1/64.jpg", "image_url_lg": "https://cdn1.player.fm/images/2210354/series/CP2HKKvW3oif9lC1/256.jpg"}, "duration": "", "tags": "", "audio_url": "https://host2.rjmusicmedia.com/media/podcast/mp3-192/Khodcast-116.mp3", "current_progress": 0.0, "real_duration_written": false}, "context_supplier": {"id": 24583351, "title": "Radio Javan Podcasts", "image_url_sm": "https://cdn1.player.fm/images/2210354/series/CP2HKKvW3oif9lC1/64.jpg", "image_url_lg": "https://cdn1.player.fm/images/2210354/series/CP2HKKvW3oif9lC1/256.jpg", "las_updated": "2018-11-29T05:00:00Z", "author": "me", "is_subscribed": false, "subscribers_count": 0, "genres": "culture"}}, {"context": "NEW_SUBSCRIBED_EPISODE", "id": 42857512, "time": "2018-11-29T02:08:03Z", "content": {"id": "186434466496", "title": "28.November 2018 - \u062f\u06a9\u062a\u0631 \u0647\u0644\u0627\u06a9\u0648\u06cc\u06cc , \u0631\u0627\u0632\u0647\u0627 \u0648 \u0646\u06cc\u0627\u0632\u0647\u0627, \u0639\u0635\u0631", "pub_date": "2018-11-29T02:08:03Z", "summary": "28.November 2018 - \u062f\u06a9\u062a\u0631 \u0647\u0644\u0627\u06a9\u0648\u06cc\u06cc , \u0631\u0627\u0632\u0647\u0627 \u0648 \u0646\u06cc\u0627\u0632\u0647\u0627, \u0639\u0635\u0631", "is_recommended": false, "recommendations_count": 0, "series": {"title": "Razha va Niazha", "id": 54230894, "image_url_sm": "https://cdn1.player.fm/images/1027679/series/n237MsJ0HGRntqQU/64.png", "image_url_lg": "https://cdn1.player.fm/images/1027679/series/n237MsJ0HGRntqQU/256.png"}, "duration": "1:59:06", "tags": "", "audio_url": "http://feeds.soundcloud.com/stream/537028371-razhavaniazha-com-28-11-2018-r-e.mp3", "current_progress": 0.0, "real_duration_written": false}, "context_supplier": {"id": 54230894, "title": "Razha va Niazha", "image_url_sm": "https://cdn1.player.fm/images/1027679/series/n237MsJ0HGRntqQU/64.png", "image_url_lg": "https://cdn1.player.fm/images/1027679/series/n237MsJ0HGRntqQU/256.png", "las_updated": "2018-11-29T02:08:03Z", "author": "me", "is_subscribed": false, "subscribers_count": 0, "genres": "culture"}}, {"context": "NEW_SUBSCRIBED_EPISODE", "id": 10574307, "time": "2018-11-29T00:08:04Z", "content": {"id": "456305148878", "title": "28.November 2018 - \u062f\u06a9\u062a\u0631 \u0647\u0644\u0627\u06a9\u0648\u0626\u06cc \u0647\u0645\u0631\u0627\u0647 \u0628\u0627 \u0639\u0644\u06cc\u0631\u0636\u0627 \u0645\u06cc\u0628\u062f\u06cc", "pub_date": "2018-11-29T00:08:04Z", "summary": "28.November 2018 - \u062f\u06a9\u062a\u0631 \u0647\u0644\u0627\u06a9\u0648\u0626\u06cc \u0647\u0645\u0631\u0627\u0647 \u0628\u0627 \u0639\u0644\u06cc\u0631\u0636\u0627 \u0645\u06cc\u0628\u062f\u06cc", "is_recommended": false, "recommendations_count": 0, "series": {"title": "Razha va Niazha", "id": 54230894, "image_url_sm": "https://cdn1.player.fm/images/1027679/series/n237MsJ0HGRntqQU/64.png", "image_url_lg": "https://cdn1.player.fm/images/1027679/series/n237MsJ0HGRntqQU/256.png"}, "duration": "1:59:06", "tags": "", "audio_url": "http://feeds.soundcloud.com/stream/536984574-razhavaniazha-com-28-11-2018-h-m.mp3", "current_progress": 0.0, "real_duration_written": false}, "context_supplier": {"id": 54230894, "title": "Razha va Niazha", "image_url_sm": "https://cdn1.player.fm/images/1027679/series/n237MsJ0HGRntqQU/64.png", "image_url_lg": "https://cdn1.player.fm/images/1027679/series/n237MsJ0HGRntqQU/256.png", "las_updated": "2018-11-29T00:08:04Z", "author": "me", "is_subscribed": false, "subscribers_count": 0, "genres": "culture"}}, {"context": "NEW_SUBSCRIBED_EPISODE", "id": 18779590, "time": "2018-11-29T00:00:00Z", "content": {"id": "227190370214", "title": "\u06af\u0646\u0627\u0647 \u06cc\u0627 \u0627\u0645\u0631 \u063a\u06cc\u0631\u0627\u062e\u0644\u0627\u0642\u06cc\u061b \u06a9\u062f\u0627\u0645 \u0645\u0647\u0645 \u0627\u0633\u062a\u061f", "pub_date": "2018-11-29T00:00:00Z", "summary": "\u06af\u0646\u0627\u0647 \u06cc\u0627 \u0627\u0645\u0631 \u063a\u06cc\u0631\u0627\u062e\u0644\u0627\u0642\u06cc\u061b \u06a9\u062f\u0627\u0645 \u0645\u0647\u0645 \u0627\u0633\u062a\u061f", "is_recommended": false, "recommendations_count": 0, "series": {"title": "Radio Farda  \u0631\u0627\u062f\u06cc\u0648 \u0641\u0631\u062f\u0627", "id": 23502008, "image_url_sm": "https://cdn1.player.fm/images/19614466/series/Jmzvxbwtrj7SwcyY/64.png", "image_url_lg": "https://cdn1.player.fm/images/19614466/series/Jmzvxbwtrj7SwcyY/256.png"}, "duration": "24:47", "tags": "", "audio_url": "http://feeds.soundcloud.com/stream/537441567-radio-farda-hvao5uubumrw.mp3", "current_progress": 0.0, "real_duration_written": false}, "context_supplier": {"id": 23502008, "title": "Radio Farda  \u0631\u0627\u062f\u06cc\u0648 \u0641\u0631\u062f\u0627", "image_url_sm": "https://cdn1.player.fm/images/19614466/series/Jmzvxbwtrj7SwcyY/64.png", "image_url_lg": "https://cdn1.player.fm/images/19614466/series/Jmzvxbwtrj7SwcyY/256.png", "las_updated": "2018-11-29T00:00:00Z", "author": "me", "is_subscribed": false, "subscribers_count": 0, "genres": "culture"}}, {"context": "NEW_SUBSCRIBED_EPISODE", "id": 14645289, "time": "2018-11-28T20:08:04Z", "content": {"id": "156155319098", "title": "28.November 2018 - \u062f\u06a9\u062a\u0631 \u0647\u0644\u0627\u06a9\u0648\u06cc\u06cc , \u0631\u0627\u0632\u0647\u0627 \u0648 \u0646\u06cc\u0627\u0632\u0647\u0627, \u0635\u0628\u062d", "pub_date": "2018-11-28T20:08:04Z", "summary": "28.November 2018 - \u062f\u06a9\u062a\u0631 \u0647\u0644\u0627\u06a9\u0648\u06cc\u06cc , \u0631\u0627\u0632\u0647\u0627 \u0648 \u0646\u06cc\u0627\u0632\u0647\u0627, \u0635\u0628\u062d", "is_recommended": false, "recommendations_count": 0, "series": {"title": "Razha va Niazha", "id": 54230894, "image_url_sm": "https://cdn1.player.fm/images/1027679/series/n237MsJ0HGRntqQU/64.png", "image_url_lg": "https://cdn1.player.fm/images/1027679/series/n237MsJ0HGRntqQU/256.png"}, "duration": "1:59:06", "tags": "", "audio_url": "http://feeds.soundcloud.com/stream/536876226-razhavaniazha-com-28-11-2018-r-m.mp3", "current_progress": 0.0, "real_duration_written": false}, "context_supplier": {"id": 54230894, "title": "Razha va Niazha", "image_url_sm": "https://cdn1.player.fm/images/1027679/series/n237MsJ0HGRntqQU/64.png", "image_url_lg": "https://cdn1.player.fm/images/1027679/series/n237MsJ0HGRntqQU/256.png", "las_updated": "2018-11-28T20:08:04Z", "author": "me", "is_subscribed": false, "subscribers_count": 0, "genres": "culture"}}, {"context": "NEW_SUBSCRIBED_EPISODE", "id": 97028736, "time": "2018-11-28T17:49:33Z", "content": {"id": "471714605651", "title": "Ganje Hozour audio Program #738_1", "pub_date": "2018-11-28T17:49:33Z", "summary": "Ganje Hozour audio Program #738_1", "is_recommended": false, "recommendations_count": 0, "series": {"title": "Ganj e Hozour Telephone messages", "id": 97938040, "image_url_sm": "https://cdn1.player.fm/images/20704450/series/oqhLxVnLgMe9ue2N/64.jpg", "image_url_lg": "https://cdn1.player.fm/images/20704450/series/oqhLxVnLgMe9ue2N/256.jpg"}, "duration": "", "tags": "", "audio_url": "http://www.parvizshahbazi.com/Audio/738-1_Webaudio.m4a", "current_progress": 0.0, "real_duration_written": false}, "context_supplier": {"id": 97938040, "title": "Ganj e Hozour Telephone messages", "image_url_sm": "https://cdn1.player.fm/images/20704450/series/oqhLxVnLgMe9ue2N/64.jpg", "image_url_lg": "https://cdn1.player.fm/images/20704450/series/oqhLxVnLgMe9ue2N/256.jpg", "las_updated": "2018-11-28T17:49:33Z", "author": "me", "is_subscribed": false, "subscribers_count": 0, "genres": "culture"}}, {"context": "NEW_SUBSCRIBED_EPISODE", "id": 7341954, "time": "2018-11-28T02:08:02Z", "content": {"id": "433865343587", "title": "27.November 2018 - \u062f\u06a9\u062a\u0631 \u0647\u0644\u0627\u06a9\u0648\u06cc\u06cc , \u0631\u0627\u0632\u0647\u0627 \u0648 \u0646\u06cc\u0627\u0632\u0647\u0627, \u0639\u0635\u0631", "pub_date": "2018-11-28T02:08:02Z", "summary": "27.November 2018 - \u062f\u06a9\u062a\u0631 \u0647\u0644\u0627\u06a9\u0648\u06cc\u06cc , \u0631\u0627\u0632\u0647\u0627 \u0648 \u0646\u06cc\u0627\u0632\u0647\u0627, \u0639\u0635\u0631", "is_recommended": false, "recommendations_count": 0, "series": {"title": "Razha va Niazha", "id": 54230894, "image_url_sm": "https://cdn1.player.fm/images/1027679/series/n237MsJ0HGRntqQU/64.png", "image_url_lg": "https://cdn1.player.fm/images/1027679/series/n237MsJ0HGRntqQU/256.png"}, "duration": "1:59:05", "tags": "", "audio_url": "http://feeds.soundcloud.com/stream/536533551-razhavaniazha-com-27-11-2018-r-e.mp3", "current_progress": 0.0, "real_duration_written": false}, "context_supplier": {"id": 54230894, "title": "Razha va Niazha", "image_url_sm": "https://cdn1.player.fm/images/1027679/series/n237MsJ0HGRntqQU/64.png", "image_url_lg": "https://cdn1.player.fm/images/1027679/series/n237MsJ0HGRntqQU/256.png", "las_updated": "2018-11-28T02:08:02Z", "author": "me", "is_subscribed": false, "subscribers_count": 0, "genres": "culture"}}, {"context": "NEW_SUBSCRIBED_EPISODE", "id": 29461641, "time": "2018-11-27T20:45:00Z", "content": {"id": "19485628036", "title": "Toranj-28-11-2018 Steps to Buy A House Part 5", "pub_date": "2018-11-27T20:45:00Z", "summary": "Toranj-28-11-2018 Steps to Buy A House Part 5", "is_recommended": false, "recommendations_count": 0, "series": {"title": "Toranj", "id": 2447873, "image_url_sm": "https://cdn1.player.fm/images/16403860/series/eGg5OFKoNQoVZSLO/64.png", "image_url_lg": "https://cdn1.player.fm/images/16403860/series/eGg5OFKoNQoVZSLO/256.png"}, "duration": "24:40", "tags": "", "audio_url": "https://cdn.accessradio.org/StationFolder/plainsfm/Toranj%2028%20Nov.mp3", "current_progress": 0.0, "real_duration_written": false}, "context_supplier": {"id": 2447873, "title": "Toranj", "image_url_sm": "https://cdn1.player.fm/images/16403860/series/eGg5OFKoNQoVZSLO/64.png", "image_url_lg": "https://cdn1.player.fm/images/16403860/series/eGg5OFKoNQoVZSLO/256.png", "las_updated": "2018-11-27T20:45:00Z", "author": "me", "is_subscribed": false, "subscribers_count": 0, "genres": "culture"}}, {"context": "NEW_SUBSCRIBED_EPISODE", "id": 35490379, "time": "2018-11-27T20:08:05Z", "content": {"id": "402035756960", "title": "27.November 2018 - \u062f\u06a9\u062a\u0631 \u0647\u0644\u0627\u06a9\u0648\u06cc\u06cc , \u0631\u0627\u0632\u0647\u0627 \u0648 \u0646\u06cc\u0627\u0632\u0647\u0627, \u0635\u0628\u062d", "pub_date": "2018-11-27T20:08:05Z", "summary": "27.November 2018 - \u062f\u06a9\u062a\u0631 \u0647\u0644\u0627\u06a9\u0648\u06cc\u06cc , \u0631\u0627\u0632\u0647\u0627 \u0648 \u0646\u06cc\u0627\u0632\u0647\u0627, \u0635\u0628\u062d", "is_recommended": false, "recommendations_count": 0, "series": {"title": "Razha va Niazha", "id": 54230894, "image_url_sm": "https://cdn1.player.fm/images/1027679/series/n237MsJ0HGRntqQU/64.png", "image_url_lg": "https://cdn1.player.fm/images/1027679/series/n237MsJ0HGRntqQU/256.png"}, "duration": "1:59:06", "tags": "", "audio_url": "http://feeds.soundcloud.com/stream/536380164-razhavaniazha-com-27-11-2018-r-m.mp3", "current_progress": 0.0, "real_duration_written": false}, "context_supplier": {"id": 54230894, "title": "Razha va Niazha", "image_url_sm": "https://cdn1.player.fm/images/1027679/series/n237MsJ0HGRntqQU/64.png", "image_url_lg": "https://cdn1.player.fm/images/1027679/series/n237MsJ0HGRntqQU/256.png", "las_updated": "2018-11-27T20:08:05Z", "author": "me", "is_subscribed": false, "subscribers_count": 0, "genres": "culture"}}, {"context": "NEW_SUBSCRIBED_EPISODE", "id": 80392641, "time": "2018-11-27T05:00:00Z", "content": {"id": "501374737004", "title": "Khodcast (115 - Decision Angles)", "pub_date": "2018-11-27T05:00:00Z", "summary": "Khodcast (115 - Decision Angles)", "is_recommended": false, "recommendations_count": 0, "series": {"title": "Radio Javan Podcasts", "id": 24583351, "image_url_sm": "https://cdn1.player.fm/images/2210354/series/CP2HKKvW3oif9lC1/64.jpg", "image_url_lg": "https://cdn1.player.fm/images/2210354/series/CP2HKKvW3oif9lC1/256.jpg"}, "duration": "", "tags": "", "audio_url": "https://host2.rjmusicmedia.com/media/podcast/mp3-192/Khodcast-115.mp3", "current_progress": 0.0, "real_duration_written": false}, "context_supplier": {"id": 24583351, "title": "Radio Javan Podcasts", "image_url_sm": "https://cdn1.player.fm/images/2210354/series/CP2HKKvW3oif9lC1/64.jpg", "image_url_lg": "https://cdn1.player.fm/images/2210354/series/CP2HKKvW3oif9lC1/256.jpg", "las_updated": "2018-11-27T05:00:00Z", "author": "me", "is_subscribed": false, "subscribers_count": 0, "genres": "culture"}}, {"context": "NEW_SUBSCRIBED_EPISODE", "id": 66309908, "time": "2018-11-27T02:08:02Z", "content": {"id": "269085731692", "title": "26.November 2018 - \u062f\u06a9\u062a\u0631 \u0647\u0644\u0627\u06a9\u0648\u06cc\u06cc , \u0631\u0627\u0632\u0647\u0627 \u0648 \u0646\u06cc\u0627\u0632\u0647\u0627, \u0639\u0635\u0631", "pub_date": "2018-11-27T02:08:02Z", "summary": "26.November 2018 - \u062f\u06a9\u062a\u0631 \u0647\u0644\u0627\u06a9\u0648\u06cc\u06cc , \u0631\u0627\u0632\u0647\u0627 \u0648 \u0646\u06cc\u0627\u0632\u0647\u0627, \u0639\u0635\u0631", "is_recommended": false, "recommendations_count": 0, "series": {"title": "Razha va Niazha", "id": 54230894, "image_url_sm": "https://cdn1.player.fm/images/1027679/series/n237MsJ0HGRntqQU/64.png", "image_url_lg": "https://cdn1.player.fm/images/1027679/series/n237MsJ0HGRntqQU/256.png"}, "duration": "1:59:06", "tags": "", "audio_url": "http://feeds.soundcloud.com/stream/536027493-razhavaniazha-com-26-11-2018-r-e.mp3", "current_progress": 0.0, "real_duration_written": false}, "context_supplier": {"id": 54230894, "title": "Razha va Niazha", "image_url_sm": "https://cdn1.player.fm/images/1027679/series/n237MsJ0HGRntqQU/64.png", "image_url_lg": "https://cdn1.player.fm/images/1027679/series/n237MsJ0HGRntqQU/256.png", "las_updated": "2018-11-27T02:08:02Z", "author": "me", "is_subscribed": false, "subscribers_count": 0, "genres": "culture"}}, {"context": "NEW_SUBSCRIBED_EPISODE", "id": 87586279, "time": "2018-11-26T20:09:06Z", "content": {"id": "440925387546", "title": "26.November 2018 - \u062f\u06a9\u062a\u0631 \u0647\u0644\u0627\u06a9\u0648\u06cc\u06cc , \u0631\u0627\u0632\u0647\u0627 \u0648 \u0646\u06cc\u0627\u0632\u0647\u0627, \u0635\u0628\u062d", "pub_date": "2018-11-26T20:09:06Z", "summary": "26.November 2018 - \u062f\u06a9\u062a\u0631 \u0647\u0644\u0627\u06a9\u0648\u06cc\u06cc , \u0631\u0627\u0632\u0647\u0627 \u0648 \u0646\u06cc\u0627\u0632\u0647\u0627, \u0635\u0628\u062d", "is_recommended": false, "recommendations_count": 0, "series": {"title": "Razha va Niazha", "id": 54230894, "image_url_sm": "https://cdn1.player.fm/images/1027679/series/n237MsJ0HGRntqQU/64.png", "image_url_lg": "https://cdn1.player.fm/images/1027679/series/n237MsJ0HGRntqQU/256.png"}, "duration": "1:59:06", "tags": "", "audio_url": "http://feeds.soundcloud.com/stream/535871091-razhavaniazha-com-26-11-2018-r-m0.mp3", "current_progress": 0.0, "real_duration_written": false}, "context_supplier": {"id": 54230894, "title": "Razha va Niazha", "image_url_sm": "https://cdn1.player.fm/images/1027679/series/n237MsJ0HGRntqQU/64.png", "image_url_lg": "https://cdn1.player.fm/images/1027679/series/n237MsJ0HGRntqQU/256.png", "las_updated": "2018-11-26T20:09:06Z", "author": "me", "is_subscribed": false, "subscribers_count": 0, "genres": "culture"}}, {"context": "NEW_SUBSCRIBED_EPISODE", "id": 65498470, "time": "2018-11-26T00:00:00Z", "content": {"id": "227049319336", "title": "\u0641\u0631\u0647\u0646\u06af \u067e\u0646\u0647\u0627\u0646\u06cc \u0648 \u0641\u0645\u06cc\u0646\u06cc\u0633\u0645 \u062f\u0631 \u0627\u06cc\u0631\u0627\u0646", "pub_date": "2018-11-26T00:00:00Z", "summary": "\u0641\u0631\u0647\u0646\u06af \u067e\u0646\u0647\u0627\u0646\u06cc \u0648 \u0641\u0645\u06cc\u0646\u06cc\u0633\u0645 \u062f\u0631 \u0627\u06cc\u0631\u0627\u0646", "is_recommended": false, "recommendations_count": 0, "series": {"title": "Radio Farda  \u0631\u0627\u062f\u06cc\u0648 \u0641\u0631\u062f\u0627", "id": 23502008, "image_url_sm": "https://cdn1.player.fm/images/19614466/series/Jmzvxbwtrj7SwcyY/64.png", "image_url_lg": "https://cdn1.player.fm/images/19614466/series/Jmzvxbwtrj7SwcyY/256.png"}, "duration": "10:05", "tags": "", "audio_url": "http://feeds.soundcloud.com/stream/535640556-radio-farda-rszro2e3qgp4.mp3", "current_progress": 0.0, "real_duration_written": false}, "context_supplier": {"id": 23502008, "title": "Radio Farda  \u0631\u0627\u062f\u06cc\u0648 \u0641\u0631\u062f\u0627", "image_url_sm": "https://cdn1.player.fm/images/19614466/series/Jmzvxbwtrj7SwcyY/64.png", "image_url_lg": "https://cdn1.player.fm/images/19614466/series/Jmzvxbwtrj7SwcyY/256.png", "las_updated": "2018-11-26T00:00:00Z", "author": "me", "is_subscribed": false, "subscribers_count": 0, "genres": "culture"}}, {"context": "NEW_SUBSCRIBED_EPISODE", "id": 77880336, "time": "2018-11-25T21:21:06Z", "content": {"id": "510233048200", "title": "You can now ask Siri to pass you on to Google Assistant  - \u06a9\u0627\u0631\u0628\u0631\u0627\u0646 \u0622\u06cc\u0641\u0648\u0646 \u0646\u06cc\u0632 \u0645\u06cc \u062a\u0648\u0627\u0646\u0646\u062f \u0627\u0632 \u062f\u0633\u062a\u06cc\u0627\u0631 \u0635\u0648\u062a\u06cc \u06af\u0648\u06af\u0644 (Google Assistant) \u0627\u0633\u062a\u0641\u0627\u062f\u0647 \u06a9\u0646\u0646\u062f", "pub_date": "2018-11-25T21:21:06Z", "summary": "You can now ask Siri to pass you on to Google Assistant  - \u06a9\u0627\u0631\u0628\u0631\u0627\u0646 \u0622\u06cc\u0641\u0648\u0646 \u0646\u06cc\u0632 \u0645\u06cc \u062a\u0648\u0627\u0646\u0646\u062f \u0627\u0632 \u062f\u0633\u062a\u06cc\u0627\u0631 \u0635\u0648\u062a\u06cc \u06af\u0648\u06af\u0644 (Google Assistant) \u0627\u0633\u062a\u0641\u0627\u062f\u0647 \u06a9\u0646\u0646\u062f", "is_recommended": false, "recommendations_count": 0, "series": {"title": "Khoresht-e Tech - \u062e\u0648\u0631\u0634\u062a \u062a\u06a9\u0646\u0648\u0644\u0648\u0698\u06cc", "id": 98965173, "image_url_sm": "https://cdn1.player.fm/images/19339342/series/ZCwNGVSQEp72i7HN/64.jpg", "image_url_lg": "https://cdn1.player.fm/images/19339342/series/ZCwNGVSQEp72i7HN/256.jpg"}, "duration": "10:32", "tags": "", "audio_url": "http://tracking.feedpress.it/link/18443/10839458/persian_3a2a469f-8852-47db-b825-01737e6f6ee0.mp3", "current_progress": 0.0, "real_duration_written": false}, "context_supplier": {"id": 98965173, "title": "Khoresht-e Tech - \u062e\u0648\u0631\u0634\u062a \u062a\u06a9\u0646\u0648\u0644\u0648\u0698\u06cc", "image_url_sm": "https://cdn1.player.fm/images/19339342/series/ZCwNGVSQEp72i7HN/64.jpg", "image_url_lg": "https://cdn1.player.fm/images/19339342/series/ZCwNGVSQEp72i7HN/256.jpg", "las_updated": "2018-11-25T21:21:06Z", "author": "me", "is_subscribed": false, "subscribers_count": 0, "genres": "culture"}}, {"context": "NEW_SUBSCRIBED_EPISODE", "id": 12645015, "time": "2018-11-24T05:00:00Z", "content": {"id": "824661027309", "title": "Majoon (Episode 4 (Autumn Special))", "pub_date": "2018-11-24T05:00:00Z", "summary": "Majoon (Episode 4 (Autumn Special))", "is_recommended": false, "recommendations_count": 0, "series": {"title": "Radio Javan Podcasts", "id": 24583351, "image_url_sm": "https://cdn1.player.fm/images/2210354/series/CP2HKKvW3oif9lC1/64.jpg", "image_url_lg": "https://cdn1.player.fm/images/2210354/series/CP2HKKvW3oif9lC1/256.jpg"}, "duration": "", "tags": "", "audio_url": "https://host2.rjmusicmedia.com/media/podcast/mp3-192/Majoon-4.mp3", "current_progress": 0.0, "real_duration_written": false}, "context_supplier": {"id": 24583351, "title": "Radio Javan Podcasts", "image_url_sm": "https://cdn1.player.fm/images/2210354/series/CP2HKKvW3oif9lC1/64.jpg", "image_url_lg": "https://cdn1.player.fm/images/2210354/series/CP2HKKvW3oif9lC1/256.jpg", "las_updated": "2018-11-24T05:00:00Z", "author": "me", "is_subscribed": false, "subscribers_count": 0, "genres": "culture"}}, {"context": "NEW_SUBSCRIBED_EPISODE", "id": 22569032, "time": "2018-11-24T02:07:59Z", "content": {"id": "367461300886", "title": "23.November 2018 - \u062f\u06a9\u062a\u0631 \u0647\u0644\u0627\u06a9\u0648\u06cc\u06cc , \u0631\u0627\u0632\u0647\u0627 \u0648 \u0646\u06cc\u0627\u0632\u0647\u0627, \u0639\u0635\u0631", "pub_date": "2018-11-24T02:07:59Z", "summary": "23.November 2018 - \u062f\u06a9\u062a\u0631 \u0647\u0644\u0627\u06a9\u0648\u06cc\u06cc , \u0631\u0627\u0632\u0647\u0627 \u0648 \u0646\u06cc\u0627\u0632\u0647\u0627, \u0639\u0635\u0631", "is_recommended": false, "recommendations_count": 0, "series": {"title": "Razha va Niazha", "id": 54230894, "image_url_sm": "https://cdn1.player.fm/images/1027679/series/n237MsJ0HGRntqQU/64.png", "image_url_lg": "https://cdn1.player.fm/images/1027679/series/n237MsJ0HGRntqQU/256.png"}, "duration": "1:59:06", "tags": "", "audio_url": "http://feeds.soundcloud.com/stream/534624798-razhavaniazha-com-23-11-2018-r-e.mp3", "current_progress": 0.0, "real_duration_written": false}, "context_supplier": {"id": 54230894, "title": "Razha va Niazha", "image_url_sm": "https://cdn1.player.fm/images/1027679/series/n237MsJ0HGRntqQU/64.png", "image_url_lg": "https://cdn1.player.fm/images/1027679/series/n237MsJ0HGRntqQU/256.png", "las_updated": "2018-11-24T02:07:59Z", "author": "me", "is_subscribed": false, "subscribers_count": 0, "genres": "culture"}}, {"context": "NEW_SUBSCRIBED_EPISODE", "id": 86775128, "time": "2018-11-23T20:07:56Z", "content": {"id": "741050511256", "title": "23.November 2018 - \u062f\u06a9\u062a\u0631 \u0647\u0644\u0627\u06a9\u0648\u06cc\u06cc , \u0631\u0627\u0632\u0647\u0627 \u0648 \u0646\u06cc\u0627\u0632\u0647\u0627, \u0635\u0628\u062d", "pub_date": "2018-11-23T20:07:56Z", "summary": "23.November 2018 - \u062f\u06a9\u062a\u0631 \u0647\u0644\u0627\u06a9\u0648\u06cc\u06cc , \u0631\u0627\u0632\u0647\u0627 \u0648 \u0646\u06cc\u0627\u0632\u0647\u0627, \u0635\u0628\u062d", "is_recommended": false, "recommendations_count": 0, "series": {"title": "Razha va Niazha", "id": 54230894, "image_url_sm": "https://cdn1.player.fm/images/1027679/series/n237MsJ0HGRntqQU/64.png", "image_url_lg": "https://cdn1.player.fm/images/1027679/series/n237MsJ0HGRntqQU/256.png"}, "duration": "1:59:06", "tags": "", "audio_url": "http://feeds.soundcloud.com/stream/534497790-razhavaniazha-com-23-11-2018-r-m.mp3", "current_progress": 0.0, "real_duration_written": false}, "context_supplier": {"id": 54230894, "title": "Razha va Niazha", "image_url_sm": "https://cdn1.player.fm/images/1027679/series/n237MsJ0HGRntqQU/64.png", "image_url_lg": "https://cdn1.player.fm/images/1027679/series/n237MsJ0HGRntqQU/256.png", "las_updated": "2018-11-23T20:07:56Z", "author": "me", "is_subscribed": false, "subscribers_count": 0, "genres": "culture"}}, {"context": "NEW_SUBSCRIBED_EPISODE", "id": 99361468, "time": "2018-11-23T18:00:14Z", "content": {"id": "863242429551", "title": "\u06af\u06cc\u0631 \u0645\u06cc\u062f\u06cc", "pub_date": "2018-11-23T18:00:14Z", "summary": "\u06af\u06cc\u0631 \u0645\u06cc\u062f\u06cc", "is_recommended": false, "recommendations_count": 0, "series": {"title": "Manoto \u0645\u0646\u200c \u0648 \u062a\u0648", "id": 17184812, "image_url_sm": "https://cdn1.player.fm/images/2074379/series/KgYoYRC972gxiCB2/64.jpg", "image_url_lg": "https://cdn1.player.fm/images/2074379/series/KgYoYRC972gxiCB2/256.jpg"}, "duration": "3:07", "tags": "", "audio_url": "http://feeds.soundcloud.com/stream/534415215-manototv-jirkvtznakjx.mp3", "current_progress": 0.0, "real_duration_written": false}, "context_supplier": {"id": 17184812, "title": "Manoto \u0645\u0646\u200c \u0648 \u062a\u0648", "image_url_sm": "https://cdn1.player.fm/images/2074379/series/KgYoYRC972gxiCB2/64.jpg", "image_url_lg": "https://cdn1.player.fm/images/2074379/series/KgYoYRC972gxiCB2/256.jpg", "las_updated": "2018-11-23T18:00:14Z", "author": "me", "is_subscribed": false, "subscribers_count": 0, "genres": "culture"}}, {"context": "NEW_SUBSCRIBED_EPISODE", "id": 57373740, "time": "2018-11-23T18:00:14Z", "content": {"id": "543082924958", "title": "\u062a\u062d\u0631\u06cc\u0645", "pub_date": "2018-11-23T18:00:14Z", "summary": "\u062a\u062d\u0631\u06cc\u0645", "is_recommended": false, "recommendations_count": 0, "series": {"title": "Manoto \u0645\u0646\u200c \u0648 \u062a\u0648", "id": 17184812, "image_url_sm": "https://cdn1.player.fm/images/2074379/series/KgYoYRC972gxiCB2/64.jpg", "image_url_lg": "https://cdn1.player.fm/images/2074379/series/KgYoYRC972gxiCB2/256.jpg"}, "duration": "2:11", "tags": "", "audio_url": "http://feeds.soundcloud.com/stream/534413475-manototv-pdyeivfajexi.mp3", "current_progress": 0.0, "real_duration_written": false}, "context_supplier": {"id": 17184812, "title": "Manoto \u0645\u0646\u200c \u0648 \u062a\u0648", "image_url_sm": "https://cdn1.player.fm/images/2074379/series/KgYoYRC972gxiCB2/64.jpg", "image_url_lg": "https://cdn1.player.fm/images/2074379/series/KgYoYRC972gxiCB2/256.jpg", "las_updated": "2018-11-23T18:00:14Z", "author": "me", "is_subscribed": false, "subscribers_count": 0, "genres": "culture"}}, {"context": "NEW_SUBSCRIBED_EPISODE", "id": 32061625, "time": "2018-11-23T05:00:00Z", "content": {"id": "725496243093", "title": "RJ Countdown (Nov 23, 2018)", "pub_date": "2018-11-23T05:00:00Z", "summary": "RJ Countdown (Nov 23, 2018)", "is_recommended": false, "recommendations_count": 0, "series": {"title": "Radio Javan Podcasts", "id": 24583351, "image_url_sm": "https://cdn1.player.fm/images/2210354/series/CP2HKKvW3oif9lC1/64.jpg", "image_url_lg": "https://cdn1.player.fm/images/2210354/series/CP2HKKvW3oif9lC1/256.jpg"}, "duration": "", "tags": "", "audio_url": "https://host2.rjmusicmedia.com/media/podcast/mp3-192/RJ-Countdown-20181123.mp3", "current_progress": 0.0, "real_duration_written": false}, "context_supplier": {"id": 24583351, "title": "Radio Javan Podcasts", "image_url_sm": "https://cdn1.player.fm/images/2210354/series/CP2HKKvW3oif9lC1/64.jpg", "image_url_lg": "https://cdn1.player.fm/images/2210354/series/CP2HKKvW3oif9lC1/256.jpg", "las_updated": "2018-11-23T05:00:00Z", "author": "me", "is_subscribed": false, "subscribers_count": 0, "genres": "culture"}}, {"context": "NEW_SUBSCRIBED_EPISODE", "id": 34630906, "time": "2018-11-23T02:07:54Z", "content": {"id": "968785640547", "title": "22.November 2018 - \u062f\u06a9\u062a\u0631 \u0647\u0644\u0627\u06a9\u0648\u06cc\u06cc , \u0631\u0627\u0632\u0647\u0627 \u0648 \u0646\u06cc\u0627\u0632\u0647\u0627, \u0639\u0635\u0631", "pub_date": "2018-11-23T02:07:54Z", "summary": "22.November 2018 - \u062f\u06a9\u062a\u0631 \u0647\u0644\u0627\u06a9\u0648\u06cc\u06cc , \u0631\u0627\u0632\u0647\u0627 \u0648 \u0646\u06cc\u0627\u0632\u0647\u0627, \u0639\u0635\u0631", "is_recommended": false, "recommendations_count": 0, "series": {"title": "Razha va Niazha", "id": 54230894, "image_url_sm": "https://cdn1.player.fm/images/1027679/series/n237MsJ0HGRntqQU/64.png", "image_url_lg": "https://cdn1.player.fm/images/1027679/series/n237MsJ0HGRntqQU/256.png"}, "duration": "1:59:06", "tags": "", "audio_url": "http://feeds.soundcloud.com/stream/534178638-razhavaniazha-com-22-11-2018-r-e.mp3", "current_progress": 0.0, "real_duration_written": false}, "context_supplier": {"id": 54230894, "title": "Razha va Niazha", "image_url_sm": "https://cdn1.player.fm/images/1027679/series/n237MsJ0HGRntqQU/64.png", "image_url_lg": "https://cdn1.player.fm/images/1027679/series/n237MsJ0HGRntqQU/256.png", "las_updated": "2018-11-23T02:07:54Z", "author": "me", "is_subscribed": false, "subscribers_count": 0, "genres": "culture"}}, {"context": "NEW_SUBSCRIBED_EPISODE", "id": 54769583, "time": "2018-11-23T00:00:00Z", "content": {"id": "262072312576", "title": "\u0633\u0627\u0639\u062a \u0634\u0634\u0645 - \u00ab\u067e\u0634\u062a \u0628\u0647 \u062f\u0634\u0645\u0646\u00bb\u061b \u0628\u0631\u0631\u0633\u06cc \u0627\u0639\u062a\u0631\u0627\u0636 \u06a9\u0627\u0631\u06af\u0631\u0627\u0646", "pub_date": "2018-11-23T00:00:00Z", "summary": "\u0633\u0627\u0639\u062a \u0634\u0634\u0645 - \u00ab\u067e\u0634\u062a \u0628\u0647 \u062f\u0634\u0645\u0646\u00bb\u061b \u0628\u0631\u0631\u0633\u06cc \u0627\u0639\u062a\u0631\u0627\u0636 \u06a9\u0627\u0631\u06af\u0631\u0627\u0646", "is_recommended": false, "recommendations_count": 0, "series": {"title": "Radio Farda  \u0631\u0627\u062f\u06cc\u0648 \u0641\u0631\u062f\u0627", "id": 23502008, "image_url_sm": "https://cdn1.player.fm/images/19614466/series/Jmzvxbwtrj7SwcyY/64.png", "image_url_lg": "https://cdn1.player.fm/images/19614466/series/Jmzvxbwtrj7SwcyY/256.png"}, "duration": "54:00", "tags": "", "audio_url": "http://feeds.soundcloud.com/stream/534428169-radio-farda-dt7m9qrbdjat.mp3", "current_progress": 0.0, "real_duration_written": false}, "context_supplier": {"id": 23502008, "title": "Radio Farda  \u0631\u0627\u062f\u06cc\u0648 \u0641\u0631\u062f\u0627", "image_url_sm": "https://cdn1.player.fm/images/19614466/series/Jmzvxbwtrj7SwcyY/64.png", "image_url_lg": "https://cdn1.player.fm/images/19614466/series/Jmzvxbwtrj7SwcyY/256.png", "las_updated": "2018-11-23T00:00:00Z", "author": "me", "is_subscribed": false, "subscribers_count": 0, "genres": "culture"}}, {"context": "NEW_SUBSCRIBED_EPISODE", "id": 70379535, "time": "2018-11-22T20:07:35Z", "content": {"id": "778215692056", "title": "22.November 2018 - \u062f\u06a9\u062a\u0631 \u0647\u0644\u0627\u06a9\u0648\u06cc\u06cc , \u0631\u0627\u0632\u0647\u0627 \u0648 \u0646\u06cc\u0627\u0632\u0647\u0627, \u0635\u0628\u062d", "pub_date": "2018-11-22T20:07:35Z", "summary": "22.November 2018 - \u062f\u06a9\u062a\u0631 \u0647\u0644\u0627\u06a9\u0648\u06cc\u06cc , \u0631\u0627\u0632\u0647\u0627 \u0648 \u0646\u06cc\u0627\u0632\u0647\u0627, \u0635\u0628\u062d", "is_recommended": false, "recommendations_count": 0, "series": {"title": "Razha va Niazha", "id": 54230894, "image_url_sm": "https://cdn1.player.fm/images/1027679/series/n237MsJ0HGRntqQU/64.png", "image_url_lg": "https://cdn1.player.fm/images/1027679/series/n237MsJ0HGRntqQU/256.png"}, "duration": "1:23:04", "tags": "", "audio_url": "http://feeds.soundcloud.com/stream/534052038-razhavaniazha-com-22-11-2018-r-m.mp3", "current_progress": 0.0, "real_duration_written": false}, "context_supplier": {"id": 54230894, "title": "Razha va Niazha", "image_url_sm": "https://cdn1.player.fm/images/1027679/series/n237MsJ0HGRntqQU/64.png", "image_url_lg": "https://cdn1.player.fm/images/1027679/series/n237MsJ0HGRntqQU/256.png", "las_updated": "2018-11-22T20:07:35Z", "author": "me", "is_subscribed": false, "subscribers_count": 0, "genres": "culture"}}, {"context": "NEW_SUBSCRIBED_EPISODE", "id": 9997076, "time": "2018-11-22T05:00:00Z", "content": {"id": "576308963183", "title": "Databass (Episode 59)", "pub_date": "2018-11-22T05:00:00Z", "summary": "Databass (Episode 59)", "is_recommended": false, "recommendations_count": 0, "series": {"title": "Radio Javan Podcasts", "id": 24583351, "image_url_sm": "https://cdn1.player.fm/images/2210354/series/CP2HKKvW3oif9lC1/64.jpg", "image_url_lg": "https://cdn1.player.fm/images/2210354/series/CP2HKKvW3oif9lC1/256.jpg"}, "duration": "", "tags": "", "audio_url": "https://host2.rjmusicmedia.com/media/podcast/mp3-192/Databass-59.mp3", "current_progress": 0.0, "real_duration_written": false}, "context_supplier": {"id": 24583351, "title": "Radio Javan Podcasts", "image_url_sm": "https://cdn1.player.fm/images/2210354/series/CP2HKKvW3oif9lC1/64.jpg", "image_url_lg": "https://cdn1.player.fm/images/2210354/series/CP2HKKvW3oif9lC1/256.jpg", "las_updated": "2018-11-22T05:00:00Z", "author": "me", "is_subscribed": false, "subscribers_count": 0, "genres": "culture"}}, {"context": "NEW_SUBSCRIBED_EPISODE", "id": 74249755, "time": "2018-11-22T05:00:00Z", "content": {"id": "222643643199", "title": "Khodcast (114 - Bias)", "pub_date": "2018-11-22T05:00:00Z", "summary": "Khodcast (114 - Bias)", "is_recommended": false, "recommendations_count": 0, "series": {"title": "Radio Javan Podcasts", "id": 24583351, "image_url_sm": "https://cdn1.player.fm/images/2210354/series/CP2HKKvW3oif9lC1/64.jpg", "image_url_lg": "https://cdn1.player.fm/images/2210354/series/CP2HKKvW3oif9lC1/256.jpg"}, "duration": "", "tags": "", "audio_url": "https://host2.rjmusicmedia.com/media/podcast/mp3-192/Khodcast-3-4-2.mp3", "current_progress": 0.0, "real_duration_written": false}, "context_supplier": {"id": 24583351, "title": "Radio Javan Podcasts", "image_url_sm": "https://cdn1.player.fm/images/2210354/series/CP2HKKvW3oif9lC1/64.jpg", "image_url_lg": "https://cdn1.player.fm/images/2210354/series/CP2HKKvW3oif9lC1/256.jpg", "las_updated": "2018-11-22T05:00:00Z", "author": "me", "is_subscribed": false, "subscribers_count": 0, "genres": "culture"}}, {"context": "NEW_SUBSCRIBED_EPISODE", "id": 88513020, "time": "2018-11-22T02:07:53Z", "content": {"id": "426053461383", "title": "21.November 2018 - \u062f\u06a9\u062a\u0631 \u0647\u0644\u0627\u06a9\u0648\u06cc\u06cc , \u0631\u0627\u0632\u0647\u0627 \u0648 \u0646\u06cc\u0627\u0632\u0647\u0627, \u0639\u0635\u0631", "pub_date": "2018-11-22T02:07:53Z", "summary": "21.November 2018 - \u062f\u06a9\u062a\u0631 \u0647\u0644\u0627\u06a9\u0648\u06cc\u06cc , \u0631\u0627\u0632\u0647\u0627 \u0648 \u0646\u06cc\u0627\u0632\u0647\u0627, \u0639\u0635\u0631", "is_recommended": false, "recommendations_count": 0, "series": {"title": "Razha va Niazha", "id": 54230894, "image_url_sm": "https://cdn1.player.fm/images/1027679/series/n237MsJ0HGRntqQU/64.png", "image_url_lg": "https://cdn1.player.fm/images/1027679/series/n237MsJ0HGRntqQU/256.png"}, "duration": "1:59:06", "tags": "", "audio_url": "http://feeds.soundcloud.com/stream/533699655-razhavaniazha-com-21-11-2018-r-e.mp3", "current_progress": 0.0, "real_duration_written": false}, "context_supplier": {"id": 54230894, "title": "Razha va Niazha", "image_url_sm": "https://cdn1.player.fm/images/1027679/series/n237MsJ0HGRntqQU/64.png", "image_url_lg": "https://cdn1.player.fm/images/1027679/series/n237MsJ0HGRntqQU/256.png", "las_updated": "2018-11-22T02:07:53Z", "author": "me", "is_subscribed": false, "subscribers_count": 0, "genres": "culture"}}, {"context": "NEW_SUBSCRIBED_EPISODE", "id": 78694591, "time": "2018-11-22T00:07:54Z", "content": {"id": "613612162316", "title": "21.November 2018 - \u062f\u06a9\u062a\u0631 \u0647\u0644\u0627\u06a9\u0648\u0626\u06cc \u0647\u0645\u0631\u0627\u0647 \u0628\u0627 \u0639\u0644\u06cc\u0631\u0636\u0627 \u0645\u06cc\u0628\u062f\u06cc", "pub_date": "2018-11-22T00:07:54Z", "summary": "21.November 2018 - \u062f\u06a9\u062a\u0631 \u0647\u0644\u0627\u06a9\u0648\u0626\u06cc \u0647\u0645\u0631\u0627\u0647 \u0628\u0627 \u0639\u0644\u06cc\u0631\u0636\u0627 \u0645\u06cc\u0628\u062f\u06cc", "is_recommended": false, "recommendations_count": 0, "series": {"title": "Razha va Niazha", "id": 54230894, "image_url_sm": "https://cdn1.player.fm/images/1027679/series/n237MsJ0HGRntqQU/64.png", "image_url_lg": "https://cdn1.player.fm/images/1027679/series/n237MsJ0HGRntqQU/256.png"}, "duration": "1:58:56", "tags": "", "audio_url": "http://feeds.soundcloud.com/stream/533658543-razhavaniazha-com-21-11-2018-h-m.mp3", "current_progress": 0.0, "real_duration_written": false}, "context_supplier": {"id": 54230894, "title": "Razha va Niazha", "image_url_sm": "https://cdn1.player.fm/images/1027679/series/n237MsJ0HGRntqQU/64.png", "image_url_lg": "https://cdn1.player.fm/images/1027679/series/n237MsJ0HGRntqQU/256.png", "las_updated": "2018-11-22T00:07:54Z", "author": "me", "is_subscribed": false, "subscribers_count": 0, "genres": "culture"}}, {"context": "NEW_SUBSCRIBED_EPISODE", "id": 39248767, "time": "2018-11-21T20:08:00Z", "content": {"id": "455689386454", "title": "21.November 2018 - \u062f\u06a9\u062a\u0631 \u0647\u0644\u0627\u06a9\u0648\u06cc\u06cc , \u0631\u0627\u0632\u0647\u0627 \u0648 \u0646\u06cc\u0627\u0632\u0647\u0627, \u0635\u0628\u062d", "pub_date": "2018-11-21T20:08:00Z", "summary": "21.November 2018 - \u062f\u06a9\u062a\u0631 \u0647\u0644\u0627\u06a9\u0648\u06cc\u06cc , \u0631\u0627\u0632\u0647\u0627 \u0648 \u0646\u06cc\u0627\u0632\u0647\u0627, \u0635\u0628\u062d", "is_recommended": false, "recommendations_count": 0, "series": {"title": "Razha va Niazha", "id": 54230894, "image_url_sm": "https://cdn1.player.fm/images/1027679/series/n237MsJ0HGRntqQU/64.png", "image_url_lg": "https://cdn1.player.fm/images/1027679/series/n237MsJ0HGRntqQU/256.png"}, "duration": "1:59:06", "tags": "", "audio_url": "http://feeds.soundcloud.com/stream/533550516-razhavaniazha-com-21-11-2018-r-m.mp3", "current_progress": 0.0, "real_duration_written": false}, "context_supplier": {"id": 54230894, "title": "Razha va Niazha", "image_url_sm": "https://cdn1.player.fm/images/1027679/series/n237MsJ0HGRntqQU/64.png", "image_url_lg": "https://cdn1.player.fm/images/1027679/series/n237MsJ0HGRntqQU/256.png", "las_updated": "2018-11-21T20:08:00Z", "author": "me", "is_subscribed": false, "subscribers_count": 0, "genres": "culture"}}, {"context": "NEW_SUBSCRIBED_EPISODE", "id": 78884212, "time": "2018-11-21T03:46:00Z", "content": {"id": "475657214599", "title": "Toranj-21-11-2018 Steps To Buying A House: Part 4", "pub_date": "2018-11-21T03:46:00Z", "summary": "Toranj-21-11-2018 Steps To Buying A House: Part 4", "is_recommended": false, "recommendations_count": 0, "series": {"title": "Toranj", "id": 2447873, "image_url_sm": "https://cdn1.player.fm/images/16403860/series/eGg5OFKoNQoVZSLO/64.png", "image_url_lg": "https://cdn1.player.fm/images/16403860/series/eGg5OFKoNQoVZSLO/256.png"}, "duration": "24:36", "tags": "", "audio_url": "https://cdn.accessradio.org/StationFolder/plainsfm/Toranj%2021st%20Nov.mp3", "current_progress": 0.0, "real_duration_written": false}, "context_supplier": {"id": 2447873, "title": "Toranj", "image_url_sm": "https://cdn1.player.fm/images/16403860/series/eGg5OFKoNQoVZSLO/64.png", "image_url_lg": "https://cdn1.player.fm/images/16403860/series/eGg5OFKoNQoVZSLO/256.png", "las_updated": "2018-11-21T03:46:00Z", "author": "me", "is_subscribed": false, "subscribers_count": 0, "genres": "culture"}}, {"context": "NEW_SUBSCRIBED_EPISODE", "id": 8067492, "time": "2018-11-21T02:07:53Z", "content": {"id": "677655346901", "title": "20.November 2018 - \u062f\u06a9\u062a\u0631 \u0647\u0644\u0627\u06a9\u0648\u06cc\u06cc , \u0631\u0627\u0632\u0647\u0627 \u0648 \u0646\u06cc\u0627\u0632\u0647\u0627, \u0639\u0635\u0631", "pub_date": "2018-11-21T02:07:53Z", "summary": "20.November 2018 - \u062f\u06a9\u062a\u0631 \u0647\u0644\u0627\u06a9\u0648\u06cc\u06cc , \u0631\u0627\u0632\u0647\u0627 \u0648 \u0646\u06cc\u0627\u0632\u0647\u0627, \u0639\u0635\u0631", "is_recommended": false, "recommendations_count": 0, "series": {"title": "Razha va Niazha", "id": 54230894, "image_url_sm": "https://cdn1.player.fm/images/1027679/series/n237MsJ0HGRntqQU/64.png", "image_url_lg": "https://cdn1.player.fm/images/1027679/series/n237MsJ0HGRntqQU/256.png"}, "duration": "1:59:06", "tags": "", "audio_url": "http://feeds.soundcloud.com/stream/533187156-razhavaniazha-com-20-11-2018-r-e.mp3", "current_progress": 0.0, "real_duration_written": false}, "context_supplier": {"id": 54230894, "title": "Razha va Niazha", "image_url_sm": "https://cdn1.player.fm/images/1027679/series/n237MsJ0HGRntqQU/64.png", "image_url_lg": "https://cdn1.player.fm/images/1027679/series/n237MsJ0HGRntqQU/256.png", "las_updated": "2018-11-21T02:07:53Z", "author": "me", "is_subscribed": false, "subscribers_count": 0, "genres": "culture"}}, {"context": "NEW_SUBSCRIBED_EPISODE", "id": 13309831, "time": "2018-11-20T20:07:54Z", "content": {"id": "826564476049", "title": "20.November 2018 - \u062f\u06a9\u062a\u0631 \u0647\u0644\u0627\u06a9\u0648\u06cc\u06cc , \u0631\u0627\u0632\u0647\u0627 \u0648 \u0646\u06cc\u0627\u0632\u0647\u0627, \u0635\u0628\u062d", "pub_date": "2018-11-20T20:07:54Z", "summary": "20.November 2018 - \u062f\u06a9\u062a\u0631 \u0647\u0644\u0627\u06a9\u0648\u06cc\u06cc , \u0631\u0627\u0632\u0647\u0627 \u0648 \u0646\u06cc\u0627\u0632\u0647\u0627, \u0635\u0628\u062d", "is_recommended": false, "recommendations_count": 0, "series": {"title": "Razha va Niazha", "id": 54230894, "image_url_sm": "https://cdn1.player.fm/images/1027679/series/n237MsJ0HGRntqQU/64.png", "image_url_lg": "https://cdn1.player.fm/images/1027679/series/n237MsJ0HGRntqQU/256.png"}, "duration": "1:59:06", "tags": "", "audio_url": "http://feeds.soundcloud.com/stream/533036784-razhavaniazha-com-20-11-2018-r-m.mp3", "current_progress": 0.0, "real_duration_written": false}, "context_supplier": {"id": 54230894, "title": "Razha va Niazha", "image_url_sm": "https://cdn1.player.fm/images/1027679/series/n237MsJ0HGRntqQU/64.png", "image_url_lg": "https://cdn1.player.fm/images/1027679/series/n237MsJ0HGRntqQU/256.png", "las_updated": "2018-11-20T20:07:54Z", "author": "me", "is_subscribed": false, "subscribers_count": 0, "genres": "culture"}}, {"context": "NEW_SUBSCRIBED_EPISODE", "id": 48148722, "time": "2018-11-20T05:00:00Z", "content": {"id": "271731868277", "title": "Traffik (Episode 41)", "pub_date": "2018-11-20T05:00:00Z", "summary": "Traffik (Episode 41)", "is_recommended": false, "recommendations_count": 0, "series": {"title": "Radio Javan Podcasts", "id": 24583351, "image_url_sm": "https://cdn1.player.fm/images/2210354/series/CP2HKKvW3oif9lC1/64.jpg", "image_url_lg": "https://cdn1.player.fm/images/2210354/series/CP2HKKvW3oif9lC1/256.jpg"}, "duration": "", "tags": "", "audio_url": "https://host2.rjmusicmedia.com/media/podcast/mp3-192/Traffik-41.mp3", "current_progress": 0.0, "real_duration_written": false}, "context_supplier": {"id": 24583351, "title": "Radio Javan Podcasts", "image_url_sm": "https://cdn1.player.fm/images/2210354/series/CP2HKKvW3oif9lC1/64.jpg", "image_url_lg": "https://cdn1.player.fm/images/2210354/series/CP2HKKvW3oif9lC1/256.jpg", "las_updated": "2018-11-20T05:00:00Z", "author": "me", "is_subscribed": false, "subscribers_count": 0, "genres": "culture"}}]